Workbook

Sheet summary
A2: Table 1: Breakdown by status of submission
A3: Status of Submission | B3: Number of firms | C3: Number of firms -investment schemes
A4: No records | B4: =SUMIFS('2.masterfirm'!E:E,'2.masterfirm'!$G:$G,$A4) -> 68 | C4: =SUMIFS('2.masterfirm'!F:F,'2.masterfirm'!$G:$G,$A4) -> 69
A5: Have records but not submitted | B5: =SUMIFS('2.masterfirm'!E:E,'2.masterfirm'!$G:$G,$A5) -> 62 | C5: =SUMIFS('2.masterfirm'!F:F,'2.masterfirm'!$G:$G,$A5) -> 159
A6: Have records and have submitted | B6: =SUMIFS('2.masterfirm'!E:E,'2.masterfirm'!$G:$G,$A6) -> 30 | C6: =SUMIFS('2.masterfirm'!F:F,'2.masterfirm'!$G:$G,$A6) -> 30
A7: Total | B7: =SUM(B4:B6) -> 160 | C7: =SUM(C4:C6) -> 258
A10: Status of Submission | B10: Number of firms | C10: Number of firms -investment schemes
A11: No records | B11: =B4/B$7 -> 0.425 | C11: =C4/C$7 -> 0.26744186
A12: Have records but not submitted | B12: =B5/B$7 -> 0.3875 | C12: =C5/C$7 -> 0.61627907
A13: Have records and have submitted | B13: =B6/B$7 -> 0.1875 | C13: =C6/C$7 -> 0.11627907
A14: Total | B14: =SUM(B11:B13) -> 1 | C14: =SUM(C11:C13) -> 1
A17: Table 2: Breakdown by industry
A18: Sector | B18: Industry | C18: Number of unreported firms | D18: Number of reported firms | E18: Number of firms | F18: %
A19: Financial Sector | B19: Australian/NZ Bank | C19: =E19-D19 -> 8 | D19: =SUMIFS('2.masterfirm'!E:E,'2.masterfirm'!C:C,summary!B19,'2.masterfirm'!G:G,summary!$A$13) -> 2 | E19: =SUMIFS('2.masterfirm'!E:E,'2.masterfirm'!C:C,summary!B19) -> 10 | F19: =D19/E19 -> 0.2
B20: Foreign Bank | C20: =E20-D20 -> 3 | D20: =SUMIFS('2.masterfirm'!E:E,'2.masterfirm'!C:C,summary!B20,'2.masterfirm'!G:G,summary!$A$13) -> 7 | E20: =SUMIFS('2.masterfirm'!E:E,'2.masterfirm'!C:C,summary!B20) -> 10 | F20: =D20/E20 -> 0.7
B21: Finance/investment | C21: =E21-D21 -> 39 | D21: =SUMIFS('2.masterfirm'!E:E,'2.masterfirm'!C:C,summary!B21,'2.masterfirm'!G:G,summary!$A$13) -> 3 | E21: =SUMIFS('2.masterfirm'!E:E,'2.masterfirm'!C:C,summary!B21) -> 42 | F21: =D21/E21 -> 0.071428571
B22: Insurance | C22: =E22-D22 -> 12 | D22: =SUMIFS('2.masterfirm'!E:E,'2.masterfirm'!C:C,summary!B22,'2.masterfirm'!G:G,summary!$A$13) -> 4 | E22: =SUMIFS('2.masterfirm'!E:E,'2.masterfirm'!C:C,summary!B22) -> 16 | F22: =D22/E22 -> 0.25
A23: Real Estate | B23: Property | C23: =E23-D23 -> 9 | D23: =SUMIFS('2.masterfirm'!E:E,'2.masterfirm'!C:C,summary!B23,'2.masterfirm'!G:G,summary!$A$13) -> 2 | E23: =SUMIFS('2.masterfirm'!E:E,'2.masterfirm'!C:C,summary!B23) -> 11 | F23: =D23/E23 -> 0.18181818
B24: Building | C24: =E24-D24 -> 3 | D24: =SUMIFS('2.masterfirm'!E:E,'2.masterfirm'!C:C,summary!B24,'2.masterfirm'!G:G,summary!$A$13) -> 0 | E24: =SUMIFS('2.masterfirm'!E:E,'2.masterfirm'!C:C,summary!B24) -> 3 | F24: =D24/E24 -> 0
B25: Age Care | C25: =E25-D25 -> 2 | D25: =SUMIFS('2.masterfirm'!E:E,'2.masterfirm'!C:C,summary!B25,'2.masterfirm'!G:G,summary!$A$13) -> 1 | E25: =SUMIFS('2.masterfirm'!E:E,'2.masterfirm'!C:C,summary!B25) -> 3 | F25: =D25/E25 -> 0.33333333
A26: Energy | B26: Energy | C26: =E26-D26 -> 8 | D26: =SUMIFS('2.masterfirm'!E:E,'2.masterfirm'!C:C,summary!B26,'2.masterfirm'!G:G,summary!$A$13) -> 1 | E26: =SUMIFS('2.masterfirm'!E:E,'2.masterfirm'!C:C,summary!B26) -> 9 | F26: =D26/E26 -> 0.11111111
A27: Agricuture | B27: Food/Agriculture | C27: =E27-D27 -> 9 | D27: =SUMIFS('2.masterfirm'!E:E,'2.masterfirm'!C:C,summary!B27,'2.masterfirm'!G:G,summary!$A$13) -> 3 | E27: =SUMIFS('2.masterfirm'!E:E,'2.masterfirm'!C:C,summary!B27) -> 12 | F27: =D27/E27 -> 0.25
A28: Industry | B28: Consumer | C28: =E28-D28 -> 1 | D28: =SUMIFS('2.masterfirm'!E:E,'2.masterfirm'!C:C,summary!B28,'2.masterfirm'!G:G,summary!$A$13) -> 1 | E28: =SUMIFS('2.masterfirm'!E:E,'2.masterfirm'!C:C,summary!B28) -> 2 | F28: =D28/E28 -> 0.5
B29: Hotel/Restaurant/Tourism | C29: =E29-D29 -> 1 | D29: =SUMIFS('2.masterfirm'!E:E,'2.masterfirm'!C:C,summary!B29,'2.masterfirm'!G:G,summary!$A$13) -> 2 | E29: =SUMIFS('2.masterfirm'!E:E,'2.masterfirm'!C:C,summary!B29) -> 3 | F29: =D29/E29 -> 0.66666667
B30: Airport/infrastructure | C30: =E30-D30 -> 7 | D30: =SUMIFS('2.masterfirm'!E:E,'2.masterfirm'!C:C,summary!B30,'2.masterfirm'!G:G,summary!$A$13) -> 2 | E30: =SUMIFS('2.masterfirm'!E:E,'2.masterfirm'!C:C,summary!B30) -> 9 | F30: =D30/E30 -> 0.22222222
B31: Transportation | C31: =E31-D31 -> 6 | D31: =SUMIFS('2.masterfirm'!E:E,'2.masterfirm'!C:C,summary!B31,'2.masterfirm'!G:G,summary!$A$13) -> 0 | E31: =SUMIFS('2.masterfirm'!E:E,'2.masterfirm'!C:C,summary!B31) -> 6 | F31: =D31/E31 -> 0
B32: Government | C32: =E32-D32 -> 2 | D32: =SUMIFS('2.masterfirm'!E:E,'2.masterfirm'!C:C,summary!B32,'2.masterfirm'!G:G,summary!$A$13) -> 0 | E32: =SUMIFS('2.masterfirm'!E:E,'2.masterfirm'!C:C,summary!B32) -> 2 | F32: =D32/E32 -> 0
B33: Manufacturing | C33: =E33-D33 -> 5 | D33: =SUMIFS('2.masterfirm'!E:E,'2.masterfirm'!C:C,summary!B33,'2.masterfirm'!G:G,summary!$A$13) -> 0 | E33: =SUMIFS('2.masterfirm'!E:E,'2.masterfirm'!C:C,summary!B33) -> 5 | F33: =D33/E33 -> 0
B34: Healthcare | C34: =E34-D34 -> 6 | D34: =SUMIFS('2.masterfirm'!E:E,'2.masterfirm'!C:C,summary!B34,'2.masterfirm'!G:G,summary!$A$13) -> 0 | E34: =SUMIFS('2.masterfirm'!E:E,'2.masterfirm'!C:C,summary!B34) -> 6 | F34: =D34/E34 -> 0
A35: IT | B35: Technology | C35: =E35-D35 -> 5 | D35: =SUMIFS('2.masterfirm'!E:E,'2.masterfirm'!C:C,summary!B35,'2.masterfirm'!G:G,summary!$A$13) -> 2 | E35: =SUMIFS('2.masterfirm'!E:E,'2.masterfirm'!C:C,summary!B35) -> 7 | F35: =D35/E35 -> 0.28571429
B36: Telecommunications | C36: =E36-D36 -> 4 | D36: =SUMIFS('2.masterfirm'!E:E,'2.masterfirm'!C:C,summary!B36,'2.masterfirm'!G:G,summary!$A$13) -> 0 | E36: =SUMIFS('2.masterfirm'!E:E,'2.masterfirm'!C:C,summary!B36) -> 4 | F36: =D36/E36 -> 0
C37: =SUM(C19:C36) -> 130 | D37: =SUM(D19:D36) -> 30 | E37: =SUM(E19:E36) -> 160 | F37: =D37/E37 -> 0.1875
A40: Table 3: Breakdown by sector
A41: Industry | B41: Industry | C41: Number of unreported firms | D41: Number of reported firms | E41: Number of firms | F41: %
A42: Financial Sector | B42: =A42 -> Financial Sector | C42: =SUM(C19:C22) -> 62 | D42: =SUM(D19:D22) -> 16 | E42: =SUM(E19:E22) -> 78 | F42: =D42/E42 -> 0.20512821
A43: Real Estate | B43: =A43 -> Real Estate | C43: =E43-D43 -> 0 | D43: =SUMIFS('2.masterfirm'!E:E,'2.masterfirm'!C:C,summary!B43,'2.masterfirm'!G:G,summary!$A$13) -> 0 | E43: =SUMIFS('2.masterfirm'!E:E,'2.masterfirm'!C:C,summary!B43) -> 0 | F43: =D43/E43 -> #DIV/0!
A44: Energy | B44: =A44 -> Energy | C44: =C26 -> 8 | D44: =D26 -> 1 | E44: =E26 -> 9 | F44: =D44/E44 -> 0.11111111
A45: Agricuture | B45: =A45 -> Agricuture | C45: =C27 -> 9 | D45: =D27 -> 3 | E45: =E27 -> 12 | F45: =D45/E45 -> 0.25
A46: Industry | B46: =A46 -> Industry | C46: =SUM(C28:C33) -> 22 | D46: =SUM(D28:D33) -> 5 | E46: =SUM(E28:E33) -> 27 | F46: =D46/E46 -> 0.18518519
A47: Telecommunication & Technology & Healthcare | B47: Telecommunication & Technology & Healthcare | C47: =SUM(C35:C36) -> 9 | D47: =SUM(D35:D36) -> 2 | E47: =SUM(E35:E36) -> 11 | F47: =D47/E47 -> 0.18181818
A62: Table 3: Climate Statement
A63: This shows the comprensiveness
A64: Type | B64: Type | C64: Number of reports | D64: Average pages | E64: Average words | F64: Average words per page | G64: %
A65: Climate statement | B65: Have their own climate statement | C65: =COUNTIFS('3.simple_text_analysis'!$P:$P,summary!A65) -> 31 | D65: =SUMIFS('3.simple_text_analysis'!C:C,'3.simple_text_analysis'!$P:$P,summary!$A65)/C65 -> 21.709677 | E65: =SUMIFS('3.simple_text_analysis'!D:D,'3.simple_text_analysis'!$P:$P,summary!$A65)/C65 -> 59723.903 | F65: =IFERROR(E65/D65,"") -> 2751.0267 | G65: =C65/C$68 -> 0.83783784
A66: Annual report | B66: Included in annual report | C66: =COUNTIFS('3.simple_text_analysis'!$P:$P,summary!A66) -> 3 | D66: =SUMIFS('3.simple_text_analysis'!C:C,'3.simple_text_analysis'!$P:$P,summary!$A66)/C66 -> 131.33333 | E66: =SUMIFS('3.simple_text_analysis'!D:D,'3.simple_text_analysis'!$P:$P,summary!$A66)/C66 -> 325870.67 | F66: =IFERROR(E66/D66,"") -> 2481.2487 | G66: =C66/C$68 -> 0.081081081
A67: sustainability report | B67: Included in sustainability report | C67: =COUNTIFS('3.simple_text_analysis'!$P:$P,summary!A67) -> 3 | D67: =SUMIFS('3.simple_text_analysis'!C:C,'3.simple_text_analysis'!$P:$P,summary!$A67)/C67 -> 78.666667 | E67: =SUMIFS('3.simple_text_analysis'!D:D,'3.simple_text_analysis'!$P:$P,summary!$A67)/C67 -> 162814.33 | F67: =IFERROR(E67/D67,"") -> 2069.6737 | G67: =C67/C$68 -> 0.081081081
B68: Total | C68: =SUM(C65:C67) -> 37 | G68: =C68/C$68 -> 1
A88: Table 3: Comprehensiveness
A89: This shows the comprensiveness
A90: Sector | B90: Industry | C90: Number of reports | D90: Average pages | E90: Average words | F90: Average words per page
A91: Financial Sector | B91: Australian/Nz Bank | C91: =COUNTIFS('3.simple_text_analysis'!$M:$M,summary!B91,'3.simple_text_analysis'!$P:$P,$A$65) -> 5 | D91: =IFERROR(SUMIFS('3.simple_text_analysis'!C:C,'3.simple_text_analysis'!$M:$M,$B91,'3.simple_text_analysis'!$P:$P,$A$65)/C91,"--") -> 9 | E91: =IFERROR(SUMIFS('3.simple_text_analysis'!D:D,'3.simple_text_analysis'!$M:$M,$B91,'3.simple_text_analysis'!$P:$P,$A$65)/C91,"--") -> 34376.6 | F91: =IFERROR(E91/D91,"") -> 3819.6222
B92: Foreign Bank | C92: =COUNTIFS('3.simple_text_analysis'!$M:$M,summary!B92,'3.simple_text_analysis'!$P:$P,$A$65) -> 9 | D92: =IFERROR(SUMIFS('3.simple_text_analysis'!C:C,'3.simple_text_analysis'!$M:$M,$B92,'3.simple_text_analysis'!$P:$P,$A$65)/C92,"--") -> 19.111111 | E92: =IFERROR(SUMIFS('3.simple_text_analysis'!D:D,'3.simple_text_analysis'!$M:$M,$B92,'3.simple_text_analysis'!$P:$P,$A$65)/C92,"--") -> 43623.556 | F92: =IFERROR(E92/D92,"") -> 2282.6279
B93: Finance | C93: =COUNTIFS('3.simple_text_analysis'!$M:$M,summary!B93,'3.simple_text_analysis'!$P:$P,$A$65) -> 0 | D93: =IFERROR(SUMIFS('3.simple_text_analysis'!C:C,'3.simple_text_analysis'!$M:$M,$B93,'3.simple_text_analysis'!$P:$P,$A$65)/C93,"--") -> -- | E93: =IFERROR(SUMIFS('3.simple_text_analysis'!D:D,'3.simple_text_analysis'!$M:$M,$B93,'3.simple_text_analysis'!$P:$P,$A$65)/C93,"--") -> -- | F93: =IFERROR(E93/D93,"")
B94: Insurance | C94: =COUNTIFS('3.simple_text_analysis'!$M:$M,summary!B94,'3.simple_text_analysis'!$P:$P,$A$65) -> 4 | D94: =IFERROR(SUMIFS('3.simple_text_analysis'!C:C,'3.simple_text_analysis'!$M:$M,$B94,'3.simple_text_analysis'!$P:$P,$A$65)/C94,"--") -> 21.5 | E94: =IFERROR(SUMIFS('3.simple_text_analysis'!D:D,'3.simple_text_analysis'!$M:$M,$B94,'3.simple_text_analysis'!$P:$P,$A$65)/C94,"--") -> 45337 | F94: =IFERROR(E94/D94,"") -> 2108.6977
B95: Investment | C95: =COUNTIFS('3.simple_text_analysis'!$M:$M,summary!B95,'3.simple_text_analysis'!$P:$P,$A$65) -> 0 | D95: =IFERROR(SUMIFS('3.simple_text_analysis'!C:C,'3.simple_text_analysis'!$M:$M,$B95,'3.simple_text_analysis'!$P:$P,$A$65)/C95,"--") -> -- | E95: =IFERROR(SUMIFS('3.simple_text_analysis'!D:D,'3.simple_text_analysis'!$M:$M,$B95,'3.simple_text_analysis'!$P:$P,$A$65)/C95,"--") -> -- | F95: =IFERROR(E95/D95,"")
A96: Real Estate | B96: Real Estate | C96: =COUNTIFS('3.simple_text_analysis'!$M:$M,summary!B96,'3.simple_text_analysis'!$P:$P,$A$65) -> 0 | D96: =IFERROR(SUMIFS('3.simple_text_analysis'!C:C,'3.simple_text_analysis'!$M:$M,$B96,'3.simple_text_analysis'!$P:$P,$A$65)/C96,"--") -> -- | E96: =IFERROR(SUMIFS('3.simple_text_analysis'!D:D,'3.simple_text_analysis'!$M:$M,$B96,'3.simple_text_analysis'!$P:$P,$A$65)/C96,"--") -> -- | F96: =IFERROR(E96/D96,"")
A97: Energy | B97: Energy | C97: =COUNTIFS('3.simple_text_analysis'!$M:$M,summary!B97,'3.simple_text_analysis'!$P:$P,$A$65) -> 1 | D97: =IFERROR(SUMIFS('3.simple_text_analysis'!C:C,'3.simple_text_analysis'!$M:$M,$B97,'3.simple_text_analysis'!$P:$P,$A$65)/C97,"--") -> 25 | E97: =IFERROR(SUMIFS('3.simple_text_analysis'!D:D,'3.simple_text_analysis'!$M:$M,$B97,'3.simple_text_analysis'!$P:$P,$A$65)/C97,"--") -> 126445 | F97: =IFERROR(E97/D97,"") -> 5057.8
A98: Agricuture | B98: Food/Agriculture | C98: =COUNTIFS('3.simple_text_analysis'!$M:$M,summary!B98,'3.simple_text_analysis'!$P:$P,$A$65) -> 2 | D98: =IFERROR(SUMIFS('3.simple_text_analysis'!C:C,'3.simple_text_analysis'!$M:$M,$B98,'3.simple_text_analysis'!$P:$P,$A$65)/C98,"--") -> 23 | E98: =IFERROR(SUMIFS('3.simple_text_analysis'!D:D,'3.simple_text_analysis'!$M:$M,$B98,'3.simple_text_analysis'!$P:$P,$A$65)/C98,"--") -> 68853.5 | F98: =IFERROR(E98/D98,"") -> 2993.6304
A99: Industry | B99: Consumer | C99: =COUNTIFS('3.simple_text_analysis'!$M:$M,summary!B99,'3.simple_text_analysis'!$P:$P,$A$65) -> 0 | D99: =IFERROR(SUMIFS('3.simple_text_analysis'!C:C,'3.simple_text_analysis'!$M:$M,$B99,'3.simple_text_analysis'!$P:$P,$A$65)/C99,"--") -> -- | E99: =IFERROR(SUMIFS('3.simple_text_analysis'!D:D,'3.simple_text_analysis'!$M:$M,$B99,'3.simple_text_analysis'!$P:$P,$A$65)/C99,"--") -> -- | F99: =IFERROR(E99/D99,"")
B100: Hotel/Restaurant/Tourism | C100: =COUNTIFS('3.simple_text_analysis'!$M:$M,summary!B100,'3.simple_text_analysis'!$P:$P,$A$65) -> 2 | D100: =IFERROR(SUMIFS('3.simple_text_analysis'!C:C,'3.simple_text_analysis'!$M:$M,$B100,'3.simple_text_analysis'!$P:$P,$A$65)/C100,"--") -> 23 | E100: =IFERROR(SUMIFS('3.simple_text_analysis'!D:D,'3.simple_text_analysis'!$M:$M,$B100,'3.simple_text_analysis'!$P:$P,$A$65)/C100,"--") -> 51626 | F100: =IFERROR(E100/D100,"") -> 2244.6087
B101: Airport/infrastructure | C101: =COUNTIFS('3.simple_text_analysis'!$M:$M,summary!B101,'3.simple_text_analysis'!$P:$P,$A$65) -> 0 | D101: =IFERROR(SUMIFS('3.simple_text_analysis'!C:C,'3.simple_text_analysis'!$M:$M,$B101,'3.simple_text_analysis'!$P:$P,$A$65)/C101,"--") -> -- | E101: =IFERROR(SUMIFS('3.simple_text_analysis'!D:D,'3.simple_text_analysis'!$M:$M,$B101,'3.simple_text_analysis'!$P:$P,$A$65)/C101,"--") -> -- | F101: =IFERROR(E101/D101,"")
B102: Transportation | C102: =COUNTIFS('3.simple_text_analysis'!$M:$M,summary!B102,'3.simple_text_analysis'!$P:$P,$A$65) -> 0 | D102: =IFERROR(SUMIFS('3.simple_text_analysis'!C:C,'3.simple_text_analysis'!$M:$M,$B102,'3.simple_text_analysis'!$P:$P,$A$65)/C102,"--") -> -- | E102: =IFERROR(SUMIFS('3.simple_text_analysis'!D:D,'3.simple_text_analysis'!$M:$M,$B102,'3.simple_text_analysis'!$P:$P,$A$65)/C102,"--") -> -- | F102: =IFERROR(E102/D102,"")
B103: Government | C103: =COUNTIFS('3.simple_text_analysis'!$M:$M,summary!B103,'3.simple_text_analysis'!$P:$P,$A$65) -> 0 | D103: =IFERROR(SUMIFS('3.simple_text_analysis'!C:C,'3.simple_text_analysis'!$M:$M,$B103,'3.simple_text_analysis'!$P:$P,$A$65)/C103,"--") -> -- | E103: =IFERROR(SUMIFS('3.simple_text_analysis'!D:D,'3.simple_text_analysis'!$M:$M,$B103,'3.simple_text_analysis'!$P:$P,$A$65)/C103,"--") -> -- | F103: =IFERROR(E103/D103,"")
B104: Manufacturing | C104: =COUNTIFS('3.simple_text_analysis'!$M:$M,summary!B104,'3.simple_text_analysis'!$P:$P,$A$65) -> 1 | D104: =IFERROR(SUMIFS('3.simple_text_analysis'!C:C,'3.simple_text_analysis'!$M:$M,$B104,'3.simple_text_analysis'!$P:$P,$A$65)/C104,"--") -> 23 | E104: =IFERROR(SUMIFS('3.simple_text_analysis'!D:D,'3.simple_text_analysis'!$M:$M,$B104,'3.simple_text_analysis'!$P:$P,$A$65)/C104,"--") -> 70344 | F104: =IFERROR(E104/D104,"") -> 3058.4348
A105: Telecommunication & Technology | B105: Technology | C105: =COUNTIFS('3.simple_text_analysis'!$M:$M,summary!B105,'3.simple_text_analysis'!$P:$P,$A$65) -> 1 | D105: =IFERROR(SUMIFS('3.simple_text_analysis'!C:C,'3.simple_text_analysis'!$M:$M,$B105,'3.simple_text_analysis'!$P:$P,$A$65)/C105,"--") -> 31 | E105: =IFERROR(SUMIFS('3.simple_text_analysis'!D:D,'3.simple_text_analysis'!$M:$M,$B105,'3.simple_text_analysis'!$P:$P,$A$65)/C105,"--") -> 59162 | F105: =IFERROR(E105/D105,"") -> 1908.4516
B106: Telecommunications | C106: =COUNTIFS('3.simple_text_analysis'!$M:$M,summary!B106,'3.simple_text_analysis'!$P:$P,$A$65) -> 0 | D106: =IFERROR(SUMIFS('3.simple_text_analysis'!C:C,'3.simple_text_analysis'!$M:$M,$B106,'3.simple_text_analysis'!$P:$P,$A$65)/C106,"--") -> -- | E106: =IFERROR(SUMIFS('3.simple_text_analysis'!D:D,'3.simple_text_analysis'!$M:$M,$B106,'3.simple_text_analysis'!$P:$P,$A$65)/C106,"--") -> -- | F106: =IFERROR(E106/D106,"")
B107: Healthcare | C107: =COUNTIFS('3.simple_text_analysis'!$M:$M,summary!B107,'3.simple_text_analysis'!$P:$P,$A$65) -> 0 | D107: =IFERROR(SUMIFS('3.simple_text_analysis'!C:C,'3.simple_text_analysis'!$M:$M,$B107,'3.simple_text_analysis'!$P:$P,$A$65)/C107,"--") -> -- | E107: =IFERROR(SUMIFS('3.simple_text_analysis'!D:D,'3.simple_text_analysis'!$M:$M,$B107,'3.simple_text_analysis'!$P:$P,$A$65)/C107,"--") -> -- | F107: =IFERROR(E107/D107,"")
B108: Grand Total | C108: =SUM(C91:C107) -> 25 | D108: =IFERROR(SUMIFS('3.simple_text_analysis'!C:C,'3.simple_text_analysis'!$P:$P,$A$65)/C108,"--") -> 26.92 | E108: =IFERROR(SUMIFS('3.simple_text_analysis'!D:D,'3.simple_text_analysis'!$P:$P,$A$65)/C108,"--") -> 74057.64 | F108: =IFERROR(E108/D108,"") -> 2751.0267
A111: Table 4: Sentiment Analysis
A112: This shows the comprensiveness
A113: Sector | B113: Industry | C113: Negative | D113: Neutral | E113: Positive | F113: Compound
A114: Financial Sector | B114: Australian/Nz Bank | C114: =IFERROR(SUMIFS('3.simple_text_analysis'!F:F,'3.simple_text_analysis'!$M:$M,summary!$B114,'3.simple_text_analysis'!$P:$P,$A$65)/$C91,"") -> 0.01 | D114: =IFERROR(SUMIFS('3.simple_text_analysis'!G:G,'3.simple_text_analysis'!$M:$M,summary!$B114,'3.simple_text_analysis'!$P:$P,$A$65)/$C91,"") -> 0.1688 | E114: =IFERROR(SUMIFS('3.simple_text_analysis'!H:H,'3.simple_text_analysis'!$M:$M,summary!$B114,'3.simple_text_analysis'!$P:$P,$A$65)/$C91,"") -> 0.0212 | F114: =IFERROR(SUMIFS('3.simple_text_analysis'!I:I,'3.simple_text_analysis'!$M:$M,summary!$B114,'3.simple_text_analysis'!$P:$P,$A$65)/$C91,"") -> 0.2
B115: Foreign Bank | C115: =IFERROR(SUMIFS('3.simple_text_analysis'!F:F,'3.simple_text_analysis'!$M:$M,summary!$B115,'3.simple_text_analysis'!$P:$P,$A$65)/$C92,"") -> 0.059555556 | D115: =IFERROR(SUMIFS('3.simple_text_analysis'!G:G,'3.simple_text_analysis'!$M:$M,summary!$B115,'3.simple_text_analysis'!$P:$P,$A$65)/$C92,"") -> 0.66544444 | E115: =IFERROR(SUMIFS('3.simple_text_analysis'!H:H,'3.simple_text_analysis'!$M:$M,summary!$B115,'3.simple_text_analysis'!$P:$P,$A$65)/$C92,"") -> 0.052888889 | F115: =IFERROR(SUMIFS('3.simple_text_analysis'!I:I,'3.simple_text_analysis'!$M:$M,summary!$B115,'3.simple_text_analysis'!$P:$P,$A$65)/$C92,"") -> -0.46496667
B116: Finance | C116: =IFERROR(SUMIFS('3.simple_text_analysis'!F:F,'3.simple_text_analysis'!$M:$M,summary!$B116,'3.simple_text_analysis'!$P:$P,$A$65)/$C93,"") | D116: =IFERROR(SUMIFS('3.simple_text_analysis'!G:G,'3.simple_text_analysis'!$M:$M,summary!$B116,'3.simple_text_analysis'!$P:$P,$A$65)/$C93,"") | E116: =IFERROR(SUMIFS('3.simple_text_analysis'!H:H,'3.simple_text_analysis'!$M:$M,summary!$B116,'3.simple_text_analysis'!$P:$P,$A$65)/$C93,"") | F116: =IFERROR(SUMIFS('3.simple_text_analysis'!I:I,'3.simple_text_analysis'!$M:$M,summary!$B116,'3.simple_text_analysis'!$P:$P,$A$65)/$C93,"")
B117: Insurance | C117: =IFERROR(SUMIFS('3.simple_text_analysis'!F:F,'3.simple_text_analysis'!$M:$M,summary!$B117,'3.simple_text_analysis'!$P:$P,$A$65)/$C94,"") -> 0.0485 | D117: =IFERROR(SUMIFS('3.simple_text_analysis'!G:G,'3.simple_text_analysis'!$M:$M,summary!$B117,'3.simple_text_analysis'!$P:$P,$A$65)/$C94,"") -> 0.8825 | E117: =IFERROR(SUMIFS('3.simple_text_analysis'!H:H,'3.simple_text_analysis'!$M:$M,summary!$B117,'3.simple_text_analysis'!$P:$P,$A$65)/$C94,"") -> 0.069 | F117: =IFERROR(SUMIFS('3.simple_text_analysis'!I:I,'3.simple_text_analysis'!$M:$M,summary!$B117,'3.simple_text_analysis'!$P:$P,$A$65)/$C94,"") -> 0.7497
B118: Investment | C118: =IFERROR(SUMIFS('3.simple_text_analysis'!F:F,'3.simple_text_analysis'!$M:$M,summary!$B118,'3.simple_text_analysis'!$P:$P,$A$65)/$C95,"") | D118: =IFERROR(SUMIFS('3.simple_text_analysis'!G:G,'3.simple_text_analysis'!$M:$M,summary!$B118,'3.simple_text_analysis'!$P:$P,$A$65)/$C95,"") | E118: =IFERROR(SUMIFS('3.simple_text_analysis'!H:H,'3.simple_text_analysis'!$M:$M,summary!$B118,'3.simple_text_analysis'!$P:$P,$A$65)/$C95,"") | F118: =IFERROR(SUMIFS('3.simple_text_analysis'!I:I,'3.simple_text_analysis'!$M:$M,summary!$B118,'3.simple_text_analysis'!$P:$P,$A$65)/$C95,"")
A119: Real Estate | B119: Real Estate | C119: =IFERROR(SUMIFS('3.simple_text_analysis'!F:F,'3.simple_text_analysis'!$M:$M,summary!$B119,'3.simple_text_analysis'!$P:$P,$A$65)/$C96,"") | D119: =IFERROR(SUMIFS('3.simple_text_analysis'!G:G,'3.simple_text_analysis'!$M:$M,summary!$B119,'3.simple_text_analysis'!$P:$P,$A$65)/$C96,"") | E119: =IFERROR(SUMIFS('3.simple_text_analysis'!H:H,'3.simple_text_analysis'!$M:$M,summary!$B119,'3.simple_text_analysis'!$P:$P,$A$65)/$C96,"") | F119: =IFERROR(SUMIFS('3.simple_text_analysis'!I:I,'3.simple_text_analysis'!$M:$M,summary!$B119,'3.simple_text_analysis'!$P:$P,$A$65)/$C96,"")
A120: Energy | B120: Energy | C120: =IFERROR(SUMIFS('3.simple_text_analysis'!F:F,'3.simple_text_analysis'!$M:$M,summary!$B120,'3.simple_text_analysis'!$P:$P,$A$65)/$C97,"") -> 0.071 | D120: =IFERROR(SUMIFS('3.simple_text_analysis'!G:G,'3.simple_text_analysis'!$M:$M,summary!$B120,'3.simple_text_analysis'!$P:$P,$A$65)/$C97,"") -> 0.81 | E120: =IFERROR(SUMIFS('3.simple_text_analysis'!H:H,'3.simple_text_analysis'!$M:$M,summary!$B120,'3.simple_text_analysis'!$P:$P,$A$65)/$C97,"") -> 0.119 | F120: =IFERROR(SUMIFS('3.simple_text_analysis'!I:I,'3.simple_text_analysis'!$M:$M,summary!$B120,'3.simple_text_analysis'!$P:$P,$A$65)/$C97,"") -> 1
A121: Agricuture | B121: Food/Agriculture | C121: =IFERROR(SUMIFS('3.simple_text_analysis'!F:F,'3.simple_text_analysis'!$M:$M,summary!$B121,'3.simple_text_analysis'!$P:$P,$A$65)/$C98,"") -> 0.0765 | D121: =IFERROR(SUMIFS('3.simple_text_analysis'!G:G,'3.simple_text_analysis'!$M:$M,summary!$B121,'3.simple_text_analysis'!$P:$P,$A$65)/$C98,"") -> 0.8455 | E121: =IFERROR(SUMIFS('3.simple_text_analysis'!H:H,'3.simple_text_analysis'!$M:$M,summary!$B121,'3.simple_text_analysis'!$P:$P,$A$65)/$C98,"") -> 0.0785 | F121: =IFERROR(SUMIFS('3.simple_text_analysis'!I:I,'3.simple_text_analysis'!$M:$M,summary!$B121,'3.simple_text_analysis'!$P:$P,$A$65)/$C98,"") -> 0.00065
A122: Industry | B122: Consumer | C122: =IFERROR(SUMIFS('3.simple_text_analysis'!F:F,'3.simple_text_analysis'!$M:$M,summary!$B122,'3.simple_text_analysis'!$P:$P,$A$65)/$C99,"") | D122: =IFERROR(SUMIFS('3.simple_text_analysis'!G:G,'3.simple_text_analysis'!$M:$M,summary!$B122,'3.simple_text_analysis'!$P:$P,$A$65)/$C99,"") | E122: =IFERROR(SUMIFS('3.simple_text_analysis'!H:H,'3.simple_text_analysis'!$M:$M,summary!$B122,'3.simple_text_analysis'!$P:$P,$A$65)/$C99,"") | F122: =IFERROR(SUMIFS('3.simple_text_analysis'!I:I,'3.simple_text_analysis'!$M:$M,summary!$B122,'3.simple_text_analysis'!$P:$P,$A$65)/$C99,"")
B123: Hotel/Restaurant/Tourism | C123: =IFERROR(SUMIFS('3.simple_text_analysis'!F:F,'3.simple_text_analysis'!$M:$M,summary!$B123,'3.simple_text_analysis'!$P:$P,$A$65)/$C100,"") -> 0.071 | D123: =IFERROR(SUMIFS('3.simple_text_analysis'!G:G,'3.simple_text_analysis'!$M:$M,summary!$B123,'3.simple_text_analysis'!$P:$P,$A$65)/$C100,"") -> 0.8465 | E123: =IFERROR(SUMIFS('3.simple_text_analysis'!H:H,'3.simple_text_analysis'!$M:$M,summary!$B123,'3.simple_text_analysis'!$P:$P,$A$65)/$C100,"") -> 0.0825 | F123: =IFERROR(SUMIFS('3.simple_text_analysis'!I:I,'3.simple_text_analysis'!$M:$M,summary!$B123,'3.simple_text_analysis'!$P:$P,$A$65)/$C100,"") -> 0.9959
B124: Airport/infrastructure | C124: =IFERROR(SUMIFS('3.simple_text_analysis'!F:F,'3.simple_text_analysis'!$M:$M,summary!$B124,'3.simple_text_analysis'!$P:$P,$A$65)/$C101,"") | D124: =IFERROR(SUMIFS('3.simple_text_analysis'!G:G,'3.simple_text_analysis'!$M:$M,summary!$B124,'3.simple_text_analysis'!$P:$P,$A$65)/$C101,"") | E124: =IFERROR(SUMIFS('3.simple_text_analysis'!H:H,'3.simple_text_analysis'!$M:$M,summary!$B124,'3.simple_text_analysis'!$P:$P,$A$65)/$C101,"") | F124: =IFERROR(SUMIFS('3.simple_text_analysis'!I:I,'3.simple_text_analysis'!$M:$M,summary!$B124,'3.simple_text_analysis'!$P:$P,$A$65)/$C101,"")
B125: Transportation | C125: =IFERROR(SUMIFS('3.simple_text_analysis'!F:F,'3.simple_text_analysis'!$M:$M,summary!$B125,'3.simple_text_analysis'!$P:$P,$A$65)/$C102,"") | D125: =IFERROR(SUMIFS('3.simple_text_analysis'!G:G,'3.simple_text_analysis'!$M:$M,summary!$B125,'3.simple_text_analysis'!$P:$P,$A$65)/$C102,"") | E125: =IFERROR(SUMIFS('3.simple_text_analysis'!H:H,'3.simple_text_analysis'!$M:$M,summary!$B125,'3.simple_text_analysis'!$P:$P,$A$65)/$C102,"") | F125: =IFERROR(SUMIFS('3.simple_text_analysis'!I:I,'3.simple_text_analysis'!$M:$M,summary!$B125,'3.simple_text_analysis'!$P:$P,$A$65)/$C102,"")
B126: Government | C126: =IFERROR(SUMIFS('3.simple_text_analysis'!F:F,'3.simple_text_analysis'!$M:$M,summary!$B126,'3.simple_text_analysis'!$P:$P,$A$65)/$C103,"") | D126: =IFERROR(SUMIFS('3.simple_text_analysis'!G:G,'3.simple_text_analysis'!$M:$M,summary!$B126,'3.simple_text_analysis'!$P:$P,$A$65)/$C103,"") | E126: =IFERROR(SUMIFS('3.simple_text_analysis'!H:H,'3.simple_text_analysis'!$M:$M,summary!$B126,'3.simple_text_analysis'!$P:$P,$A$65)/$C103,"") | F126: =IFERROR(SUMIFS('3.simple_text_analysis'!I:I,'3.simple_text_analysis'!$M:$M,summary!$B126,'3.simple_text_analysis'!$P:$P,$A$65)/$C103,"")
B127: Manufacturing | C127: =IFERROR(SUMIFS('3.simple_text_analysis'!F:F,'3.simple_text_analysis'!$M:$M,summary!$B127,'3.simple_text_analysis'!$P:$P,$A$65)/$C104,"") -> 0.064 | D127: =IFERROR(SUMIFS('3.simple_text_analysis'!G:G,'3.simple_text_analysis'!$M:$M,summary!$B127,'3.simple_text_analysis'!$P:$P,$A$65)/$C104,"") -> 0.798 | E127: =IFERROR(SUMIFS('3.simple_text_analysis'!H:H,'3.simple_text_analysis'!$M:$M,summary!$B127,'3.simple_text_analysis'!$P:$P,$A$65)/$C104,"") -> 0.138 | F127: =IFERROR(SUMIFS('3.simple_text_analysis'!I:I,'3.simple_text_analysis'!$M:$M,summary!$B127,'3.simple_text_analysis'!$P:$P,$A$65)/$C104,"") -> 1
A128: Telecommunication & Technology | B128: Technology | C128: =IFERROR(SUMIFS('3.simple_text_analysis'!F:F,'3.simple_text_analysis'!$M:$M,summary!$B128,'3.simple_text_analysis'!$P:$P,$A$65)/$C105,"") -> 0.065 | D128: =IFERROR(SUMIFS('3.simple_text_analysis'!G:G,'3.simple_text_analysis'!$M:$M,summary!$B128,'3.simple_text_analysis'!$P:$P,$A$65)/$C105,"") -> 0.845 | E128: =IFERROR(SUMIFS('3.simple_text_analysis'!H:H,'3.simple_text_analysis'!$M:$M,summary!$B128,'3.simple_text_analysis'!$P:$P,$A$65)/$C105,"") -> 0.09 | F128: =IFERROR(SUMIFS('3.simple_text_analysis'!I:I,'3.simple_text_analysis'!$M:$M,summary!$B128,'3.simple_text_analysis'!$P:$P,$A$65)/$C105,"") -> 0.9997
B129: Telecommunications | C129: =IFERROR(SUMIFS('3.simple_text_analysis'!F:F,'3.simple_text_analysis'!$M:$M,summary!$B129,'3.simple_text_analysis'!$P:$P,$A$65)/$C106,"") | D129: =IFERROR(SUMIFS('3.simple_text_analysis'!G:G,'3.simple_text_analysis'!$M:$M,summary!$B129,'3.simple_text_analysis'!$P:$P,$A$65)/$C106,"") | E129: =IFERROR(SUMIFS('3.simple_text_analysis'!H:H,'3.simple_text_analysis'!$M:$M,summary!$B129,'3.simple_text_analysis'!$P:$P,$A$65)/$C106,"") | F129: =IFERROR(SUMIFS('3.simple_text_analysis'!I:I,'3.simple_text_analysis'!$M:$M,summary!$B129,'3.simple_text_analysis'!$P:$P,$A$65)/$C106,"")
B130: Healthcare | C130: =IFERROR(SUMIFS('3.simple_text_analysis'!F:F,'3.simple_text_analysis'!$M:$M,summary!$B130,'3.simple_text_analysis'!$P:$P,$A$65)/$C107,"") | D130: =IFERROR(SUMIFS('3.simple_text_analysis'!G:G,'3.simple_text_analysis'!$M:$M,summary!$B130,'3.simple_text_analysis'!$P:$P,$A$65)/$C107,"") | E130: =IFERROR(SUMIFS('3.simple_text_analysis'!H:H,'3.simple_text_analysis'!$M:$M,summary!$B130,'3.simple_text_analysis'!$P:$P,$A$65)/$C107,"") | F130: =IFERROR(SUMIFS('3.simple_text_analysis'!I:I,'3.simple_text_analysis'!$M:$M,summary!$B130,'3.simple_text_analysis'!$P:$P,$A$65)/$C107,"")
B131: Average | C131: =IFERROR(SUMIFS('3.simple_text_analysis'!F:F,'3.simple_text_analysis'!$P:$P,$A$65)/$C108,"") -> 0.06824 | D131: =IFERROR(SUMIFS('3.simple_text_analysis'!G:G,'3.simple_text_analysis'!$P:$P,$A$65)/$C108,"") -> 0.84724 | E131: =IFERROR(SUMIFS('3.simple_text_analysis'!H:H,'3.simple_text_analysis'!$P:$P,$A$65)/$C108,"") -> 0.0846 | F131: =IFERROR(SUMIFS('3.simple_text_analysis'!I:I,'3.simple_text_analysis'!$P:$P,$A$65)/$C108,"") -> 0.352216
A137: Reporting firms breakdown by industry
A138: 1 | B138: 16 | C138: 1 | D138: 10 | E138: 2 | F138: =SUM(A138:E138) -> 30
A139: Energy | B139: Financial sector | C139: Food/agricuture | D139: Industry | E139: Real Estate
A140: Z ENERGY | B140: AIA NZ | C140: T&G GLOBAL | D140: BRISCOE GROUP | E140: PROPERTY FOR INDUSTRY
B141: BANK OF CHINA (NZ) | D141: CHANNEL INFRASTRUCTURE NZ | E141: SUMMERSET GROUP HOLDINGS
B142: CDL INVESTMENTS NZ | D142: MILLENNIUM & COPTHORNE HOTELS NEW ZEALAND
B143: CHINA CONSTRUCTION BANK (NZ) | D143: NEW ZEALAND RURAL LAND COMPANY
B144: CHINA CONSTRUCTION BANK CORPORATION | D144: NZME
B145: CHUBB LIFE INSURANCE NZ | D145: RESTAURANT BRANDS NEW ZEALAND
B146: CITIBANK, N.A. | D146: SCALES CORPORATION
B147: COOPERATIEVE RABOBANK U.A. | D147: SEEKA
...

Sheet 20April
B1: Link | C1: Company Name | D1: Text | E1: text_new | F1: Scheme Name | G1: status | H1: scheme | I1: Submit Date | J1: Due Date
A2: 0 | B2: https://crd-app.companiesoffice.govt.nz/dashboard/reportingentity/?id=8b6b5ca5-8394-ee11-be37-00224892b34a | C2: AA INSURANCE LIMITED | D2: Reporting Period . sort descending Actions There are no records to display. | E2: There are no records to display. | G2: No records | H2: Company | I2: no data | J2: no data
A3: 1 | B3: https://crd-app.companiesoffice.govt.nz/dashboard/reportingentity/?id=a96b5ca5-8394-ee11-be37-00224892b34a | C3: AFT PHARMACEUTICALS LIMITED | D3: Reporting Period . sort descending Actions 31-03-2024 - Due by 31-07-2024 | E3: 31-03-2024 - Due by 31-07-2024 | G3: Have records but not submitted | H3: Company | I3: 45382 | J3: 45504
A4: 2 | B4: https://crd-app.companiesoffice.govt.nz/dashboard/reportingentity/?id=8d6b5ca5-8394-ee11-be37-00224892b34a | C4: AIA NEW ZEALAND LIMITED | D4: Reporting Period . sort descending Actions 31-12-2023 - Due by 30-04-2024 | E4: 31-12-2023 - Due by 30-04-2024 | G4: Have records but not submitted | H4: Company | I4: 45291 | J4: 45412
A5: 3 | B5: https://crd-app.companiesoffice.govt.nz/dashboard/reportingentity/?id=ab6b5ca5-8394-ee11-be37-00224892b34a | C5: AIR NEW ZEALAND LIMITED | D5: Reporting Period . sort descending Actions There are no records to display. | E5: There are no records to display. | G5: No records | H5: Company | I5: no data | J5: no data
A6: 4 | B6: https://crd-app.companiesoffice.govt.nz/dashboard/reportingentity/?id=ad6b5ca5-8394-ee11-be37-00224892b34a | C6: ARBORGEN HOLDINGS LIMITED | D6: Reporting Period . sort descending Actions 31-03-2024 - Due by 31-07-2024 | E6: 31-03-2024 - Due by 31-07-2024 | G6: Have records but not submitted | H6: Company | I6: 45382 | J6: 45504
A7: 5 | B7: https://crd-app.companiesoffice.govt.nz/dashboard/reportingentity/?id=af6b5ca5-8394-ee11-be37-00224892b34a | C7: ARGOSY PROPERTY LIMITED | D7: Reporting Period . sort descending Actions 31-03-2024 - Due by 31-07-2024 | E7: 31-03-2024 - Due by 31-07-2024 | G7: Have records but not submitted | H7: Company | I7: 45382 | J7: 45504
A8: 6 | B8: https://crd-app.companiesoffice.govt.nz/dashboard/reportingentity/?id=b16b5ca5-8394-ee11-be37-00224892b34a | C8: ARVIDA GROUP LIMITED | D8: Reporting Period . sort descending Actions 31-03-2024 - Due by 31-07-2024 | E8: 31-03-2024 - Due by 31-07-2024 | G8: Have records but not submitted | H8: Company | I8: 45382 | J8: 45504
A9: 7 | B9: https://crd-app.companiesoffice.govt.nz/dashboard/reportingentity/?id=656b5ca5-8394-ee11-be37-00224892b34a | C9: ASB BANK LIMITED | D9: Reporting Period . sort descending Actions There are no records to display. | E9: There are no records to display. | G9: No records | H9: Company | I9: no data | J9: no data
A10: 8 | B10: https://crd-app.companiesoffice.govt.nz/dashboard/reportingentity/?id=b36b5ca5-8394-ee11-be37-00224892b34a | C10: ASSET PLUS LIMITED | D10: Reporting Period . sort descending Actions 31-03-2024 - Due by 31-07-2024 | E10: 31-03-2024 - Due by 31-07-2024 | G10: Have records but not submitted | H10: Company | I10: 45382 | J10: 45504
A11: 9 | B11: https://crd-app.companiesoffice.govt.nz/dashboard/reportingentity/?id=8f6b5ca5-8394-ee11-be37-00224892b34a | C11: ASTERON LIFE LIMITED | D11: Reporting Period . sort descending Actions There are no records to display. | E11: There are no records to display. | G11: No records | H11: Company | I11: no data | J11: no data
A12: 10 | B12: https://crd-app.companiesoffice.govt.nz/dashboard/reportingentity/?id=b56b5ca5-8394-ee11-be37-00224892b34a | C12: AUCKLAND COUNCIL | D12: Reporting Period . sort descending Actions There are no records to display. | E12: There are no records to display. | G12: No records | H12: Company | I12: no data | J12: no data
A13: 11 | B13: https://crd-app.companiesoffice.govt.nz/dashboard/reportingentity/?id=b76b5ca5-8394-ee11-be37-00224892b34a | C13: AUCKLAND INTERNATIONAL AIRPORT LIMITED | D13: Reporting Period . sort descending Actions There are no records to display. | E13: There are no records to display. | G13: No records | H13: Company | I13: no data | J13: no data
A14: 12 | B14: https://crd-app.companiesoffice.govt.nz/dashboard/reportingentity/?id=b96b5ca5-8394-ee11-be37-00224892b34a | C14: AUSTRALIAN FOUNDATION INVESTMENT COMPANY LIMITED | D14: Reporting Period . sort descending Actions There are no records to display. | E14: There are no records to display. | G14: No records | H14: Company | I14: no data | J14: no data
A15: 13 | B15: https://crd-app.companiesoffice.govt.nz/dashboard/reportingentity/?id=676b5ca5-8394-ee11-be37-00224892b34a | C15: BANK OF CHINA (NEW ZEALAND) LIMITED | D15: Reporting Period . sort descending Actions 31-12-2023 - Due by 30-04-2024 | E15: 31-12-2023 - Due by 30-04-2024 | G15: Have records but not submitted | H15: Company | I15: 45291 | J15: 45412
A16: 14 | B16: https://crd-app.companiesoffice.govt.nz/dashboard/reportingentity/?id=696b5ca5-8394-ee11-be37-00224892b34a | C16: BANK OF CHINA LIMITED | D16: Reporting Period . sort descending Actions 31-12-2023 - Due by 30-04-2024 | E16: 31-12-2023 - Due by 30-04-2024 | G16: Have records but not submitted | H16: Company | I16: 45291 | J16: 45412
A17: 15 | B17: https://crd-app.companiesoffice.govt.nz/dashboard/reportingentity/?id=bb6b5ca5-8394-ee11-be37-00224892b34a | C17: BARRAMUNDI LIMITED | D17: Reporting Period . sort descending Actions There are no records to display. | E17: There are no records to display. | G17: No records | H17: Company | I17: no data | J17: no data
A18: 16 | B18: https://crd-app.companiesoffice.govt.nz/dashboard/reportingentity/?id=bd6b5ca5-8394-ee11-be37-00224892b34a | C18: BRISCOE GROUP LIMITED | D18: Reporting Period . sort descending Actions 31-01-2024 - Click to view Climate Statement/s | E18: 31-01-2024 - Click to view Climate Statement/s | G18: Have records and have submitted | H18: Company | I18: no data | J18: no data
A19: 17 | B19: https://crd-app.companiesoffice.govt.nz/dashboard/reportingentity/?id=bf6b5ca5-8394-ee11-be37-00224892b34a | C19: CDL INVESTMENTS NEW ZEALAND LIMITED | D19: Reporting Period . sort descending Actions 31-12-2023 - Click to view Climate Statement/s | E19: 31-12-2023 - Click to view Climate Statement/s | G19: Have records and have submitted | H19: Company | I19: no data | J19: no data
A20: 18 | B20: https://crd-app.companiesoffice.govt.nz/dashboard/reportingentity/?id=c16b5ca5-8394-ee11-be37-00224892b34a | C20: CHANNEL INFRASTRUCTURE NZ LIMITED | D20: Reporting Period . sort descending Actions 31-12-2023 - Click to view Climate Statement/s | E20: 31-12-2023 - Click to view Climate Statement/s | G20: Have records and have submitted | H20: Company | I20: no data | J20: no data
A21: 19 | B21: https://crd-app.companiesoffice.govt.nz/dashboard/reportingentity/?id=6b6b5ca5-8394-ee11-be37-00224892b34a | C21: CHINA CONSTRUCTION BANK (NEW ZEALAND) LIMITED | D21: Reporting Period . sort descending Actions 31-12-2023 - Due by 30-04-2024 | E21: 31-12-2023 - Due by 30-04-2024 | G21: Have records but not submitted | H21: Company | I21: 45291 | J21: 45412
A22: 20 | B22: https://crd-app.companiesoffice.govt.nz/dashboard/reportingentity/?id=6d6b5ca5-8394-ee11-be37-00224892b34a | C22: CHINA CONSTRUCTION BANK CORPORATION | D22: Reporting Period . sort descending Actions 31-12-2023 - Due by 30-04-2024 | E22: 31-12-2023 - Due by 30-04-2024 | G22: Have records but not submitted | H22: Company | I22: 45291 | J22: 45412
A23: 21 | B23: https://crd-app.companiesoffice.govt.nz/dashboard/reportingentity/?id=c36b5ca5-8394-ee11-be37-00224892b34a | C23: CHORUS LIMITED | D23: Reporting Period . sort descending Actions There are no records to display. | E23: There are no records to display. | G23: No records | H23: Company | I23: no data | J23: no data
A24: 22 | B24: https://crd-app.companiesoffice.govt.nz/dashboard/reportingentity/?id=c56b5ca5-8394-ee11-be37-00224892b34a | C24: CHRISTCHURCH CITY HOLDINGS LIMITED | D24: Reporting Period . sort descending Actions There are no records to display. | E24: There are no records to display. | G24: No records | H24: Company | I24: no data | J24: no data
A25: 23 | B25: https://crd-app.companiesoffice.govt.nz/dashboard/reportingentity/?id=c76b5ca5-8394-ee11-be37-00224892b34a | C25: CHRISTCHURCH INTERNATIONAL AIRPORT LIMITED | D25: Reporting Period . sort descending Actions There are no records to display. | E25: There are no records to display. | G25: No records | H25: Company | I25: no data | J25: no data
A26: 24 | B26: https://crd-app.companiesoffice.govt.nz/dashboard/reportingentity/?id=916b5ca5-8394-ee11-be37-00224892b34a | C26: CHUBB LIFE INSURANCE NEW ZEALAND LIMITED | D26: Reporting Period . sort descending Actions 31-12-2023 - Due by 30-04-2024 | E26: 31-12-2023 - Due by 30-04-2024 | G26: Have records but not submitted | H26: Company | I26: 45291 | J26: 45412
A27: 25 | B27: https://crd-app.companiesoffice.govt.nz/dashboard/reportingentity/?id=6f6b5ca5-8394-ee11-be37-00224892b34a | C27: CITIBANK, N.A. | D27: Reporting Period . sort descending Actions 31-12-2023 - Due by 30-04-2024 | E27: 31-12-2023 - Due by 30-04-2024 | G27: Have records but not submitted | H27: Company | I27: 45291 | J27: 45412
A28: 26 | B28: https://crd-app.companiesoffice.govt.nz/dashboard/reportingentity/?id=716b5ca5-8394-ee11-be37-00224892b34a | C28: COMMONWEALTH BANK OF AUSTRALIA | D28: Reporting Period . sort descending Actions There are no records to display. | E28: There are no records to display. | G28: No records | H28: Company | I28: no data | J28: no data
A29: 27 | B29: https://crd-app.companiesoffice.govt.nz/dashboard/reportingentity/?id=c96b5ca5-8394-ee11-be37-00224892b34a | C29: COMVITA LIMITED | D29: Reporting Period . sort descending Actions There are no records to display. | E29: There are no records to display. | G29: No records | H29: Company | I29: no data | J29: no data
A30: 28 | B30: https://crd-app.companiesoffice.govt.nz/dashboard/reportingentity/?id=cb6b5ca5-8394-ee11-be37-00224892b34a | C30: CONTACT ENERGY LIMITED | D30: Reporting Period . sort descending Actions There are no records to display. | E30: There are no records to display. | G30: No records | H30: Company | I30: no data | J30: no data
A31: 29 | B31: https://crd-app.companiesoffice.govt.nz/dashboard/reportingentity/?id=736b5ca5-8394-ee11-be37-00224892b34a | C31: COOPERATIEVE RABOBANK U.A. | D31: Reporting Period . sort descending Actions 31-12-2023 - Due by 30-04-2024 | E31: 31-12-2023 - Due by 30-04-2024 | G31: Have records but not submitted | H31: Company | I31: 45291 | J31: 45412
A32: 30 | B32: https://crd-app.companiesoffice.govt.nz/dashboard/reportingentity/?id=cd6b5ca5-8394-ee11-be37-00224892b34a | C32: DELEGAT GROUP LIMITED | D32: Reporting Period . sort descending Actions There are no records to display. | E32: There are no records to display. | G32: No records | H32: Company | I32: no data | J32: no data
A33: 31 | B33: https://crd-app.companiesoffice.govt.nz/dashboard/reportingentity/?id=cf6b5ca5-8394-ee11-be37-00224892b34a | C33: EBOS GROUP LIMITED | D33: Reporting Period . sort descending Actions There are no records to display. | E33: There are no records to display. | G33: No records | H33: Company | I33: no data | J33: no data
A34: 32 | B34: https://crd-app.companiesoffice.govt.nz/dashboard/reportingentity/?id=d16b5ca5-8394-ee11-be37-00224892b34a | C34: EROAD LIMITED | D34: Reporting Period . sort descending Actions 31-03-2024 - Due by 31-07-2024 | E34: 31-03-2024 - Due by 31-07-2024 | G34: Have records but not submitted | H34: Company | I34: 45382 | J34: 45504
A35: 33 | B35: https://crd-app.companiesoffice.govt.nz/dashboard/reportingentity/?id=d36b5ca5-8394-ee11-be37-00224892b34a | C35: F&C INVESTMENT TRUST PLC | D35: Reporting Period . sort descending Actions 31-12-2023 - Due by 30-04-2024 | E35: 31-12-2023 - Due by 30-04-2024 | G35: Have records but not submitted | H35: Company | I35: 45291 | J35: 45412
A36: 34 | B36: https://crd-app.companiesoffice.govt.nz/dashboard/reportingentity/?id=936b5ca5-8394-ee11-be37-00224892b34a | C36: FIDELITY LIFE ASSURANCE COMPANY LIMITED | D36: Reporting Period . sort descending Actions There are no records to display. | E36: There are no records to display. | G36: No records | H36: Company | I36: no data | J36: no data
A37: 35 | B37: https://crd-app.companiesoffice.govt.nz/dashboard/reportingentity/?id=d56b5ca5-8394-ee11-be37-00224892b34a | C37: FISHER & PAYKEL HEALTHCARE CORPORATION LIMITED | D37: Reporting Period . sort descending Actions 31-03-2024 - Due by 31-07-2024 | E37: 31-03-2024 - Due by 31-07-2024 | G37: Have records but not submitted | H37: Company | I37: 45382 | J37: 45504
A38: 36 | B38: https://crd-app.companiesoffice.govt.nz/dashboard/reportingentity/?id=d76b5ca5-8394-ee11-be37-00224892b34a | C38: FLETCHER BUILDING INDUSTRIES LIMITED | D38: Reporting Period . sort descending Actions There are no records to display. | E38: There are no records to display. | G38: No records | H38: Company | I38: no data | J38: no data
A39: 37 | B39: https://crd-app.companiesoffice.govt.nz/dashboard/reportingentity/?id=d96b5ca5-8394-ee11-be37-00224892b34a | C39: FLETCHER BUILDING LIMITED | D39: Reporting Period . sort descending Actions There are no records to display. | E39: There are no records to display. | G39: No records | H39: Company | I39: no data | J39: no data
A40: 38 | B40: https://crd-app.companiesoffice.govt.nz/dashboard/reportingentity/?id=956b5ca5-8394-ee11-be37-00224892b34a | C40: FMG INSURANCE LIMITED | D40: Reporting Period . sort descending Actions 31-03-2024 - Due by 31-07-2024 | E40: 31-03-2024 - Due by 31-07-2024 | G40: Have records but not submitted | H40: Company | I40: 45382 | J40: 45504
A41: 39 | B41: https://crd-app.companiesoffice.govt.nz/dashboard/reportingentity/?id=db6b5ca5-8394-ee11-be37-00224892b34a | C41: FOLEY WINES LIMITED | D41: Reporting Period . sort descending Actions There are no records to display. | E41: There are no records to display. | G41: No records | H41: Company | I41: no data | J41: no data
A42: 40 | B42: https://crd-app.companiesoffice.govt.nz/dashboard/reportingentity/?id=dd6b5ca5-8394-ee11-be37-00224892b34a | C42: FREIGHTWAYS GROUP LIMITED | D42: Reporting Period . sort descending Actions There are no records to display. | E42: There are no records to display. | G42: No records | H42: Company | I42: no data | J42: no data
A43: 41 | B43: https://crd-app.companiesoffice.govt.nz/dashboard/reportingentity/?id=df6b5ca5-8394-ee11-be37-00224892b34a | C43: GENESIS ENERGY LIMITED | D43: Reporting Period . sort descending Actions There are no records to display. | E43: There are no records to display. | G43: No records | H43: Company | I43: no data | J43: no data
A44: 42 | B44: https://crd-app.companiesoffice.govt.nz/dashboard/reportingentity/?id=e16b5ca5-8394-ee11-be37-00224892b34a | C44: GMT BOND ISSUER LIMITED | D44: Reporting Period . sort descending Actions 31-03-2024 - Due by 31-07-2024 | E44: 31-03-2024 - Due by 31-07-2024 | G44: Have records but not submitted | H44: Company | I44: 45382 | J44: 45504
A45: 43 | B45: https://crd-app.companiesoffice.govt.nz/dashboard/reportingentity/?id=e36b5ca5-8394-ee11-be37-00224892b34a | C45: GREEN CROSS HEALTH LIMITED | D45: Reporting Period . sort descending Actions 31-03-2024 - Due by 31-07-2024 | E45: 31-03-2024 - Due by 31-07-2024 | G45: Have records but not submitted | H45: Company | I45: 45382 | J45: 45504
A46: 44 | B46: https://crd-app.companiesoffice.govt.nz/dashboard/reportingentity/?id=756b5ca5-8394-ee11-be37-00224892b34a | C46: HEARTLAND BANK LIMITED | D46: Reporting Period . sort descending Actions There are no records to display. | E46: There are no records to display. | G46: No records | H46: Company | I46: no data | J46: no data
A47: 45 | B47: https://crd-app.companiesoffice.govt.nz/dashboard/reportingentity/?id=e56b5ca5-8394-ee11-be37-00224892b34a | C47: HEARTLAND GROUP HOLDINGS LIMITED | D47: Reporting Period . sort descending Actions There are no records to display. | E47: There are no records to display. | G47: No records | H47: Company | I47: no data | J47: no data
A48: 46 | B48: https://crd-app.companiesoffice.govt.nz/dashboard/reportingentity/?id=e76b5ca5-8394-ee11-be37-00224892b34a | C48: HOUSING NEW ZEALAND LIMITED | D48: Reporting Period . sort descending Actions There are no records to display. | E48: There are no records to display. | G48: No records | H48: Company | I48: no data | J48: no data
A49: 47 | B49: https://crd-app.companiesoffice.govt.nz/dashboard/reportingentity/?id=976b5ca5-8394-ee11-be37-00224892b34a | C49: IAG NEW ZEALAND LIMITED | D49: Reporting Period . sort descending Actions There are no records to display. | E49: There are no records to display. | G49: No records | H49: Company | I49: no data | J49: no data
A50: 48 | B50: https://crd-app.companiesoffice.govt.nz/dashboard/reportingentity/?id=e96b5ca5-8394-ee11-be37-00224892b34a | C50: IKEGPS GROUP LIMITED | D50: Reporting Period . sort descending Actions 31-03-2024 - Due by 31-07-2024 | E50: 31-03-2024 - Due by 31-07-2024 | G50: Have records but not submitted | H50: Company | I50: 45382 | J50: 45504
A51: 49 | B51: https://crd-app.companiesoffice.govt.nz/dashboard/reportingentity/?id=776b5ca5-8394-ee11-be37-00224892b34a | C51: INDUSTRIAL AND COMMERCIAL BANK OF CHINA (NEW ZEALAND) LIMITED | D51: Reporting Period . sort descending Actions 31-12-2023 - Due by 30-04-2024 | E51: 31-12-2023 - Due by 30-04-2024 | G51: Have records but not submitted | H51: Company | I51: 45291 | J51: 45412
A52: 50 | B52: https://crd-app.companiesoffice.govt.nz/dashboard/reportingentity/?id=796b5ca5-8394-ee11-be37-00224892b34a | C52: INDUSTRIAL AND COMMERCIAL BANK OF CHINA LIMITED | D52: Reporting Period . sort descending Actions 31-12-2023 - Due by 30-04-2024 | E52: 31-12-2023 - Due by 30-04-2024 | G52: Have records but not submitted | H52: Company | I52: 45291 | J52: 45412
A53: 51 | B53: https://crd-app.companiesoffice.govt.nz/dashboard/reportingentity/?id=eb6b5ca5-8394-ee11-be37-00224892b34a | C53: INFRATIL LIMITED | D53: Reporting Period . sort descending Actions 31-03-2024 - Due by 31-07-2024 | E53: 31-03-2024 - Due by 31-07-2024 | G53: Have records but not submitted | H53: Company | I53: 45382 | J53: 45504
A54: 52 | B54: https://crd-app.companiesoffice.govt.nz/dashboard/reportingentity/?id=ed6b5ca5-8394-ee11-be37-00224892b34a | C54: INSURANCE AUSTRALIA GROUP LIMITED | D54: Reporting Period . sort descending Actions There are no records to display. | E54: There are no records to display. | G54: No records | H54: Company | I54: no data | J54: no data
A55: 53 | B55: https://crd-app.companiesoffice.govt.nz/dashboard/reportingentity/?id=ef6b5ca5-8394-ee11-be37-00224892b34a | C55: INVESTORE PROPERTY LIMITED | D55: Reporting Period . sort descending Actions 31-03-2024 - Due by 31-07-2024 | E55: 31-03-2024 - Due by 31-07-2024 | G55: Have records but not submitted | H55: Company | I55: 45382 | J55: 45504
A56: 54 | B56: https://crd-app.companiesoffice.govt.nz/dashboard/reportingentity/?id=7b6b5ca5-8394-ee11-be37-00224892b34a | C56: JPMORGAN CHASE BANK, N.A. | D56: Reporting Period . sort descending Actions 31-12-2023 - Due by 30-04-2024 | E56: 31-12-2023 - Due by 30-04-2024 | G56: Have records but not submitted | H56: Company | I56: 45291 | J56: 45412
A57: 55 | B57: https://crd-app.companiesoffice.govt.nz/dashboard/reportingentity/?id=f16b5ca5-8394-ee11-be37-00224892b34a | C57: KINGFISH LIMITED | D57: Reporting Period . sort descending Actions 31-03-2024 - Due by 31-07-2024 | E57: 31-03-2024 - Due by 31-07-2024 | G57: Have records but not submitted | H57: Company | I57: 45382 | J57: 45504
A58: 56 | B58: https://crd-app.companiesoffice.govt.nz/dashboard/reportingentity/?id=f36b5ca5-8394-ee11-be37-00224892b34a | C58: KIWI PROPERTY GROUP LIMITED | D58: Reporting Period . sort descending Actions 31-03-2024 - Due by 31-07-2024 | E58: 31-03-2024 - Due by 31-07-2024 | G58: Have records but not submitted | H58: Company | I58: 45382 | J58: 45504
A59: 57 | B59: https://crd-app.companiesoffice.govt.nz/dashboard/reportingentity/?id=7d6b5ca5-8394-ee11-be37-00224892b34a | C59: KIWIBANK LIMITED | D59: Reporting Period . sort descending Actions There are no records to display. | E59: There are no records to display. | G59: No records | H59: Company | I59: no data | J59: no data
A60: 58 | B60: https://crd-app.companiesoffice.govt.nz/dashboard/reportingentity/?id=f56b5ca5-8394-ee11-be37-00224892b34a | C60: LIVESTOCK IMPROVEMENT CORPORATION LIMITED | D60: Reporting Period . sort descending Actions There are no records to display. | E60: There are no records to display. | G60: No records | H60: Company | I60: no data | J60: no data
A61: 59 | B61: https://crd-app.companiesoffice.govt.nz/dashboard/reportingentity/?id=f76b5ca5-8394-ee11-be37-00224892b34a | C61: MAINFREIGHT LIMITED | D61: Reporting Period . sort descending Actions 31-03-2024 - Due by 31-07-2024 | E61: 31-03-2024 - Due by 31-07-2024 | G61: Have records but not submitted | H61: Company | I61: 45382 | J61: 45504
A62: 60 | B62: https://crd-app.companiesoffice.govt.nz/dashboard/reportingentity/?id=f96b5ca5-8394-ee11-be37-00224892b34a | C62: MANAWA ENERGY LIMITED | D62: Reporting Period . sort descending Actions 31-03-2024 - Due by 31-07-2024 | E62: 31-03-2024 - Due by 31-07-2024 | G62: Have records but not submitted | H62: Company | I62: 45382 | J62: 45504
A63: 61 | B63: https://crd-app.companiesoffice.govt.nz/dashboard/reportingentity/?id=fb6b5ca5-8394-ee11-be37-00224892b34a | C63: MARLIN GLOBAL LIMITED | D63: Reporting Period . sort descending Actions There are no records to display. | E63: There are no records to display. | G63: No records | H63: Company | I63: no data | J63: no data
A64: 62 | B64: https://crd-app.companiesoffice.govt.nz/dashboard/reportingentity/?id=fd6b5ca5-8394-ee11-be37-00224892b34a | C64: MARSDEN MARITIME HOLDINGS LIMITED | D64: Reporting Period . sort descending Actions There are no records to display. | E64: There are no records to display. | G64: No records | H64: Company | I64: no data | J64: no data
A65: 63 | B65: https://crd-app.companiesoffice.govt.nz/dashboard/reportingentity/?id=ff6b5ca5-8394-ee11-be37-00224892b34a | C65: MERCURY NZ LIMITED | D65: Reporting Period . sort descending Actions There are no records to display. | E65: There are no records to display. | G65: No records | H65: Company | I65: no data | J65: no data
A66: 64 | B66: https://crd-app.companiesoffice.govt.nz/dashboard/reportingentity/?id=016c5ca5-8394-ee11-be37-00224892b34a | C66: MERIDIAN ENERGY LIMITED | D66: Reporting Period . sort descending Actions There are no records to display. | E66: There are no records to display. | G66: No records | H66: Company | I66: no data | J66: no data
A67: 65 | B67: https://crd-app.companiesoffice.govt.nz/dashboard/reportingentity/?id=036c5ca5-8394-ee11-be37-00224892b34a | C67: METLIFECARE LIMITED | D67: Reporting Period . sort descending Actions There are no records to display. | E67: There are no records to display. | G67: No records | H67: Company | I67: no data | J67: no data
A68: 66 | B68: https://crd-app.companiesoffice.govt.nz/dashboard/reportingentity/?id=056c5ca5-8394-ee11-be37-00224892b34a | C68: MICHAEL HILL INTERNATIONAL LIMITED | D68: Reporting Period . sort descending Actions There are no records to display. | E68: There are no records to display. | G68: No records | H68: Company | I68: no data | J68: no data
A69: 67 | B69: https://crd-app.companiesoffice.govt.nz/dashboard/reportingentity/?id=076c5ca5-8394-ee11-be37-00224892b34a | C69: MILLENNIUM & COPTHORNE HOTELS NEW ZEALAND LIMITED | D69: Reporting Period . sort descending Actions 31-12-2023 - Click to view Climate Statement/s | E69: 31-12-2023 - Click to view Climate Statement/s | G69: Have records and have submitted | H69: Company | I69: no data | J69: no data
A70: 68 | B70: https://crd-app.companiesoffice.govt.nz/dashboard/reportingentity/?id=096c5ca5-8394-ee11-be37-00224892b34a | C70: MOVE LOGISTICS GROUP LIMITED | D70: Reporting Period . sort descending Actions There are no records to display. | E70: There are no records to display. | G70: No records | H70: Company | I70: no data | J70: no data
A71: 69 | B71: https://crd-app.companiesoffice.govt.nz/dashboard/reportingentity/?id=7f6b5ca5-8394-ee11-be37-00224892b34a | C71: MUFG BANK, LTD. | D71: Reporting Period . sort descending Actions 31-03-2024 - Due by 31-07-2024 | E71: 31-03-2024 - Due by 31-07-2024 | G71: Have records but not submitted | H71: Company | I71: 45382 | J71: 45504
A72: 70 | B72: https://crd-app.companiesoffice.govt.nz/dashboard/reportingentity/?id=9b6c5ca5-8394-ee11-be37-00224892b34a | C72: NELSON BUILDING SOCIETY | D72: Reporting Period . sort descending Actions 31-03-2024 - Due by 31-07-2024 | E72: 31-03-2024 - Due by 31-07-2024 | G72: Have records but not submitted | H72: Company | I72: 45382 | J72: 45504
A73: 71 | B73: https://crd-app.companiesoffice.govt.nz/dashboard/reportingentity/?id=0b6c5ca5-8394-ee11-be37-00224892b34a | C73: NEW ZEALAND KING SALMON INVESTMENTS LIMITED | D73: Reporting Period . sort descending Actions 31-01-2024 - Due by 31-05-2024 | E73: 31-01-2024 - Due by 31-05-2024 | G73: Have records but not submitted | H73: Company | I73: 45322 | J73: 45443
A74: 72 | B74: https://crd-app.companiesoffice.govt.nz/dashboard/reportingentity/?id=0d6c5ca5-8394-ee11-be37-00224892b34a | C74: NEW ZEALAND LOCAL GOVERNMENT FUNDING AGENCY LIMITED | D74: Reporting Period . sort descending Actions There are no records to display. | E74: There are no records to display. | G74: No records | H74: Company | I74: no data | J74: no data
A75: 73 | B75: https://crd-app.companiesoffice.govt.nz/dashboard/reportingentity/?id=0f6c5ca5-8394-ee11-be37-00224892b34a | C75: NEW ZEALAND OIL & GAS LIMITED | D75: Reporting Period . sort descending Actions There are no records to display. | E75: There are no records to display. | G75: No records | H75: Company | I75: no data | J75: no data
A76: 74 | B76: https://crd-app.companiesoffice.govt.nz/dashboard/reportingentity/?id=116c5ca5-8394-ee11-be37-00224892b34a | C76: NEW ZEALAND RURAL LAND COMPANY LIMITED | D76: Reporting Period . sort descending Actions 31-12-2023 - Due by 30-04-2024 | E76: 31-12-2023 - Due by 30-04-2024 | G76: Have records but not submitted | H76: Company | I76: 45291 | J76: 45412
A77: 75 | B77: https://crd-app.companiesoffice.govt.nz/dashboard/reportingentity/?id=996b5ca5-8394-ee11-be37-00224892b34a | C77: NIB NZ LIMITED | D77: Reporting Period . sort descending Actions There are no records to display. | E77: There are no records to display. | G77: No records | H77: Company | I77: no data | J77: no data
A78: 76 | B78: https://crd-app.companiesoffice.govt.nz/dashboard/reportingentity/?id=136c5ca5-8394-ee11-be37-00224892b34a | C78: NZME LIMITED | D78: Reporting Period . sort descending Actions 31-12-2023 - Click to view Climate Statement/s | E78: 31-12-2023 - Click to view Climate Statement/s | G78: Have records and have submitted | H78: Company | I78: no data | J78: no data
A79: 77 | B79: https://crd-app.companiesoffice.govt.nz/dashboard/reportingentity/?id=156c5ca5-8394-ee11-be37-00224892b34a | C79: NZX LIMITED | D79: Reporting Period . sort descending Actions 31-12-2023 - Click to view Climate Statement/s | E79: 31-12-2023 - Click to view Climate Statement/s | G79: Have records and have submitted | H79: Company | I79: no data | J79: no data
A80: 78 | B80: https://crd-app.companiesoffice.govt.nz/dashboard/reportingentity/?id=176c5ca5-8394-ee11-be37-00224892b34a | C80: OCEANIA HEALTHCARE LIMITED | D80: Reporting Period . sort descending Actions 31-03-2024 - Due by 31-07-2024 | E80: 31-03-2024 - Due by 31-07-2024 | G80: Have records but not submitted | H80: Company | I80: 45382 | J80: 45504
A81: 79 | B81: https://crd-app.companiesoffice.govt.nz/dashboard/reportingentity/?id=196c5ca5-8394-ee11-be37-00224892b34a | C81: PACIFIC EDGE LIMITED | D81: Reporting Period . sort descending Actions 31-03-2024 - Due by 31-07-2024 | E81: 31-03-2024 - Due by 31-07-2024 | G81: Have records but not submitted | H81: Company | I81: 45382 | J81: 45504
A82: 80 | B82: https://crd-app.companiesoffice.govt.nz/dashboard/reportingentity/?id=9b6b5ca5-8394-ee11-be37-00224892b34a | C82: PARTNERS LIFE LIMITED | D82: Reporting Period . sort descending Actions 31-03-2024 - Due by 31-07-2024 | E82: 31-03-2024 - Due by 31-07-2024 | G82: Have records but not submitted | H82: Company | I82: 45382 | J82: 45504
A83: 81 | B83: https://crd-app.companiesoffice.govt.nz/dashboard/reportingentity/?id=1b6c5ca5-8394-ee11-be37-00224892b34a | C83: PGG WRIGHTSON LIMITED | D83: Reporting Period . sort descending Actions There are no records to display. | E83: There are no records to display. | G83: No records | H83: Company | I83: no data | J83: no data
A84: 82 | B84: https://crd-app.companiesoffice.govt.nz/dashboard/reportingentity/?id=1d6c5ca5-8394-ee11-be37-00224892b34a | C84: PORT OF TAURANGA LIMITED | D84: Reporting Period . sort descending Actions There are no records to display. | E84: There are no records to display. | G84: No records | H84: Company | I84: no data | J84: no data
A85: 83 | B85: https://crd-app.companiesoffice.govt.nz/dashboard/reportingentity/?id=1f6c5ca5-8394-ee11-be37-00224892b34a | C85: PRECINCT PROPERTIES NEW ZEALAND LIMITED | D85: Reporting Period . sort descending Actions There are no records to display. | E85: There are no records to display. | G85: No records | H85: Company | I85: no data | J85: no data
A86: 84 | B86: https://crd-app.companiesoffice.govt.nz/dashboard/reportingentity/?id=216c5ca5-8394-ee11-be37-00224892b34a | C86: PROPERTY FOR INDUSTRY LIMITED | D86: Reporting Period . sort descending Actions 31-12-2023 - Click to view Climate Statement/s | E86: 31-12-2023 - Click to view Climate Statement/s | G86: Have records and have submitted | H86: Company | I86: no data | J86: no data
A87: 85 | B87: https://crd-app.companiesoffice.govt.nz/dashboard/reportingentity/?id=9d6b5ca5-8394-ee11-be37-00224892b34a | C87: QBE INSURANCE (AUSTRALIA) LIMITED | D87: Reporting Period . sort descending Actions 31-12-2023 - Due by 30-04-2024 | E87: 31-12-2023 - Due by 30-04-2024 | G87: Have records but not submitted | H87: Company | I87: 45291 | J87: 45412
A88: 86 | B88: https://crd-app.companiesoffice.govt.nz/dashboard/reportingentity/?id=236c5ca5-8394-ee11-be37-00224892b34a | C88: QUAYSIDE HOLDINGS LIMITED | D88: Reporting Period . sort descending Actions There are no records to display. | E88: There are no records to display. | G88: No records | H88: Company | I88: no data | J88: no data
A89: 87 | B89: https://crd-app.companiesoffice.govt.nz/dashboard/reportingentity/?id=816b5ca5-8394-ee11-be37-00224892b34a | C89: RABOBANK NEW ZEALAND LIMITED | D89: Reporting Period . sort descending Actions 31-12-2023 - Due by 30-04-2024 | E89: 31-12-2023 - Due by 30-04-2024 | G89: Have records but not submitted | H89: Company | I89: 45291 | J89: 45412
A90: 88 | B90: https://crd-app.companiesoffice.govt.nz/dashboard/reportingentity/?id=256c5ca5-8394-ee11-be37-00224892b34a | C90: RADIUS RESIDENTIAL CARE LIMITED | D90: Reporting Period . sort descending Actions 31-03-2024 - Due by 31-07-2024 | E90: 31-03-2024 - Due by 31-07-2024 | G90: Have records but not submitted | H90: Company | I90: 45382 | J90: 45504
A91: 89 | B91: https://crd-app.companiesoffice.govt.nz/dashboard/reportingentity/?id=276c5ca5-8394-ee11-be37-00224892b34a | C91: RAKON LIMITED | D91: Reporting Period . sort descending Actions 31-03-2024 - Due by 31-07-2024 | E91: 31-03-2024 - Due by 31-07-2024 | G91: Have records but not submitted | H91: Company | I91: 45382 | J91: 45504
A92: 90 | B92: https://crd-app.companiesoffice.govt.nz/dashboard/reportingentity/?id=9f6b5ca5-8394-ee11-be37-00224892b34a | C92: RESOLUTION LIFE AUSTRALASIA LIMITED | D92: Reporting Period . sort descending Actions 31-12-2023 - Due by 30-04-2024 | E92: 31-12-2023 - Due by 30-04-2024 | G92: Have records but not submitted | H92: Company | I92: 45291 | J92: 45412
A93: 91 | B93: https://crd-app.companiesoffice.govt.nz/dashboard/reportingentity/?id=296c5ca5-8394-ee11-be37-00224892b34a | C93: RESTAURANT BRANDS NEW ZEALAND LIMITED | D93: Reporting Period . sort descending Actions 31-12-2023 - Due by 30-04-2024 | E93: 31-12-2023 - Due by 30-04-2024 | G93: Have records but not submitted | H93: Company | I93: 45291 | J93: 45412
A94: 92 | B94: https://crd-app.companiesoffice.govt.nz/dashboard/reportingentity/?id=2b6c5ca5-8394-ee11-be37-00224892b34a | C94: RYMAN HEALTHCARE LIMITED | D94: Reporting Period . sort descending Actions 31-03-2024 - Due by 31-07-2024 | E94: 31-03-2024 - Due by 31-07-2024 | G94: Have records but not submitted | H94: Company | I94: 45382 | J94: 45504
A95: 93 | B95: https://crd-app.companiesoffice.govt.nz/dashboard/reportingentity/?id=2d6c5ca5-8394-ee11-be37-00224892b34a | C95: SCALES CORPORATION LIMITED | D95: Reporting Period . sort descending Actions 31-12-2023 - Due by 30-04-2024 | E95: 31-12-2023 - Due by 30-04-2024 | G95: Have records but not submitted | H95: Company | I95: 45291 | J95: 45412
A96: 94 | B96: https://crd-app.companiesoffice.govt.nz/dashboard/reportingentity/?id=2f6c5ca5-8394-ee11-be37-00224892b34a | C96: SEEKA LIMITED | D96: Reporting Period . sort descending Actions 31-12-2023 - Click to view Climate Statement/s | E96: 31-12-2023 - Click to view Climate Statement/s | G96: Have records and have submitted | H96: Company | I96: no data | J96: no data
A97: 95 | B97: https://crd-app.companiesoffice.govt.nz/dashboard/reportingentity/?id=316c5ca5-8394-ee11-be37-00224892b34a | C97: SERKO LIMITED | D97: Reporting Period . sort descending Actions 31-03-2024 - Due by 31-07-2024 | E97: 31-03-2024 - Due by 31-07-2024 | G97: Have records but not submitted | H97: Company | I97: 45382 | J97: 45504
A98: 96 | B98: https://crd-app.companiesoffice.govt.nz/dashboard/reportingentity/?id=336c5ca5-8394-ee11-be37-00224892b34a | C98: SKELLERUP HOLDINGS LIMITED | D98: Reporting Period . sort descending Actions There are no records to display. | E98: There are no records to display. | G98: No records | H98: Company | I98: no data | J98: no data
A99: 97 | B99: https://crd-app.companiesoffice.govt.nz/dashboard/reportingentity/?id=356c5ca5-8394-ee11-be37-00224892b34a | C99: SKY NETWORK TELEVISION LIMITED | D99: Reporting Period . sort descending Actions There are no records to display. | E99: There are no records to display. | G99: No records | H99: Company | I99: no data | J99: no data
A100: 98 | B100: https://crd-app.companiesoffice.govt.nz/dashboard/reportingentity/?id=376c5ca5-8394-ee11-be37-00224892b34a | C100: SKYCITY ENTERTAINMENT GROUP LIMITED | D100: Reporting Period . sort descending Actions There are no records to display. | E100: There are no records to display. | G100: No records | H100: Company | I100: no data | J100: no data
...

Sheet 1.master_list_7May
B1: Link | C1: Company Name | D1: Text | E1: text_new | F1: Scheme Name | G1: status | H1: scheme | I1: Due Date | J1: Submit Date | K1: Status on April
A2: 0 | B2: https://crd-app.companiesoffice.govt.nz/dashboard/reportingentity/?id=8b6b5ca5-8394-ee11-be37-00224892b34a | C2: AA INSURANCE LIMITED | D2: Reporting Period . sort descending Actions There are no records to display. | E2: There are no records to display. | G2: No records | H2: Company | K2: =VLOOKUP(B2,'20April'!B:G,6,0) -> No records
A3: 1 | B3: https://crd-app.companiesoffice.govt.nz/dashboard/reportingentity/?id=a96b5ca5-8394-ee11-be37-00224892b34a | C3: AFT PHARMACEUTICALS LIMITED | D3: Reporting Period . sort descending Actions 31-03-2024 - Due by 31-07-2024 | E3: 31-03-2024 - Due by 31-07-2024 | G3: Have records but not submitted | H3: Company | I3: 45382 | J3: 45504 | K3: =VLOOKUP(B3,'20April'!B:G,6,0) -> Have records but not submitted
A4: 2 | B4: https://crd-app.companiesoffice.govt.nz/dashboard/reportingentity/?id=8d6b5ca5-8394-ee11-be37-00224892b34a | C4: AIA NEW ZEALAND LIMITED | D4: Reporting Period . sort descending Actions 31-12-2023 - Click to view Climate Statement/s | E4: 31-12-2023 - Click to view Climate Statement/s | G4: Have records and have submitted | H4: Company | K4: =VLOOKUP(B4,'20April'!B:G,6,0) -> Have records but not submitted
A5: 3 | B5: https://crd-app.companiesoffice.govt.nz/dashboard/reportingentity/?id=ab6b5ca5-8394-ee11-be37-00224892b34a | C5: AIR NEW ZEALAND LIMITED | D5: Reporting Period . sort descending Actions There are no records to display. | E5: There are no records to display. | G5: No records | H5: Company | K5: =VLOOKUP(B5,'20April'!B:G,6,0) -> No records
A6: 135 | B6: https://crd-app.companiesoffice.govt.nz/dashboard/reportingentity/scheme/?id=ff5ba035-8a94-ee11-be37-00224892b34a&refentity=mbie_reportingentity&refid=696c5ca5-8394-ee11-be37-00224892b34a&refrel=mbie_Scheme_ReportingEntityId_mbie_Report | C6: AMP WEALTH MANAGEMENT NEW ZEALAND LIMITED | D6: Reporting Period . sort descending Actions 31-03-2024 - Due by 31-07-2024 | E6: 31-03-2024 - Due by 31-07-2024 | F6: AMP INVESTMENT TRUST (SCH10721) | G6: Have records but not submitted | H6: Investment Scheme | I6: 45382 | J6: 45504 | K6: =VLOOKUP(B6,'20April'!B:G,6,0) -> Have records but not submitted
A7: 136 | B7: https://crd-app.companiesoffice.govt.nz/dashboard/reportingentity/scheme/?id=fd5ba035-8a94-ee11-be37-00224892b34a&refentity=mbie_reportingentity&refid=696c5ca5-8394-ee11-be37-00224892b34a&refrel=mbie_Scheme_ReportingEntityId_mbie_Report | C7: AMP WEALTH MANAGEMENT NEW ZEALAND LIMITED | D7: Reporting Period . sort descending Actions 31-03-2024 - Due by 31-07-2024 | E7: 31-03-2024 - Due by 31-07-2024 | F7: AMP KIWISAVER SCHEME (SCH10367) | G7: Have records but not submitted | H7: Investment Scheme | I7: 45382 | J7: 45504 | K7: =VLOOKUP(B7,'20April'!B:G,6,0) -> Have records but not submitted
A8: 137 | B8: https://crd-app.companiesoffice.govt.nz/dashboard/reportingentity/scheme/?id=095ca035-8a94-ee11-be37-00224892b34a&refentity=mbie_reportingentity&refid=696c5ca5-8394-ee11-be37-00224892b34a&refrel=mbie_Scheme_ReportingEntityId_mbie_Report | C8: AMP WEALTH MANAGEMENT NEW ZEALAND LIMITED | D8: Reporting Period . sort descending Actions 31-03-2024 - Due by 31-07-2024 | E8: 31-03-2024 - Due by 31-07-2024 | F8: AMP MANAGED FUNDS (SCH13265) | G8: Have records but not submitted | H8: Investment Scheme | I8: 45382 | J8: 45504 | K8: =VLOOKUP(B8,'20April'!B:G,6,0) -> Have records but not submitted
A9: 138 | B9: https://crd-app.companiesoffice.govt.nz/dashboard/reportingentity/scheme/?id=035ca035-8a94-ee11-be37-00224892b34a&refentity=mbie_reportingentity&refid=696c5ca5-8394-ee11-be37-00224892b34a&refrel=mbie_Scheme_ReportingEntityId_mbie_Report | C9: AMP WEALTH MANAGEMENT NEW ZEALAND LIMITED | D9: Reporting Period . sort descending Actions 31-03-2024 - Due by 31-07-2024 | E9: 31-03-2024 - Due by 31-07-2024 | F9: AMP PASSIVE PERSONAL RETIREMENT PLAN - INTERNATIONAL PASSIVE SHARES INVESTMENT FUND (SCH10821) | G9: Have records but not submitted | H9: Investment Scheme | I9: 45382 | J9: 45504 | K9: =VLOOKUP(B9,'20April'!B:G,6,0) -> Have records but not submitted
A10: 139 | B10: https://crd-app.companiesoffice.govt.nz/dashboard/reportingentity/scheme/?id=055ca035-8a94-ee11-be37-00224892b34a&refentity=mbie_reportingentity&refid=696c5ca5-8394-ee11-be37-00224892b34a&refrel=mbie_Scheme_ReportingEntityId_mbie_Report | C10: AMP WEALTH MANAGEMENT NEW ZEALAND LIMITED | D10: Reporting Period . sort descending Actions 31-03-2024 - Due by 31-07-2024 | E10: 31-03-2024 - Due by 31-07-2024 | F10: AMP PASSIVE PERSONAL RETIREMENT PLAN - NEW ZEALAND PASSIVE SHARES INVESTMENT FUND (SCH10822) | G10: Have records but not submitted | H10: Investment Scheme | I10: 45382 | J10: 45504 | K10: =VLOOKUP(B10,'20April'!B:G,6,0) -> Have records but not submitted
A11: 140 | B11: https://crd-app.companiesoffice.govt.nz/dashboard/reportingentity/scheme/?id=015ca035-8a94-ee11-be37-00224892b34a&refentity=mbie_reportingentity&refid=696c5ca5-8394-ee11-be37-00224892b34a&refrel=mbie_Scheme_ReportingEntityId_mbie_Report | C11: AMP WEALTH MANAGEMENT NEW ZEALAND LIMITED | D11: Reporting Period . sort descending Actions 31-03-2024 - Due by 31-07-2024 | E11: 31-03-2024 - Due by 31-07-2024 | F11: AMP PERSONAL RETIREMENT PLAN (SCH10820) | G11: Have records but not submitted | H11: Investment Scheme | I11: 45382 | J11: 45504 | K11: =VLOOKUP(B11,'20April'!B:G,6,0) -> Have records but not submitted
A12: 141 | B12: https://crd-app.companiesoffice.govt.nz/dashboard/reportingentity/scheme/?id=075ca035-8a94-ee11-be37-00224892b34a&refentity=mbie_reportingentity&refid=696c5ca5-8394-ee11-be37-00224892b34a&refrel=mbie_Scheme_ReportingEntityId_mbie_Report | C12: AMP WEALTH MANAGEMENT NEW ZEALAND LIMITED | D12: Reporting Period . sort descending Actions There are no records to display. | E12: There are no records to display. | F12: NEW ZEALAND RETIREMENT TRUST (SCH10911) | G12: No records | H12: Investment Scheme | K12: =VLOOKUP(B12,'20April'!B:G,6,0) -> No records
A13: 142 | B13: https://crd-app.companiesoffice.govt.nz/dashboard/reportingentity/scheme/?id=0b5ca035-8a94-ee11-be37-00224892b34a&refentity=mbie_reportingentity&refid=6b6c5ca5-8394-ee11-be37-00224892b34a&refrel=mbie_Scheme_ReportingEntityId_mbie_Report | C13: ANZ INVESTMENT SERVICES (NEW ZEALAND) LIMITED | D13: Reporting Period . sort descending Actions 31-03-2024 - Due by 31-07-2024 | E13: 31-03-2024 - Due by 31-07-2024 | F13: BONUS BONDS SCHEME (SCH11094) | G13: Have records but not submitted | H13: Investment Scheme | I13: 45382 | J13: 45504 | K13: =VLOOKUP(B13,'20April'!B:G,6,0) -> Have records but not submitted
A14: 143 | B14: https://crd-app.companiesoffice.govt.nz/dashboard/reportingentity/scheme/?id=115ca035-8a94-ee11-be37-00224892b34a&refentity=mbie_reportingentity&refid=6d6c5ca5-8394-ee11-be37-00224892b34a&refrel=mbie_Scheme_ReportingEntityId_mbie_Report | C14: ANZ NEW ZEALAND INVESTMENTS LIMITED | D14: Reporting Period . sort descending Actions 31-03-2024 - Due by 31-07-2024 | E14: 31-03-2024 - Due by 31-07-2024 | F14: ANZ DEFAULT KIWISAVER SCHEME (SCH11063) | G14: Have records but not submitted | H14: Investment Scheme | I14: 45382 | J14: 45504 | K14: =VLOOKUP(B14,'20April'!B:G,6,0) -> Have records but not submitted
A15: 145 | B15: https://crd-app.companiesoffice.govt.nz/dashboard/reportingentity/scheme/?id=155ca035-8a94-ee11-be37-00224892b34a&refentity=mbie_reportingentity&refid=6d6c5ca5-8394-ee11-be37-00224892b34a&refrel=mbie_Scheme_ReportingEntityId_mbie_Report | C15: ANZ NEW ZEALAND INVESTMENTS LIMITED | D15: Reporting Period . sort descending Actions 31-03-2024 - Due by 31-07-2024 | E15: 31-03-2024 - Due by 31-07-2024 | F15: ANZ INVESTMENTS SINGLE-ASSET-CLASS SCHEME (MARKETED AS THE ONEANSWER SINGLE-ASSET-CLASS FUNDS) (SCH11065) | G15: Have records but not submitted | H15: Investment Scheme | I15: 45382 | J15: 45504 | K15: =VLOOKUP(B15,'20April'!B:G,6,0) -> Have records but not submitted
A16: 146 | B16: https://crd-app.companiesoffice.govt.nz/dashboard/reportingentity/scheme/?id=0f5ca035-8a94-ee11-be37-00224892b34a&refentity=mbie_reportingentity&refid=6d6c5ca5-8394-ee11-be37-00224892b34a&refrel=mbie_Scheme_ReportingEntityId_mbie_Report | C16: ANZ NEW ZEALAND INVESTMENTS LIMITED | D16: Reporting Period . sort descending Actions 31-03-2024 - Due by 31-07-2024 | E16: 31-03-2024 - Due by 31-07-2024 | F16: ANZ KIWISAVER SCHEME (SCH11062) | G16: Have records but not submitted | H16: Investment Scheme | I16: 45382 | J16: 45504 | K16: =VLOOKUP(B16,'20April'!B:G,6,0) -> Have records but not submitted
A17: 147 | B17: https://crd-app.companiesoffice.govt.nz/dashboard/reportingentity/scheme/?id=0d5ca035-8a94-ee11-be37-00224892b34a&refentity=mbie_reportingentity&refid=6d6c5ca5-8394-ee11-be37-00224892b34a&refrel=mbie_Scheme_ReportingEntityId_mbie_Report | C17: ANZ NEW ZEALAND INVESTMENTS LIMITED | D17: Reporting Period . sort descending Actions 31-03-2024 - Due by 31-07-2024 | E17: 31-03-2024 - Due by 31-07-2024 | F17: ONEANSWER KIWISAVER SCHEME (SCH11061) | G17: Have records but not submitted | H17: Investment Scheme | I17: 45382 | J17: 45504 | K17: =VLOOKUP(B17,'20April'!B:G,6,0) -> Have records but not submitted
A18: 144 | B18: https://crd-app.companiesoffice.govt.nz/dashboard/reportingentity/scheme/?id=135ca035-8a94-ee11-be37-00224892b34a&refentity=mbie_reportingentity&refid=6d6c5ca5-8394-ee11-be37-00224892b34a&refrel=mbie_Scheme_ReportingEntityId_mbie_Report | C18: ANZ NEW ZEALAND INVESTMENTS LIMITED | D18: Reporting Period . sort descending Actions There are no records to display. | E18: There are no records to display. | F18: ANZ INVESTMENTS MULTI-ASSET-CLASS SCHEME (MARKETED AS THE ANZ INVESTMENT FUNDS AND ONEANSWER MULTI-ASSET-CLASS FUNDS) (SCH11064) | G18: No records | H18: Investment Scheme | K18: =VLOOKUP(B18,'20April'!B:G,6,0) -> No records
A19: 4 | B19: https://crd-app.companiesoffice.govt.nz/dashboard/reportingentity/?id=ad6b5ca5-8394-ee11-be37-00224892b34a | C19: ARBORGEN HOLDINGS LIMITED | D19: Reporting Period . sort descending Actions 31-03-2024 - Due by 31-07-2024 | E19: 31-03-2024 - Due by 31-07-2024 | G19: Have records but not submitted | H19: Company | I19: 45382 | J19: 45504 | K19: =VLOOKUP(B19,'20April'!B:G,6,0) -> Have records but not submitted
A20: 5 | B20: https://crd-app.companiesoffice.govt.nz/dashboard/reportingentity/?id=af6b5ca5-8394-ee11-be37-00224892b34a | C20: ARGOSY PROPERTY LIMITED | D20: Reporting Period . sort descending Actions 31-03-2024 - Due by 31-07-2024 | E20: 31-03-2024 - Due by 31-07-2024 | G20: Have records but not submitted | H20: Company | I20: 45382 | J20: 45504 | K20: =VLOOKUP(B20,'20April'!B:G,6,0) -> Have records but not submitted
A21: 6 | B21: https://crd-app.companiesoffice.govt.nz/dashboard/reportingentity/?id=b16b5ca5-8394-ee11-be37-00224892b34a | C21: ARVIDA GROUP LIMITED | D21: Reporting Period . sort descending Actions 31-03-2024 - Due by 31-07-2024 | E21: 31-03-2024 - Due by 31-07-2024 | G21: Have records but not submitted | H21: Company | I21: 45382 | J21: 45504 | K21: =VLOOKUP(B21,'20April'!B:G,6,0) -> Have records but not submitted
A22: 7 | B22: https://crd-app.companiesoffice.govt.nz/dashboard/reportingentity/?id=656b5ca5-8394-ee11-be37-00224892b34a | C22: ASB BANK LIMITED | D22: Reporting Period . sort descending Actions There are no records to display. | E22: There are no records to display. | G22: No records | H22: Company | K22: =VLOOKUP(B22,'20April'!B:G,6,0) -> No records
A23: 148 | B23: https://crd-app.companiesoffice.govt.nz/dashboard/reportingentity/scheme/?id=195ca035-8a94-ee11-be37-00224892b34a&refentity=mbie_reportingentity&refid=6f6c5ca5-8394-ee11-be37-00224892b34a&refrel=mbie_Scheme_ReportingEntityId_mbie_Report | C23: ASB GROUP INVESTMENTS LIMITED | D23: Reporting Period . sort descending Actions 31-03-2024 - Due by 31-07-2024 | E23: 31-03-2024 - Due by 31-07-2024 | F23: ASB INVESTMENT FUNDS (SCH10685) | G23: Have records but not submitted | H23: Investment Scheme | I23: 45382 | J23: 45504 | K23: =VLOOKUP(B23,'20April'!B:G,6,0) -> Have records but not submitted
A24: 149 | B24: https://crd-app.companiesoffice.govt.nz/dashboard/reportingentity/scheme/?id=175ca035-8a94-ee11-be37-00224892b34a&refentity=mbie_reportingentity&refid=6f6c5ca5-8394-ee11-be37-00224892b34a&refrel=mbie_Scheme_ReportingEntityId_mbie_Report | C24: ASB GROUP INVESTMENTS LIMITED | D24: Reporting Period . sort descending Actions 31-03-2024 - Due by 31-07-2024 | E24: 31-03-2024 - Due by 31-07-2024 | F24: ASB KIWISAVER SCHEME (SCH10678) | G24: Have records but not submitted | H24: Investment Scheme | I24: 45382 | J24: 45504 | K24: =VLOOKUP(B24,'20April'!B:G,6,0) -> Have records but not submitted
A25: 8 | B25: https://crd-app.companiesoffice.govt.nz/dashboard/reportingentity/?id=b36b5ca5-8394-ee11-be37-00224892b34a | C25: ASSET PLUS LIMITED | D25: Reporting Period . sort descending Actions 31-03-2024 - Due by 31-07-2024 | E25: 31-03-2024 - Due by 31-07-2024 | G25: Have records but not submitted | H25: Company | I25: 45382 | J25: 45504 | K25: =VLOOKUP(B25,'20April'!B:G,6,0) -> Have records but not submitted
A26: 9 | B26: https://crd-app.companiesoffice.govt.nz/dashboard/reportingentity/?id=8f6b5ca5-8394-ee11-be37-00224892b34a | C26: ASTERON LIFE LIMITED | D26: Reporting Period . sort descending Actions There are no records to display. | E26: There are no records to display. | G26: No records | H26: Company | K26: =VLOOKUP(B26,'20April'!B:G,6,0) -> No records
A27: 10 | B27: https://crd-app.companiesoffice.govt.nz/dashboard/reportingentity/?id=b56b5ca5-8394-ee11-be37-00224892b34a | C27: AUCKLAND COUNCIL | D27: Reporting Period . sort descending Actions There are no records to display. | E27: There are no records to display. | G27: No records | H27: Company | K27: =VLOOKUP(B27,'20April'!B:G,6,0) -> No records
A28: 11 | B28: https://crd-app.companiesoffice.govt.nz/dashboard/reportingentity/?id=b76b5ca5-8394-ee11-be37-00224892b34a | C28: AUCKLAND INTERNATIONAL AIRPORT LIMITED | D28: Reporting Period . sort descending Actions There are no records to display. | E28: There are no records to display. | G28: No records | H28: Company | K28: =VLOOKUP(B28,'20April'!B:G,6,0) -> No records
A29: 12 | B29: https://crd-app.companiesoffice.govt.nz/dashboard/reportingentity/?id=b96b5ca5-8394-ee11-be37-00224892b34a | C29: AUSTRALIAN FOUNDATION INVESTMENT COMPANY LIMITED | D29: Reporting Period . sort descending Actions There are no records to display. | E29: There are no records to display. | G29: No records | H29: Company | K29: =VLOOKUP(B29,'20April'!B:G,6,0) -> No records
A30: 13 | B30: https://crd-app.companiesoffice.govt.nz/dashboard/reportingentity/?id=676b5ca5-8394-ee11-be37-00224892b34a | C30: BANK OF CHINA (NEW ZEALAND) LIMITED | D30: Reporting Period . sort descending Actions 31-12-2023 - Click to view Climate Statement/s | E30: 31-12-2023 - Click to view Climate Statement/s | G30: Have records and have submitted | H30: Company | K30: =VLOOKUP(B30,'20April'!B:G,6,0) -> Have records but not submitted
A31: 14 | B31: https://crd-app.companiesoffice.govt.nz/dashboard/reportingentity/?id=696b5ca5-8394-ee11-be37-00224892b34a | C31: BANK OF CHINA LIMITED | D31: Reporting Period . sort descending Actions 31-12-2023 - Due by 30-04-2024 | E31: 31-12-2023 - Due by 30-04-2024 | G31: Have records but not submitted | H31: Company | I31: 45291 | J31: 45412 | K31: =VLOOKUP(B31,'20April'!B:G,6,0) -> Have records but not submitted
A32: 15 | B32: https://crd-app.companiesoffice.govt.nz/dashboard/reportingentity/?id=bb6b5ca5-8394-ee11-be37-00224892b34a | C32: BARRAMUNDI LIMITED | D32: Reporting Period . sort descending Actions There are no records to display. | E32: There are no records to display. | G32: No records | H32: Company | K32: =VLOOKUP(B32,'20April'!B:G,6,0) -> No records
A33: 150 | B33: https://crd-app.companiesoffice.govt.nz/dashboard/reportingentity/scheme/?id=1b5ca035-8a94-ee11-be37-00224892b34a&refentity=mbie_reportingentity&refid=716c5ca5-8394-ee11-be37-00224892b34a&refrel=mbie_Scheme_ReportingEntityId_mbie_Report | C33: BNZ INVESTMENT SERVICES LIMITED | D33: Reporting Period . sort descending Actions 31-03-2024 - Due by 31-07-2024 | E33: 31-03-2024 - Due by 31-07-2024 | F33: BNZ KIWISAVER SCHEME (SCH10701) | G33: Have records but not submitted | H33: Investment Scheme | I33: 45382 | J33: 45504 | K33: =VLOOKUP(B33,'20April'!B:G,6,0) -> Have records but not submitted
A34: 151 | B34: https://crd-app.companiesoffice.govt.nz/dashboard/reportingentity/scheme/?id=1d5ca035-8a94-ee11-be37-00224892b34a&refentity=mbie_reportingentity&refid=716c5ca5-8394-ee11-be37-00224892b34a&refrel=mbie_Scheme_ReportingEntityId_mbie_Report | C34: BNZ INVESTMENT SERVICES LIMITED | D34: Reporting Period . sort descending Actions 31-03-2024 - Due by 31-07-2024 | E34: 31-03-2024 - Due by 31-07-2024 | F34: PRIVATE WEALTH SERIES (SCH11384) | G34: Have records but not submitted | H34: Investment Scheme | I34: 45382 | J34: 45504 | K34: =VLOOKUP(B34,'20April'!B:G,6,0) -> Have records but not submitted
A35: 152 | B35: https://crd-app.companiesoffice.govt.nz/dashboard/reportingentity/scheme/?id=1f5ca035-8a94-ee11-be37-00224892b34a&refentity=mbie_reportingentity&refid=716c5ca5-8394-ee11-be37-00224892b34a&refrel=mbie_Scheme_ReportingEntityId_mbie_Report | C35: BNZ INVESTMENT SERVICES LIMITED | D35: Reporting Period . sort descending Actions 31-03-2024 - Due by 31-07-2024 | E35: 31-03-2024 - Due by 31-07-2024 | F35: YOUWEALTH (SCH12341) | G35: Have records but not submitted | H35: Investment Scheme | I35: 45382 | J35: 45504 | K35: =VLOOKUP(B35,'20April'!B:G,6,0) -> Have records but not submitted
A36: 153 | B36: https://crd-app.companiesoffice.govt.nz/dashboard/reportingentity/scheme/?id=295ca035-8a94-ee11-be37-00224892b34a&refentity=mbie_reportingentity&refid=736c5ca5-8394-ee11-be37-00224892b34a&refrel=mbie_Scheme_ReportingEntityId_mbie_Report | C36: BOOSTER INVESTMENT MANAGEMENT LIMITED | D36: Reporting Period . sort descending Actions 31-03-2024 - Due by 31-07-2024 | E36: 31-03-2024 - Due by 31-07-2024 | F36: BOOSTER INNOVATION SCHEME (SCH13202) | G36: Have records but not submitted | H36: Investment Scheme | I36: 45382 | J36: 45504 | K36: =VLOOKUP(B36,'20April'!B:G,6,0) -> Have records but not submitted
A37: 154 | B37: https://crd-app.companiesoffice.govt.nz/dashboard/reportingentity/scheme/?id=235ca035-8a94-ee11-be37-00224892b34a&refentity=mbie_reportingentity&refid=736c5ca5-8394-ee11-be37-00224892b34a&refrel=mbie_Scheme_ReportingEntityId_mbie_Report | C37: BOOSTER INVESTMENT MANAGEMENT LIMITED | D37: Reporting Period . sort descending Actions 31-03-2024 - Due by 31-07-2024 | E37: 31-03-2024 - Due by 31-07-2024 | F37: BOOSTER INVESTMENT SCHEME (SCH10844) | G37: Have records but not submitted | H37: Investment Scheme | I37: 45382 | J37: 45504 | K37: =VLOOKUP(B37,'20April'!B:G,6,0) -> Have records but not submitted
A38: 155 | B38: https://crd-app.companiesoffice.govt.nz/dashboard/reportingentity/scheme/?id=275ca035-8a94-ee11-be37-00224892b34a&refentity=mbie_reportingentity&refid=736c5ca5-8394-ee11-be37-00224892b34a&refrel=mbie_Scheme_ReportingEntityId_mbie_Report | C38: BOOSTER INVESTMENT MANAGEMENT LIMITED | D38: Reporting Period . sort descending Actions 31-03-2024 - Due by 31-07-2024 | E38: 31-03-2024 - Due by 31-07-2024 | F38: BOOSTER INVESTMENT SCHEME 2 (SCH12548) | G38: Have records but not submitted | H38: Investment Scheme | I38: 45382 | J38: 45504 | K38: =VLOOKUP(B38,'20April'!B:G,6,0) -> Have records but not submitted
A39: 156 | B39: https://crd-app.companiesoffice.govt.nz/dashboard/reportingentity/scheme/?id=215ca035-8a94-ee11-be37-00224892b34a&refentity=mbie_reportingentity&refid=736c5ca5-8394-ee11-be37-00224892b34a&refrel=mbie_Scheme_ReportingEntityId_mbie_Report | C39: BOOSTER INVESTMENT MANAGEMENT LIMITED | D39: Reporting Period . sort descending Actions 31-03-2024 - Due by 31-07-2024 | E39: 31-03-2024 - Due by 31-07-2024 | F39: BOOSTER KIWISAVER SCHEME (SCH10841) | G39: Have records but not submitted | H39: Investment Scheme | I39: 45382 | J39: 45504 | K39: =VLOOKUP(B39,'20April'!B:G,6,0) -> Have records but not submitted
A40: 157 | B40: https://crd-app.companiesoffice.govt.nz/dashboard/reportingentity/scheme/?id=2b5ca035-8a94-ee11-be37-00224892b34a&refentity=mbie_reportingentity&refid=736c5ca5-8394-ee11-be37-00224892b34a&refrel=mbie_Scheme_ReportingEntityId_mbie_Report | C40: BOOSTER INVESTMENT MANAGEMENT LIMITED | D40: Reporting Period . sort descending Actions 31-03-2024 - Due by 31-07-2024 | E40: 31-03-2024 - Due by 31-07-2024 | F40: BOOSTER SAVVY SCHEME (SCH13546) | G40: Have records but not submitted | H40: Investment Scheme | I40: 45382 | J40: 45504 | K40: =VLOOKUP(B40,'20April'!B:G,6,0) -> Have records but not submitted
A41: 158 | B41: https://crd-app.companiesoffice.govt.nz/dashboard/reportingentity/scheme/?id=255ca035-8a94-ee11-be37-00224892b34a&refentity=mbie_reportingentity&refid=736c5ca5-8394-ee11-be37-00224892b34a&refrel=mbie_Scheme_ReportingEntityId_mbie_Report | C41: BOOSTER INVESTMENT MANAGEMENT LIMITED | D41: Reporting Period . sort descending Actions 31-03-2024 - Due by 31-07-2024 | E41: 31-03-2024 - Due by 31-07-2024 | F41: BOOSTER SUPERSCHEME (SCH11323) | G41: Have records but not submitted | H41: Investment Scheme | I41: 45382 | J41: 45504 | K41: =VLOOKUP(B41,'20April'!B:G,6,0) -> Have records but not submitted
A42: 16 | B42: https://crd-app.companiesoffice.govt.nz/dashboard/reportingentity/?id=bd6b5ca5-8394-ee11-be37-00224892b34a | C42: BRISCOE GROUP LIMITED | D42: Reporting Period . sort descending Actions 31-01-2024 - Click to view Climate Statement/s | E42: 31-01-2024 - Click to view Climate Statement/s | G42: Have records and have submitted | H42: Company | K42: =VLOOKUP(B42,'20April'!B:G,6,0) -> Have records and have submitted
A43: 159 | B43: https://crd-app.companiesoffice.govt.nz/dashboard/reportingentity/scheme/?id=2d5ca035-8a94-ee11-be37-00224892b34a&refentity=mbie_reportingentity&refid=756c5ca5-8394-ee11-be37-00224892b34a&refrel=mbie_Scheme_ReportingEntityId_mbie_Report | C43: BT FUNDS MANAGEMENT (NZ) LIMITED | D43: Reporting Period . sort descending Actions 31-03-2024 - Due by 31-07-2024 | E43: 31-03-2024 - Due by 31-07-2024 | F43: WESTPAC ACTIVE SERIES (SCH10564) | G43: Have records but not submitted | H43: Investment Scheme | I43: 45382 | J43: 45504 | K43: =VLOOKUP(B43,'20April'!B:G,6,0) -> Have records but not submitted
A44: 160 | B44: https://crd-app.companiesoffice.govt.nz/dashboard/reportingentity/scheme/?id=2f5ca035-8a94-ee11-be37-00224892b34a&refentity=mbie_reportingentity&refid=756c5ca5-8394-ee11-be37-00224892b34a&refrel=mbie_Scheme_ReportingEntityId_mbie_Report | C44: BT FUNDS MANAGEMENT (NZ) LIMITED | D44: Reporting Period . sort descending Actions 31-03-2024 - Due by 31-07-2024 | E44: 31-03-2024 - Due by 31-07-2024 | F44: WESTPAC KIWISAVER SCHEME (SCH10585) | G44: Have records but not submitted | H44: Investment Scheme | I44: 45382 | J44: 45504 | K44: =VLOOKUP(B44,'20April'!B:G,6,0) -> Have records but not submitted
A45: 161 | B45: https://crd-app.companiesoffice.govt.nz/dashboard/reportingentity/scheme/?id=315ca035-8a94-ee11-be37-00224892b34a&refentity=mbie_reportingentity&refid=756c5ca5-8394-ee11-be37-00224892b34a&refrel=mbie_Scheme_ReportingEntityId_mbie_Report | C45: BT FUNDS MANAGEMENT (NZ) LIMITED | D45: Reporting Period . sort descending Actions 31-03-2024 - Due by 31-07-2024 | E45: 31-03-2024 - Due by 31-07-2024 | F45: WESTPAC PREMIUM INVESTMENT FUNDS (SCH10817) | G45: Have records but not submitted | H45: Investment Scheme | I45: 45382 | J45: 45504 | K45: =VLOOKUP(B45,'20April'!B:G,6,0) -> Have records but not submitted
A46: 162 | B46: https://crd-app.companiesoffice.govt.nz/dashboard/reportingentity/scheme/?id=335ca035-8a94-ee11-be37-00224892b34a&refentity=mbie_reportingentity&refid=756c5ca5-8394-ee11-be37-00224892b34a&refrel=mbie_Scheme_ReportingEntityId_mbie_Report | C46: BT FUNDS MANAGEMENT (NZ) LIMITED | D46: Reporting Period . sort descending Actions 31-03-2024 - Due by 31-07-2024 | E46: 31-03-2024 - Due by 31-07-2024 | F46: WESTPAC RETIREMENT PLAN (SCH11614) | G46: Have records but not submitted | H46: Investment Scheme | I46: 45382 | J46: 45504 | K46: =VLOOKUP(B46,'20April'!B:G,6,0) -> Have records but not submitted
A47: 17 | B47: https://crd-app.companiesoffice.govt.nz/dashboard/reportingentity/?id=bf6b5ca5-8394-ee11-be37-00224892b34a | C47: CDL INVESTMENTS NEW ZEALAND LIMITED | D47: Reporting Period . sort descending Actions 31-12-2023 - Click to view Climate Statement/s | E47: 31-12-2023 - Click to view Climate Statement/s | G47: Have records and have submitted | H47: Company | K47: =VLOOKUP(B47,'20April'!B:G,6,0) -> Have records and have submitted
A48: 163 | B48: https://crd-app.companiesoffice.govt.nz/dashboard/reportingentity/scheme/?id=5b5ca035-8a94-ee11-be37-00224892b34a&refentity=mbie_reportingentity&refid=776c5ca5-8394-ee11-be37-00224892b34a&refrel=mbie_Scheme_ReportingEntityId_mbie_Report | C48: CENTURIA FUNDS MANAGEMENT (NZ) LIMITED | D48: Reporting Period . sort descending Actions 31-03-2024 - Due by 31-07-2024 | E48: 31-03-2024 - Due by 31-07-2024 | F48: 33 BROADWAY TRUST (SCH11912) | G48: Have records but not submitted | H48: Investment Scheme | I48: 45382 | J48: 45504 | K48: =VLOOKUP(B48,'20April'!B:G,6,0) -> Have records but not submitted
A49: 164 | B49: https://crd-app.companiesoffice.govt.nz/dashboard/reportingentity/scheme/?id=595ca035-8a94-ee11-be37-00224892b34a&refentity=mbie_reportingentity&refid=776c5ca5-8394-ee11-be37-00224892b34a&refrel=mbie_Scheme_ReportingEntityId_mbie_Report | C49: CENTURIA FUNDS MANAGEMENT (NZ) LIMITED | D49: Reporting Period . sort descending Actions 31-03-2024 - Due by 31-07-2024 | E49: 31-03-2024 - Due by 31-07-2024 | F49: AIRPARK NOMINEES JOINT VENTURE (SCH11740) | G49: Have records but not submitted | H49: Investment Scheme | I49: 45382 | J49: 45504 | K49: =VLOOKUP(B49,'20April'!B:G,6,0) -> Have records but not submitted
A50: 166 | B50: https://crd-app.companiesoffice.govt.nz/dashboard/reportingentity/scheme/?id=5f5ca035-8a94-ee11-be37-00224892b34a&refentity=mbie_reportingentity&refid=776c5ca5-8394-ee11-be37-00224892b34a&refrel=mbie_Scheme_ReportingEntityId_mbie_Report | C50: CENTURIA FUNDS MANAGEMENT (NZ) LIMITED | D50: Reporting Period . sort descending Actions 31-03-2024 - Due by 31-07-2024 | E50: 31-03-2024 - Due by 31-07-2024 | F50: AUGUSTA ST GEORGES BAY ROAD PROPERTY TRUST (SCH12448) | G50: Have records but not submitted | H50: Investment Scheme | I50: 45382 | J50: 45504 | K50: =VLOOKUP(B50,'20April'!B:G,6,0) -> Have records but not submitted
A51: 167 | B51: https://crd-app.companiesoffice.govt.nz/dashboard/reportingentity/scheme/?id=4d5ca035-8a94-ee11-be37-00224892b34a&refentity=mbie_reportingentity&refid=776c5ca5-8394-ee11-be37-00224892b34a&refrel=mbie_Scheme_ReportingEntityId_mbie_Report | C51: CENTURIA FUNDS MANAGEMENT (NZ) LIMITED | D51: Reporting Period . sort descending Actions 31-03-2024 - Due by 31-07-2024 | E51: 31-03-2024 - Due by 31-07-2024 | F51: BIRCH NOMINEES JOINT VENTURE (SCH11560) | G51: Have records but not submitted | H51: Investment Scheme | I51: 45382 | J51: 45504 | K51: =VLOOKUP(B51,'20April'!B:G,6,0) -> Have records but not submitted
A52: 169 | B52: https://crd-app.companiesoffice.govt.nz/dashboard/reportingentity/scheme/?id=375ca035-8a94-ee11-be37-00224892b34a&refentity=mbie_reportingentity&refid=776c5ca5-8394-ee11-be37-00224892b34a&refrel=mbie_Scheme_ReportingEntityId_mbie_Report | C52: CENTURIA FUNDS MANAGEMENT (NZ) LIMITED | D52: Reporting Period . sort descending Actions 31-03-2024 - Due by 31-07-2024 | E52: 31-03-2024 - Due by 31-07-2024 | F52: BUILDING A GRAHAM STREET LIMITED PARTNERSHIP (SCH10571) | G52: Have records but not submitted | H52: Investment Scheme | I52: 45382 | J52: 45504 | K52: =VLOOKUP(B52,'20April'!B:G,6,0) -> Have records but not submitted
A53: 170 | B53: https://crd-app.companiesoffice.govt.nz/dashboard/reportingentity/scheme/?id=395ca035-8a94-ee11-be37-00224892b34a&refentity=mbie_reportingentity&refid=776c5ca5-8394-ee11-be37-00224892b34a&refrel=mbie_Scheme_ReportingEntityId_mbie_Report | C53: CENTURIA FUNDS MANAGEMENT (NZ) LIMITED | D53: Reporting Period . sort descending Actions 31-03-2024 - Due by 31-07-2024 | E53: 31-03-2024 - Due by 31-07-2024 | F53: BUILDING B GRAHAM STREET LIMITED PARTNERSHIP (SCH10922) | G53: Have records but not submitted | H53: Investment Scheme | I53: 45382 | J53: 45504 | K53: =VLOOKUP(B53,'20April'!B:G,6,0) -> Have records but not submitted
A54: 171 | B54: https://crd-app.companiesoffice.govt.nz/dashboard/reportingentity/scheme/?id=635ca035-8a94-ee11-be37-00224892b34a&refentity=mbie_reportingentity&refid=776c5ca5-8394-ee11-be37-00224892b34a&refrel=mbie_Scheme_ReportingEntityId_mbie_Report | C54: CENTURIA FUNDS MANAGEMENT (NZ) LIMITED | D54: Reporting Period . sort descending Actions 31-03-2024 - Due by 31-07-2024 | E54: 31-03-2024 - Due by 31-07-2024 | F54: CENTURIA NZ PROPERTY FUND (SCH12900) | G54: Have records but not submitted | H54: Investment Scheme | I54: 45382 | J54: 45504 | K54: =VLOOKUP(B54,'20April'!B:G,6,0) -> Have records but not submitted
A55: 172 | B55: https://crd-app.companiesoffice.govt.nz/dashboard/reportingentity/scheme/?id=4f5ca035-8a94-ee11-be37-00224892b34a&refentity=mbie_reportingentity&refid=776c5ca5-8394-ee11-be37-00224892b34a&refrel=mbie_Scheme_ReportingEntityId_mbie_Report | C55: CENTURIA FUNDS MANAGEMENT (NZ) LIMITED | D55: Reporting Period . sort descending Actions 31-03-2024 - Due by 31-07-2024 | E55: 31-03-2024 - Due by 31-07-2024 | F55: FERNHILL NOMINEES JOINT VENTURE (SCH11564) | G55: Have records but not submitted | H55: Investment Scheme | I55: 45382 | J55: 45504 | K55: =VLOOKUP(B55,'20April'!B:G,6,0) -> Have records but not submitted
A56: 174 | B56: https://crd-app.companiesoffice.govt.nz/dashboard/reportingentity/scheme/?id=3d5ca035-8a94-ee11-be37-00224892b34a&refentity=mbie_reportingentity&refid=776c5ca5-8394-ee11-be37-00224892b34a&refrel=mbie_Scheme_ReportingEntityId_mbie_Report | C56: CENTURIA FUNDS MANAGEMENT (NZ) LIMITED | D56: Reporting Period . sort descending Actions 31-03-2024 - Due by 31-07-2024 | E56: 31-03-2024 - Due by 31-07-2024 | F56: HIBISCUS NOMINEES JOINT VENTURES (SCH11466) | G56: Have records but not submitted | H56: Investment Scheme | I56: 45382 | J56: 45504 | K56: =VLOOKUP(B56,'20April'!B:G,6,0) -> Have records but not submitted
A57: 175 | B57: https://crd-app.companiesoffice.govt.nz/dashboard/reportingentity/scheme/?id=535ca035-8a94-ee11-be37-00224892b34a&refentity=mbie_reportingentity&refid=776c5ca5-8394-ee11-be37-00224892b34a&refrel=mbie_Scheme_ReportingEntityId_mbie_Report | C57: CENTURIA FUNDS MANAGEMENT (NZ) LIMITED | D57: Reporting Period . sort descending Actions 31-03-2024 - Due by 31-07-2024 | E57: 31-03-2024 - Due by 31-07-2024 | F57: LAMBIE DR PROPERTY SCHEME (SCH11586) | G57: Have records but not submitted | H57: Investment Scheme | I57: 45382 | J57: 45504 | K57: =VLOOKUP(B57,'20April'!B:G,6,0) -> Have records but not submitted
A58: 176 | B58: https://crd-app.companiesoffice.govt.nz/dashboard/reportingentity/scheme/?id=555ca035-8a94-ee11-be37-00224892b34a&refentity=mbie_reportingentity&refid=776c5ca5-8394-ee11-be37-00224892b34a&refrel=mbie_Scheme_ReportingEntityId_mbie_Report | C58: CENTURIA FUNDS MANAGEMENT (NZ) LIMITED | D58: Reporting Period . sort descending Actions 31-03-2024 - Due by 31-07-2024 | E58: 31-03-2024 - Due by 31-07-2024 | F58: LINK DR PROPERTY SCHEME (SCH11587) | G58: Have records but not submitted | H58: Investment Scheme | I58: 45382 | J58: 45504 | K58: =VLOOKUP(B58,'20April'!B:G,6,0) -> Have records but not submitted
A59: 177 | B59: https://crd-app.companiesoffice.govt.nz/dashboard/reportingentity/scheme/?id=495ca035-8a94-ee11-be37-00224892b34a&refentity=mbie_reportingentity&refid=776c5ca5-8394-ee11-be37-00224892b34a&refrel=mbie_Scheme_ReportingEntityId_mbie_Report | C59: CENTURIA FUNDS MANAGEMENT (NZ) LIMITED | D59: Reporting Period . sort descending Actions 31-03-2024 - Due by 31-07-2024 | E59: 31-03-2024 - Due by 31-07-2024 | F59: MANADON STREET PROPERTY SCHEME (SCH11532) | G59: Have records but not submitted | H59: Investment Scheme | I59: 45382 | J59: 45504 | K59: =VLOOKUP(B59,'20April'!B:G,6,0) -> Have records but not submitted
... A66: 186 | B66: https://crd-app.companiesoffice.govt.nz/dashboard/reportingentity/scheme/?id=515ca035-8a94-ee11-be37-00224892b34a&refentity=mbie_reportingentity&refid=776c5ca5-8394-ee11-be37-00224892b34a&refrel=mbie_Scheme_ReportingEntityId_mbie_Report | C66: CENTURIA FUNDS MANAGEMENT (NZ) LIMITED | D66: Reporting Period . sort descending Actions 31-03-2024 - Due by 31-07-2024 | E66: 31-03-2024 - Due by 31-07-2024 | F66: WILLIAMS STREET NOMINEES JOINT VENTURE (SCH11570) | G66: Have records but not submitted | H66: Investment Scheme | I66: 45382 | J66: 45504 | K66: =VLOOKUP(B66,'20April'!B:G,6,0) -> Have records but not submitted
A67: 165 | B67: https://crd-app.companiesoffice.govt.nz/dashboard/reportingentity/scheme/?id=615ca035-8a94-ee11-be37-00224892b34a&refentity=mbie_reportingentity&refid=776c5ca5-8394-ee11-be37-00224892b34a&refrel=mbie_Scheme_ReportingEntityId_mbie_Report | C67: CENTURIA FUNDS MANAGEMENT (NZ) LIMITED | D67: Reporting Period . sort descending Actions There are no records to display. | E67: There are no records to display. | F67: AUGUSTA KEDRON PARTNERSHIP (SCH12564) | G67: No records | H67: Investment Scheme | K67: =VLOOKUP(B67,'20April'!B:G,6,0) -> No records
A68: 168 | B68: https://crd-app.companiesoffice.govt.nz/dashboard/reportingentity/scheme/?id=455ca035-8a94-ee11-be37-00224892b34a&refentity=mbie_reportingentity&refid=776c5ca5-8394-ee11-be37-00224892b34a&refrel=mbie_Scheme_ReportingEntityId_mbie_Report | C68: CENTURIA FUNDS MANAGEMENT (NZ) LIMITED | D68: Reporting Period . sort descending Actions There are no records to display. | E68: There are no records to display. | F68: BRADMAN STREET PROPORTIONATE OWNERSHIP SCHEME (SCH11503) | G68: No records | H68: Investment Scheme | K68: =VLOOKUP(B68,'20April'!B:G,6,0) -> No records
A69: 173 | B69: https://crd-app.companiesoffice.govt.nz/dashboard/reportingentity/scheme/?id=435ca035-8a94-ee11-be37-00224892b34a&refentity=mbie_reportingentity&refid=776c5ca5-8394-ee11-be37-00224892b34a&refrel=mbie_Scheme_ReportingEntityId_mbie_Report | C69: CENTURIA FUNDS MANAGEMENT (NZ) LIMITED | D69: Reporting Period . sort descending Actions There are no records to display. | E69: There are no records to display. | F69: FORMATION ST PROPORTIONATE OWNERSHIP SCHEME (SCH11478) | G69: No records | H69: Investment Scheme | K69: =VLOOKUP(B69,'20April'!B:G,6,0) -> No records
A70: 179 | B70: https://crd-app.companiesoffice.govt.nz/dashboard/reportingentity/scheme/?id=355ca035-8a94-ee11-be37-00224892b34a&refentity=mbie_reportingentity&refid=776c5ca5-8394-ee11-be37-00224892b34a&refrel=mbie_Scheme_ReportingEntityId_mbie_Report | C70: CENTURIA FUNDS MANAGEMENT (NZ) LIMITED | D70: Reporting Period . sort descending Actions There are no records to display. | E70: There are no records to display. | F70: QUINNS HILL ROAD PARTNERSHIP (SCH10523) | G70: No records | H70: Investment Scheme | K70: =VLOOKUP(B70,'20April'!B:G,6,0) -> No records
A71: 181 | B71: https://crd-app.companiesoffice.govt.nz/dashboard/reportingentity/scheme/?id=475ca035-8a94-ee11-be37-00224892b34a&refentity=mbie_reportingentity&refid=776c5ca5-8394-ee11-be37-00224892b34a&refrel=mbie_Scheme_ReportingEntityId_mbie_Report | C71: CENTURIA FUNDS MANAGEMENT (NZ) LIMITED | D71: Reporting Period . sort descending Actions There are no records to display. | E71: There are no records to display. | F71: SHERBROOKE RD PARTNERSHIP (SCH11507) | G71: No records | H71: Investment Scheme | K71: =VLOOKUP(B71,'20April'!B:G,6,0) -> No records
A72: 18 | B72: https://crd-app.companiesoffice.govt.nz/dashboard/reportingentity/?id=c16b5ca5-8394-ee11-be37-00224892b34a | C72: CHANNEL INFRASTRUCTURE NZ LIMITED | D72: Reporting Period . sort descending Actions 31-12-2023 - Click to view Climate Statement/s | E72: 31-12-2023 - Click to view Climate Statement/s | G72: Have records and have submitted | H72: Company | K72: =VLOOKUP(B72,'20April'!B:G,6,0) -> Have records and have submitted
A73: 19 | B73: https://crd-app.companiesoffice.govt.nz/dashboard/reportingentity/?id=6b6b5ca5-8394-ee11-be37-00224892b34a | C73: CHINA CONSTRUCTION BANK (NEW ZEALAND) LIMITED | D73: Reporting Period . sort descending Actions 31-12-2023 - Click to view Climate Statement/s | E73: 31-12-2023 - Click to view Climate Statement/s | G73: Have records and have submitted | H73: Company | K73: =VLOOKUP(B73,'20April'!B:G,6,0) -> Have records but not submitted
A74: 20 | B74: https://crd-app.companiesoffice.govt.nz/dashboard/reportingentity/?id=6d6b5ca5-8394-ee11-be37-00224892b34a | C74: CHINA CONSTRUCTION BANK CORPORATION | D74: Reporting Period . sort descending Actions 31-12-2023 - Click to view Climate Statement/s | E74: 31-12-2023 - Click to view Climate Statement/s | G74: Have records and have submitted | H74: Company | K74: =VLOOKUP(B74,'20April'!B:G,6,0) -> Have records but not submitted
A75: 21 | B75: https://crd-app.companiesoffice.govt.nz/dashboard/reportingentity/?id=c36b5ca5-8394-ee11-be37-00224892b34a | C75: CHORUS LIMITED | D75: Reporting Period . sort descending Actions There are no records to display. | E75: There are no records to display. | G75: No records | H75: Company | K75: =VLOOKUP(B75,'20April'!B:G,6,0) -> No records
A76: 22 | B76: https://crd-app.companiesoffice.govt.nz/dashboard/reportingentity/?id=c56b5ca5-8394-ee11-be37-00224892b34a | C76: CHRISTCHURCH CITY HOLDINGS LIMITED | D76: Reporting Period . sort descending Actions There are no records to display. | E76: There are no records to display. | G76: No records | H76: Company | K76: =VLOOKUP(B76,'20April'!B:G,6,0) -> No records
A77: 23 | B77: https://crd-app.companiesoffice.govt.nz/dashboard/reportingentity/?id=c76b5ca5-8394-ee11-be37-00224892b34a | C77: CHRISTCHURCH INTERNATIONAL AIRPORT LIMITED | D77: Reporting Period . sort descending Actions There are no records to display. | E77: There are no records to display. | G77: No records | H77: Company | K77: =VLOOKUP(B77,'20April'!B:G,6,0) -> No records
A78: 24 | B78: https://crd-app.companiesoffice.govt.nz/dashboard/reportingentity/?id=916b5ca5-8394-ee11-be37-00224892b34a | C78: CHUBB LIFE INSURANCE NEW ZEALAND LIMITED | D78: Reporting Period . sort descending Actions 31-12-2023 - Click to view Climate Statement/s | E78: 31-12-2023 - Click to view Climate Statement/s | G78: Have records and have submitted | H78: Company | K78: =VLOOKUP(B78,'20April'!B:G,6,0) -> Have records but not submitted
A79: 25 | B79: https://crd-app.companiesoffice.govt.nz/dashboard/reportingentity/?id=6f6b5ca5-8394-ee11-be37-00224892b34a | C79: CITIBANK, N.A. | D79: Reporting Period . sort descending Actions 31-12-2023 - Click to view Climate Statement/s | E79: 31-12-2023 - Click to view Climate Statement/s | G79: Have records and have submitted | H79: Company | K79: =VLOOKUP(B79,'20April'!B:G,6,0) -> Have records but not submitted
A80: 26 | B80: https://crd-app.companiesoffice.govt.nz/dashboard/reportingentity/?id=716b5ca5-8394-ee11-be37-00224892b34a | C80: COMMONWEALTH BANK OF AUSTRALIA | D80: Reporting Period . sort descending Actions There are no records to display. | E80: There are no records to display. | G80: No records | H80: Company | K80: =VLOOKUP(B80,'20April'!B:G,6,0) -> No records
A81: 27 | B81: https://crd-app.companiesoffice.govt.nz/dashboard/reportingentity/?id=c96b5ca5-8394-ee11-be37-00224892b34a | C81: COMVITA LIMITED | D81: Reporting Period . sort descending Actions There are no records to display. | E81: There are no records to display. | G81: No records | H81: Company | K81: =VLOOKUP(B81,'20April'!B:G,6,0) -> No records
A82: 28 | B82: https://crd-app.companiesoffice.govt.nz/dashboard/reportingentity/?id=cb6b5ca5-8394-ee11-be37-00224892b34a | C82: CONTACT ENERGY LIMITED | D82: Reporting Period . sort descending Actions There are no records to display. | E82: There are no records to display. | G82: No records | H82: Company | K82: =VLOOKUP(B82,'20April'!B:G,6,0) -> No records
A83: 29 | B83: https://crd-app.companiesoffice.govt.nz/dashboard/reportingentity/?id=736b5ca5-8394-ee11-be37-00224892b34a | C83: COOPERATIEVE RABOBANK U.A. | D83: Reporting Period . sort descending Actions 31-12-2023 - Click to view Climate Statement/s | E83: 31-12-2023 - Click to view Climate Statement/s | G83: Have records and have submitted | H83: Company | K83: =VLOOKUP(B83,'20April'!B:G,6,0) -> Have records but not submitted
... A85: 31 | B85: https://crd-app.companiesoffice.govt.nz/dashboard/reportingentity/?id=cf6b5ca5-8394-ee11-be37-00224892b34a | C85: EBOS GROUP LIMITED | D85: Reporting Period . sort descending Actions There are no records to display. | E85: There are no records to display. | G85: No records | H85: Company | K85: =VLOOKUP(B85,'20April'!B:G,6,0) -> No records
A86: 32 | B86: https://crd-app.companiesoffice.govt.nz/dashboard/reportingentity/?id=d16b5ca5-8394-ee11-be37-00224892b34a | C86: EROAD LIMITED | D86: Reporting Period . sort descending Actions 31-03-2024 - Due by 31-07-2024 | E86: 31-03-2024 - Due by 31-07-2024 | G86: Have records but not submitted | H86: Company | I86: 45382 | J86: 45504 | K86: =VLOOKUP(B86,'20April'!B:G,6,0) -> Have records but not submitted
A87: 33 | B87: https://crd-app.companiesoffice.govt.nz/dashboard/reportingentity/?id=d36b5ca5-8394-ee11-be37-00224892b34a | C87: F&C INVESTMENT TRUST PLC | D87: Reporting Period . sort descending Actions 31-12-2023 - Due by 30-04-2024 | E87: 31-12-2023 - Due by 30-04-2024 | G87: Have records but not submitted | H87: Company | I87: 45291 | J87: 45412 | K87: =VLOOKUP(B87,'20April'!B:G,6,0) -> Have records but not submitted
A88: 34 | B88: https://crd-app.companiesoffice.govt.nz/dashboard/reportingentity/?id=936b5ca5-8394-ee11-be37-00224892b34a | C88: FIDELITY LIFE ASSURANCE COMPANY LIMITED | D88: Reporting Period . sort descending Actions There are no records to display. | E88: There are no records to display. | G88: No records | H88: Company | K88: =VLOOKUP(B88,'20April'!B:G,6,0) -> No records
A89: 187 | B89: https://crd-app.companiesoffice.govt.nz/dashboard/reportingentity/scheme/?id=675ca035-8a94-ee11-be37-00224892b34a&refentity=mbie_reportingentity&refid=796c5ca5-8394-ee11-be37-00224892b34a&refrel=mbie_Scheme_ReportingEntityId_mbie_Report | C89: FIRST MORTGAGE MANAGERS LIMITED | D89: Reporting Period . sort descending Actions 31-03-2024 - Due by 31-07-2024 | E89: 31-03-2024 - Due by 31-07-2024 | F89: FIRST MORTGAGE PIE TRUST (SCH10249) | G89: Have records but not submitted | H89: Investment Scheme | I89: 45382 | J89: 45504 | K89: =VLOOKUP(B89,'20April'!B:G,6,0) -> Have records but not submitted
A90: 188 | B90: https://crd-app.companiesoffice.govt.nz/dashboard/reportingentity/scheme/?id=655ca035-8a94-ee11-be37-00224892b34a&refentity=mbie_reportingentity&refid=796c5ca5-8394-ee11-be37-00224892b34a&refrel=mbie_Scheme_ReportingEntityId_mbie_Report | C90: FIRST MORTGAGE MANAGERS LIMITED | D90: Reporting Period . sort descending Actions 31-03-2024 - Due by 31-07-2024 | E90: 31-03-2024 - Due by 31-07-2024 | F90: FIRST MORTGAGE TRUST GROUP INVESTMENT FUND (SCH10239) | G90: Have records but not submitted | H90: Investment Scheme | I90: 45382 | J90: 45504 | K90: =VLOOKUP(B90,'20April'!B:G,6,0) -> Have records but not submitted
A91: 35 | B91: https://crd-app.companiesoffice.govt.nz/dashboard/reportingentity/?id=d56b5ca5-8394-ee11-be37-00224892b34a | C91: FISHER & PAYKEL HEALTHCARE CORPORATION LIMITED | D91: Reporting Period . sort descending Actions 31-03-2024 - Due by 31-07-2024 | E91: 31-03-2024 - Due by 31-07-2024 | G91: Have records but not submitted | H91: Company | I91: 45382 | J91: 45504 | K91: =VLOOKUP(B91,'20April'!B:G,6,0) -> Have records but not submitted
A92: 189 | B92: https://crd-app.companiesoffice.govt.nz/dashboard/reportingentity/scheme/?id=735ca035-8a94-ee11-be37-00224892b34a&refentity=mbie_reportingentity&refid=7b6c5ca5-8394-ee11-be37-00224892b34a&refrel=mbie_Scheme_ReportingEntityId_mbie_Report | C92: FISHER FUNDS MANAGEMENT LIMITED | D92: Reporting Period . sort descending Actions 31-03-2024 - Due by 31-07-2024 | E92: 31-03-2024 - Due by 31-07-2024 | F92: FISHER FUNDS INVESTMENT SERIES (SCH10642) | G92: Have records but not submitted | H92: Investment Scheme | I92: 45382 | J92: 45504 | K92: =VLOOKUP(B92,'20April'!B:G,6,0) -> Have records but not submitted
A93: 190 | B93: https://crd-app.companiesoffice.govt.nz/dashboard/reportingentity/scheme/?id=6b5ca035-8a94-ee11-be37-00224892b34a&refentity=mbie_reportingentity&refid=7b6c5ca5-8394-ee11-be37-00224892b34a&refrel=mbie_Scheme_ReportingEntityId_mbie_Report | C93: FISHER FUNDS MANAGEMENT LIMITED | D93: Reporting Period . sort descending Actions 31-03-2024 - Due by 31-07-2024 | E93: 31-03-2024 - Due by 31-07-2024 | F93: FISHER FUNDS KIWISAVER SCHEME (SCH10636) | G93: Have records but not submitted | H93: Investment Scheme | I93: 45382 | J93: 45504 | K93: =VLOOKUP(B93,'20April'!B:G,6,0) -> Have records but not submitted
A94: 191 | B94: https://crd-app.companiesoffice.govt.nz/dashboard/reportingentity/scheme/?id=6d5ca035-8a94-ee11-be37-00224892b34a&refentity=mbie_reportingentity&refid=7b6c5ca5-8394-ee11-be37-00224892b34a&refrel=mbie_Scheme_ReportingEntityId_mbie_Report | C94: FISHER FUNDS MANAGEMENT LIMITED | D94: Reporting Period . sort descending Actions 31-03-2024 - Due by 31-07-2024 | E94: 31-03-2024 - Due by 31-07-2024 | F94: FISHER FUNDS LIFESAVER PLAN (SCH10637) | G94: Have records but not submitted | H94: Investment Scheme | I94: 45382 | J94: 45504 | K94: =VLOOKUP(B94,'20April'!B:G,6,0) -> Have records but not submitted
A95: 192 | B95: https://crd-app.companiesoffice.govt.nz/dashboard/reportingentity/scheme/?id=6f5ca035-8a94-ee11-be37-00224892b34a&refentity=mbie_reportingentity&refid=7b6c5ca5-8394-ee11-be37-00224892b34a&refrel=mbie_Scheme_ReportingEntityId_mbie_Report | C95: FISHER FUNDS MANAGEMENT LIMITED | D95: Reporting Period . sort descending Actions 31-03-2024 - Due by 31-07-2024 | E95: 31-03-2024 - Due by 31-07-2024 | F95: FISHER FUNDS MANAGED FUNDS (SCH10640) | G95: Have records but not submitted | H95: Investment Scheme | I95: 45382 | J95: 45504 | K95: =VLOOKUP(B95,'20April'!B:G,6,0) -> Have records but not submitted
A96: 193 | B96: https://crd-app.companiesoffice.govt.nz/dashboard/reportingentity/scheme/?id=715ca035-8a94-ee11-be37-00224892b34a&refentity=mbie_reportingentity&refid=7b6c5ca5-8394-ee11-be37-00224892b34a&refrel=mbie_Scheme_ReportingEntityId_mbie_Report | C96: FISHER FUNDS MANAGEMENT LIMITED | D96: Reporting Period . sort descending Actions 31-03-2024 - Due by 31-07-2024 | E96: 31-03-2024 - Due by 31-07-2024 | F96: FISHER FUNDS PREMIUM SERVICE (SCH10641) | G96: Have records but not submitted | H96: Investment Scheme | I96: 45382 | J96: 45504 | K96: =VLOOKUP(B96,'20April'!B:G,6,0) -> Have records but not submitted
A97: 194 | B97: https://crd-app.companiesoffice.govt.nz/dashboard/reportingentity/scheme/?id=695ca035-8a94-ee11-be37-00224892b34a&refentity=mbie_reportingentity&refid=7b6c5ca5-8394-ee11-be37-00224892b34a&refrel=mbie_Scheme_ReportingEntityId_mbie_Report | C97: FISHER FUNDS MANAGEMENT LIMITED | D97: Reporting Period . sort descending Actions 31-03-2024 - Due by 31-07-2024 | E97: 31-03-2024 - Due by 31-07-2024 | F97: FISHER FUNDS TWO KIWISAVER SCHEME (SCH10597) | G97: Have records but not submitted | H97: Investment Scheme | I97: 45382 | J97: 45504 | K97: =VLOOKUP(B97,'20April'!B:G,6,0) -> Have records but not submitted
A98: 195 | B98: https://crd-app.companiesoffice.govt.nz/dashboard/reportingentity/scheme/?id=755ca035-8a94-ee11-be37-00224892b34a&refentity=mbie_reportingentity&refid=7b6c5ca5-8394-ee11-be37-00224892b34a&refrel=mbie_Scheme_ReportingEntityId_mbie_Report | C98: FISHER FUNDS MANAGEMENT LIMITED | D98: Reporting Period . sort descending Actions There are no records to display. | E98: There are no records to display. | F98: FUTUREPLAN (SCH11318) | G98: No records | H98: Investment Scheme | K98: =VLOOKUP(B98,'20April'!B:G,6,0) -> No records
A99: 36 | B99: https://crd-app.companiesoffice.govt.nz/dashboard/reportingentity/?id=d76b5ca5-8394-ee11-be37-00224892b34a | C99: FLETCHER BUILDING INDUSTRIES LIMITED | D99: Reporting Period . sort descending Actions There are no records to display. | E99: There are no records to display. | G99: No records | H99: Company | K99: =VLOOKUP(B99,'20April'!B:G,6,0) -> No records
A100: 37 | B100: https://crd-app.companiesoffice.govt.nz/dashboard/reportingentity/?id=d96b5ca5-8394-ee11-be37-00224892b34a | C100: FLETCHER BUILDING LIMITED | D100: Reporting Period . sort descending Actions There are no records to display. | E100: There are no records to display. | G100: No records | H100: Company | K100: =VLOOKUP(B100,'20April'!B:G,6,0) -> No records
A101: 38 | B101: https://crd-app.companiesoffice.govt.nz/dashboard/reportingentity/?id=956b5ca5-8394-ee11-be37-00224892b34a | C101: FMG INSURANCE LIMITED | D101: Reporting Period . sort descending Actions 31-03-2024 - Due by 31-07-2024 | E101: 31-03-2024 - Due by 31-07-2024 | G101: Have records but not submitted | H101: Company | I101: 45382 | J101: 45504 | K101: =VLOOKUP(B101,'20April'!B:G,6,0) -> Have records but not submitted
A102: 39 | B102: https://crd-app.companiesoffice.govt.nz/dashboard/reportingentity/?id=db6b5ca5-8394-ee11-be37-00224892b34a | C102: FOLEY WINES LIMITED | D102: Reporting Period . sort descending Actions There are no records to display. | E102: There are no records to display. | G102: No records | H102: Company | K102: =VLOOKUP(B102,'20April'!B:G,6,0) -> No records
A103: 40 | B103: https://crd-app.companiesoffice.govt.nz/dashboard/reportingentity/?id=0aac69fc-3208-ef11-9f89-002248954af0 | C103: FONTERRA CO-OPERATIVE GROUP LIMITED | D103: Reporting Period . sort descending Actions There are no records to display. | E103: There are no records to display. | G103: No records | H103: Company | K103: =VLOOKUP(B103,'20April'!B:G,6,0) -> #N/A
A104: 41 | B104: https://crd-app.companiesoffice.govt.nz/dashboard/reportingentity/?id=dd6b5ca5-8394-ee11-be37-00224892b34a | C104: FREIGHTWAYS GROUP LIMITED | D104: Reporting Period . sort descending Actions There are no records to display. | E104: There are no records to display. | G104: No records | H104: Company | K104: =VLOOKUP(B104,'20April'!B:G,6,0) -> No records
A105: 196 | B105: https://crd-app.companiesoffice.govt.nz/dashboard/reportingentity/scheme/?id=9f5ca035-8a94-ee11-be37-00224892b34a&refentity=mbie_reportingentity&refid=7d6c5ca5-8394-ee11-be37-00224892b34a&refrel=mbie_Scheme_ReportingEntityId_mbie_Report | C105: FUNDROCK NZ LIMITED | D105: Reporting Period . sort descending Actions 31-03-2024 - Due by 31-07-2024 | E105: 31-03-2024 - Due by 31-07-2024 | F105: ACI FUNDS (SCH13499) | G105: Have records but not submitted | H105: Investment Scheme | I105: 45382 | J105: 45504 | K105: =VLOOKUP(B105,'20April'!B:G,6,0) -> Have records but not submitted
A106: 197 | B106: https://crd-app.companiesoffice.govt.nz/dashboard/reportingentity/scheme/?id=7d5ca035-8a94-ee11-be37-00224892b34a&refentity=mbie_reportingentity&refid=7d6c5ca5-8394-ee11-be37-00224892b34a&refrel=mbie_Scheme_ReportingEntityId_mbie_Report | C106: FUNDROCK NZ LIMITED | D106: Reporting Period . sort descending Actions 31-03-2024 - Due by 31-07-2024 | E106: 31-03-2024 - Due by 31-07-2024 | F106: ANTIPODES INVESTMENT FUNDS (SCH12434) | G106: Have records but not submitted | H106: Investment Scheme | I106: 45382 | J106: 45504 | K106: =VLOOKUP(B106,'20April'!B:G,6,0) -> Have records but not submitted
A107: 198 | B107: https://crd-app.companiesoffice.govt.nz/dashboard/reportingentity/scheme/?id=795ca035-8a94-ee11-be37-00224892b34a&refentity=mbie_reportingentity&refid=7d6c5ca5-8394-ee11-be37-00224892b34a&refrel=mbie_Scheme_ReportingEntityId_mbie_Report | C107: FUNDROCK NZ LIMITED | D107: Reporting Period . sort descending Actions 31-03-2024 - Due by 31-07-2024 | E107: 31-03-2024 - Due by 31-07-2024 | F107: APN INVESTMENT FUNDS SCHEME (SCH11734) | G107: Have records but not submitted | H107: Investment Scheme | I107: 45382 | J107: 45504 | K107: =VLOOKUP(B107,'20April'!B:G,6,0) -> Have records but not submitted
...

Sheet 2.masterfirm
A1: Company Name | B1: scheme | C1: industry | D1: industry_large group | E1: count_firm | F1: count | G1: status | H1: duedate | I1: duemonth
A2: AA INSURANCE LIMITED | B2: Company | C2: Insurance | D2: Financial Sector | E2: 1 | F2: =COUNTIFS('1.master_list_7May'!C:C,A2) -> 1 | G2: =VLOOKUP($A2,'1.master_list_7May'!C:G,5,0) -> No records | I2: =IF(H2=0,"No month", MONTH(H2)) -> No month
A3: AFT PHARMACEUTICALS LIMITED | B3: Company | C3: Healthcare | D3: Other | E3: 1 | F3: =COUNTIFS('1.master_list_7May'!C:C,A3) -> 1 | G3: =VLOOKUP($A3,'1.master_list_7May'!C:G,5,0) -> Have records but not submitted | H3: =VLOOKUP(A3,'1.master_list_7May'!C:J,8,0) -> 45504 | I3: =IF(H3=0,"No month", MONTH(H3)) -> 7
A4: AIA NEW ZEALAND LIMITED | B4: Company | C4: Insurance | D4: Financial Sector | E4: 1 | F4: =COUNTIFS('1.master_list_7May'!C:C,A4) -> 1 | G4: =VLOOKUP($A4,'1.master_list_7May'!C:G,5,0) -> Have records and have submitted | I4: =IF(H4=0,"No month", MONTH(H4)) -> No month
A5: AIR NEW ZEALAND LIMITED | B5: Company | C5: Airport/Infrastructure | D5: Other | E5: 1 | F5: =COUNTIFS('1.master_list_7May'!C:C,A5) -> 1 | G5: =VLOOKUP($A5,'1.master_list_7May'!C:G,5,0) -> No records | I5: =IF(H5=0,"No month", MONTH(H5)) -> No month
A6: AMP WEALTH MANAGEMENT NEW ZEALAND LIMITED | B6: Investment Scheme | C6: Finance/Investment | D6: Financial Sector | E6: 1 | F6: =COUNTIFS('1.master_list_7May'!C:C,A6) -> 7 | G6: =VLOOKUP($A6,'1.master_list_7May'!C:G,5,0) -> Have records but not submitted | H6: =VLOOKUP(A6,'1.master_list_7May'!C:J,8,0) -> 45504 | I6: =IF(H6=0,"No month", MONTH(H6)) -> 7
A7: ANZ INVESTMENT SERVICES (NEW ZEALAND) LIMITED | B7: Investment Scheme | C7: Finance/Investment | D7: Financial Sector | E7: 1 | F7: =COUNTIFS('1.master_list_7May'!C:C,A7) -> 1 | G7: =VLOOKUP($A7,'1.master_list_7May'!C:G,5,0) -> Have records but not submitted | H7: =VLOOKUP(A7,'1.master_list_7May'!C:J,8,0) -> 45504 | I7: =IF(H7=0,"No month", MONTH(H7)) -> 7
A8: ANZ NEW ZEALAND INVESTMENTS LIMITED | B8: Investment Scheme | C8: Australian/Nz Bank | D8: Financial Sector | E8: 1 | F8: =COUNTIFS('1.master_list_7May'!C:C,A8) -> 5 | G8: =VLOOKUP($A8,'1.master_list_7May'!C:G,5,0) -> Have records but not submitted | H8: =VLOOKUP(A8,'1.master_list_7May'!C:J,8,0) -> 45504 | I8: =IF(H8=0,"No month", MONTH(H8)) -> 7
A9: ARBORGEN HOLDINGS LIMITED | B9: Company | C9: Finance/Investment | D9: Financial Sector | E9: 1 | F9: =COUNTIFS('1.master_list_7May'!C:C,A9) -> 1 | G9: =VLOOKUP($A9,'1.master_list_7May'!C:G,5,0) -> Have records but not submitted | H9: =VLOOKUP(A9,'1.master_list_7May'!C:J,8,0) -> 45504 | I9: =IF(H9=0,"No month", MONTH(H9)) -> 7
A10: ARGOSY PROPERTY LIMITED | B10: Company | C10: Property | D10: Real Estate | E10: 1 | F10: =COUNTIFS('1.master_list_7May'!C:C,A10) -> 1 | G10: =VLOOKUP($A10,'1.master_list_7May'!C:G,5,0) -> Have records but not submitted | H10: =VLOOKUP(A10,'1.master_list_7May'!C:J,8,0) -> 45504 | I10: =IF(H10=0,"No month", MONTH(H10)) -> 7
A11: ARVIDA GROUP LIMITED | B11: Company | C11: Property | D11: Real Estate | E11: 1 | F11: =COUNTIFS('1.master_list_7May'!C:C,A11) -> 1 | G11: =VLOOKUP($A11,'1.master_list_7May'!C:G,5,0) -> Have records but not submitted | H11: =VLOOKUP(A11,'1.master_list_7May'!C:J,8,0) -> 45504 | I11: =IF(H11=0,"No month", MONTH(H11)) -> 7
A12: ASB BANK LIMITED | B12: Company | C12: Australian/Nz Bank | D12: Financial Sector | E12: 1 | F12: =COUNTIFS('1.master_list_7May'!C:C,A12) -> 1 | G12: =VLOOKUP($A12,'1.master_list_7May'!C:G,5,0) -> No records | I12: =IF(H12=0,"No month", MONTH(H12)) -> No month
A13: ASB GROUP INVESTMENTS LIMITED | B13: Investment Scheme | C13: Finance/Investment | D13: Financial Sector | E13: 1 | F13: =COUNTIFS('1.master_list_7May'!C:C,A13) -> 2 | G13: =VLOOKUP($A13,'1.master_list_7May'!C:G,5,0) -> Have records but not submitted | H13: =VLOOKUP(A13,'1.master_list_7May'!C:J,8,0) -> 45504 | I13: =IF(H13=0,"No month", MONTH(H13)) -> 7
A14: ASSET PLUS LIMITED | B14: Company | C14: Finance/Investment | D14: Financial Sector | E14: 1 | F14: =COUNTIFS('1.master_list_7May'!C:C,A14) -> 1 | G14: =VLOOKUP($A14,'1.master_list_7May'!C:G,5,0) -> Have records but not submitted | H14: =VLOOKUP(A14,'1.master_list_7May'!C:J,8,0) -> 45504 | I14: =IF(H14=0,"No month", MONTH(H14)) -> 7
A15: ASTERON LIFE LIMITED | B15: Company | C15: Insurance | D15: Financial Sector | E15: 1 | F15: =COUNTIFS('1.master_list_7May'!C:C,A15) -> 1 | G15: =VLOOKUP($A15,'1.master_list_7May'!C:G,5,0) -> No records | I15: =IF(H15=0,"No month", MONTH(H15)) -> No month
A16: AUCKLAND COUNCIL | B16: Company | C16: Government | D16: Other | E16: 1 | F16: =COUNTIFS('1.master_list_7May'!C:C,A16) -> 1 | G16: =VLOOKUP($A16,'1.master_list_7May'!C:G,5,0) -> No records | I16: =IF(H16=0,"No month", MONTH(H16)) -> No month
A17: AUCKLAND INTERNATIONAL AIRPORT LIMITED | B17: Company | C17: Airport/Infrastructure | D17: Other | E17: 1 | F17: =COUNTIFS('1.master_list_7May'!C:C,A17) -> 1 | G17: =VLOOKUP($A17,'1.master_list_7May'!C:G,5,0) -> No records | I17: =IF(H17=0,"No month", MONTH(H17)) -> No month
A18: AUSTRALIAN FOUNDATION INVESTMENT COMPANY LIMITED | B18: Company | C18: Finance/Investment | D18: Financial Sector | E18: 1 | F18: =COUNTIFS('1.master_list_7May'!C:C,A18) -> 1 | G18: =VLOOKUP($A18,'1.master_list_7May'!C:G,5,0) -> No records | I18: =IF(H18=0,"No month", MONTH(H18)) -> No month
A19: BANK OF CHINA (NEW ZEALAND) LIMITED | B19: Company | C19: Foreign Bank | D19: Financial Sector | E19: 1 | F19: =COUNTIFS('1.master_list_7May'!C:C,A19) -> 1 | G19: =VLOOKUP($A19,'1.master_list_7May'!C:G,5,0) -> Have records and have submitted | I19: =IF(H19=0,"No month", MONTH(H19)) -> No month
A20: BANK OF CHINA LIMITED | B20: Company | C20: Foreign Bank | D20: Financial Sector | E20: 1 | F20: =COUNTIFS('1.master_list_7May'!C:C,A20) -> 1 | G20: =VLOOKUP($A20,'1.master_list_7May'!C:G,5,0) -> Have records but not submitted | H20: =VLOOKUP(A20,'1.master_list_7May'!C:J,8,0) -> 45412 | I20: =IF(H20=0,"No month", MONTH(H20)) -> 4
A21: BARRAMUNDI LIMITED | B21: Company | C21: Finance/Investment | D21: Financial Sector | E21: 1 | F21: =COUNTIFS('1.master_list_7May'!C:C,A21) -> 1 | G21: =VLOOKUP($A21,'1.master_list_7May'!C:G,5,0) -> No records | I21: =IF(H21=0,"No month", MONTH(H21)) -> No month
A22: BNZ INVESTMENT SERVICES LIMITED | B22: Investment Scheme | C22: Finance/Investment | D22: Financial Sector | E22: 1 | F22: =COUNTIFS('1.master_list_7May'!C:C,A22) -> 3 | G22: =VLOOKUP($A22,'1.master_list_7May'!C:G,5,0) -> Have records but not submitted | H22: =VLOOKUP(A22,'1.master_list_7May'!C:J,8,0) -> 45504 | I22: =IF(H22=0,"No month", MONTH(H22)) -> 7
A23: BOOSTER INVESTMENT MANAGEMENT LIMITED | B23: Investment Scheme | C23: Finance/Investment | D23: Financial Sector | E23: 1 | F23: =COUNTIFS('1.master_list_7May'!C:C,A23) -> 6 | G23: =VLOOKUP($A23,'1.master_list_7May'!C:G,5,0) -> Have records but not submitted | H23: =VLOOKUP(A23,'1.master_list_7May'!C:J,8,0) -> 45504 | I23: =IF(H23=0,"No month", MONTH(H23)) -> 7
A24: BRISCOE GROUP LIMITED | B24: Company | C24: Consumer | D24: Industry | E24: 1 | F24: =COUNTIFS('1.master_list_7May'!C:C,A24) -> 1 | G24: =VLOOKUP($A24,'1.master_list_7May'!C:G,5,0) -> Have records and have submitted | I24: =IF(H24=0,"No month", MONTH(H24)) -> No month
A25: BT FUNDS MANAGEMENT (NZ) LIMITED | B25: Investment Scheme | C25: Finance/Investment | D25: Financial Sector | E25: 1 | F25: =COUNTIFS('1.master_list_7May'!C:C,A25) -> 4 | G25: =VLOOKUP($A25,'1.master_list_7May'!C:G,5,0) -> Have records but not submitted | H25: =VLOOKUP(A25,'1.master_list_7May'!C:J,8,0) -> 45504 | I25: =IF(H25=0,"No month", MONTH(H25)) -> 7
A26: CDL INVESTMENTS NEW ZEALAND LIMITED | B26: Company | C26: Finance/Investment | D26: Financial Sector | E26: 1 | F26: =COUNTIFS('1.master_list_7May'!C:C,A26) -> 1 | G26: =VLOOKUP($A26,'1.master_list_7May'!C:G,5,0) -> Have records and have submitted | I26: =IF(H26=0,"No month", MONTH(H26)) -> No month
A27: CENTURIA FUNDS MANAGEMENT (NZ) LIMITED | B27: Investment Scheme | C27: Finance/Investment | D27: Financial Sector | E27: 1 | F27: =COUNTIFS('1.master_list_7May'!C:C,A27) -> 24 | G27: =VLOOKUP($A27,'1.master_list_7May'!C:G,5,0) -> Have records but not submitted | H27: =VLOOKUP(A27,'1.master_list_7May'!C:J,8,0) -> 45504 | I27: =IF(H27=0,"No month", MONTH(H27)) -> 7
A28: CHANNEL INFRASTRUCTURE NZ LIMITED | B28: Company | C28: Airport/Infrastructure | D28: Industry | E28: 1 | F28: =COUNTIFS('1.master_list_7May'!C:C,A28) -> 1 | G28: =VLOOKUP($A28,'1.master_list_7May'!C:G,5,0) -> Have records and have submitted | I28: =IF(H28=0,"No month", MONTH(H28)) -> No month
A29: CHINA CONSTRUCTION BANK (NEW ZEALAND) LIMITED | B29: Company | C29: Foreign Bank | D29: Financial Sector | E29: 1 | F29: =COUNTIFS('1.master_list_7May'!C:C,A29) -> 1 | G29: =VLOOKUP($A29,'1.master_list_7May'!C:G,5,0) -> Have records and have submitted | I29: =IF(H29=0,"No month", MONTH(H29)) -> No month
A30: CHINA CONSTRUCTION BANK CORPORATION | B30: Company | C30: Foreign Bank | D30: Financial Sector | E30: 1 | F30: =COUNTIFS('1.master_list_7May'!C:C,A30) -> 1 | G30: =VLOOKUP($A30,'1.master_list_7May'!C:G,5,0) -> Have records and have submitted | I30: =IF(H30=0,"No month", MONTH(H30)) -> No month
A31: CHORUS LIMITED | B31: Company | C31: Telecommunications | D31: It | E31: 1 | F31: =COUNTIFS('1.master_list_7May'!C:C,A31) -> 1 | G31: =VLOOKUP($A31,'1.master_list_7May'!C:G,5,0) -> No records | I31: =IF(H31=0,"No month", MONTH(H31)) -> No month
A32: CHRISTCHURCH CITY HOLDINGS LIMITED | B32: Company | C32: Finance/Investment | D32: Financial Sector | E32: 1 | F32: =COUNTIFS('1.master_list_7May'!C:C,A32) -> 1 | G32: =VLOOKUP($A32,'1.master_list_7May'!C:G,5,0) -> No records | I32: =IF(H32=0,"No month", MONTH(H32)) -> No month
A33: CHRISTCHURCH INTERNATIONAL AIRPORT LIMITED | B33: Company | C33: Airport/Infrastructure | D33: Other | E33: 1 | F33: =COUNTIFS('1.master_list_7May'!C:C,A33) -> 1 | G33: =VLOOKUP($A33,'1.master_list_7May'!C:G,5,0) -> No records | I33: =IF(H33=0,"No month", MONTH(H33)) -> No month
A34: CHUBB LIFE INSURANCE NEW ZEALAND LIMITED | B34: Company | C34: Insurance | D34: Financial Sector | E34: 1 | F34: =COUNTIFS('1.master_list_7May'!C:C,A34) -> 1 | G34: =VLOOKUP($A34,'1.master_list_7May'!C:G,5,0) -> Have records and have submitted | I34: =IF(H34=0,"No month", MONTH(H34)) -> No month
A35: CITIBANK, N.A. | B35: Company | C35: Foreign Bank | D35: Financial Sector | E35: 1 | F35: =COUNTIFS('1.master_list_7May'!C:C,A35) -> 1 | G35: =VLOOKUP($A35,'1.master_list_7May'!C:G,5,0) -> Have records and have submitted | I35: =IF(H35=0,"No month", MONTH(H35)) -> No month
A36: COMMONWEALTH BANK OF AUSTRALIA | B36: Company | C36: Australian/Nz Bank | D36: Financial Sector | E36: 1 | F36: =COUNTIFS('1.master_list_7May'!C:C,A36) -> 1 | G36: =VLOOKUP($A36,'1.master_list_7May'!C:G,5,0) -> No records | I36: =IF(H36=0,"No month", MONTH(H36)) -> No month
A37: COMVITA LIMITED | B37: Company | C37: Food/Agriculture | D37: Food/Agricuture | E37: 1 | F37: =COUNTIFS('1.master_list_7May'!C:C,A37) -> 1 | G37: =VLOOKUP($A37,'1.master_list_7May'!C:G,5,0) -> No records | I37: =IF(H37=0,"No month", MONTH(H37)) -> No month
A38: CONTACT ENERGY LIMITED | B38: Company | C38: Energy | D38: Energy | E38: 1 | F38: =COUNTIFS('1.master_list_7May'!C:C,A38) -> 1 | G38: =VLOOKUP($A38,'1.master_list_7May'!C:G,5,0) -> No records | I38: =IF(H38=0,"No month", MONTH(H38)) -> No month
A39: COOPERATIEVE RABOBANK U.A. | B39: Company | C39: Australian/Nz Bank | D39: Financial Sector | E39: 1 | F39: =COUNTIFS('1.master_list_7May'!C:C,A39) -> 1 | G39: =VLOOKUP($A39,'1.master_list_7May'!C:G,5,0) -> Have records and have submitted | I39: =IF(H39=0,"No month", MONTH(H39)) -> No month
... A41: EBOS GROUP LIMITED | B41: Company | C41: Healthcare | D41: Other | E41: 1 | F41: =COUNTIFS('1.master_list_7May'!C:C,A41) -> 1 | G41: =VLOOKUP($A41,'1.master_list_7May'!C:G,5,0) -> No records | I41: =IF(H41=0,"No month", MONTH(H41)) -> No month
A42: EROAD LIMITED | B42: Company | C42: Transportation | D42: Other | E42: 1 | F42: =COUNTIFS('1.master_list_7May'!C:C,A42) -> 1 | G42: =VLOOKUP($A42,'1.master_list_7May'!C:G,5,0) -> Have records but not submitted | H42: =VLOOKUP(A42,'1.master_list_7May'!C:J,8,0) -> 45504 | I42: =IF(H42=0,"No month", MONTH(H42)) -> 7
A43: F&C INVESTMENT TRUST PLC | B43: Company | C43: Finance/Investment | D43: Financial Sector | E43: 1 | F43: =COUNTIFS('1.master_list_7May'!C:C,A43) -> 1 | G43: =VLOOKUP($A43,'1.master_list_7May'!C:G,5,0) -> Have records but not submitted | H43: =VLOOKUP(A43,'1.master_list_7May'!C:J,8,0) -> 45412 | I43: =IF(H43=0,"No month", MONTH(H43)) -> 4
A44: FIDELITY LIFE ASSURANCE COMPANY LIMITED | B44: Company | C44: Insurance | D44: Financial Sector | E44: 1 | F44: =COUNTIFS('1.master_list_7May'!C:C,A44) -> 1 | G44: =VLOOKUP($A44,'1.master_list_7May'!C:G,5,0) -> No records | I44: =IF(H44=0,"No month", MONTH(H44)) -> No month
A45: FIRST MORTGAGE MANAGERS LIMITED | B45: Investment Scheme | C45: Finance/Investment | D45: Financial Sector | E45: 1 | F45: =COUNTIFS('1.master_list_7May'!C:C,A45) -> 2 | G45: =VLOOKUP($A45,'1.master_list_7May'!C:G,5,0) -> Have records but not submitted | H45: =VLOOKUP(A45,'1.master_list_7May'!C:J,8,0) -> 45504 | I45: =IF(H45=0,"No month", MONTH(H45)) -> 7
A46: FISHER & PAYKEL HEALTHCARE CORPORATION LIMITED | B46: Company | C46: Healthcare | D46: Other | E46: 1 | F46: =COUNTIFS('1.master_list_7May'!C:C,A46) -> 1 | G46: =VLOOKUP($A46,'1.master_list_7May'!C:G,5,0) -> Have records but not submitted | H46: =VLOOKUP(A46,'1.master_list_7May'!C:J,8,0) -> 45504 | I46: =IF(H46=0,"No month", MONTH(H46)) -> 7
A47: FISHER FUNDS MANAGEMENT LIMITED | B47: Investment Scheme | C47: Finance/Investment | D47: Financial Sector | E47: 1 | F47: =COUNTIFS('1.master_list_7May'!C:C,A47) -> 7 | G47: =VLOOKUP($A47,'1.master_list_7May'!C:G,5,0) -> Have records but not submitted | H47: =VLOOKUP(A47,'1.master_list_7May'!C:J,8,0) -> 45504 | I47: =IF(H47=0,"No month", MONTH(H47)) -> 7
A48: FLETCHER BUILDING INDUSTRIES LIMITED | B48: Company | C48: Building | D48: Real Estate | E48: 1 | F48: =COUNTIFS('1.master_list_7May'!C:C,A48) -> 1 | G48: =VLOOKUP($A48,'1.master_list_7May'!C:G,5,0) -> No records | I48: =IF(H48=0,"No month", MONTH(H48)) -> No month
A49: FLETCHER BUILDING LIMITED | B49: Company | C49: Building | D49: Real Estate | E49: 1 | F49: =COUNTIFS('1.master_list_7May'!C:C,A49) -> 1 | G49: =VLOOKUP($A49,'1.master_list_7May'!C:G,5,0) -> No records | I49: =IF(H49=0,"No month", MONTH(H49)) -> No month
A50: FMG INSURANCE LIMITED | B50: Company | C50: Insurance | D50: Financial Sector | E50: 1 | F50: =COUNTIFS('1.master_list_7May'!C:C,A50) -> 1 | G50: =VLOOKUP($A50,'1.master_list_7May'!C:G,5,0) -> Have records but not submitted | H50: =VLOOKUP(A50,'1.master_list_7May'!C:J,8,0) -> 45504 | I50: =IF(H50=0,"No month", MONTH(H50)) -> 7
A51: FOLEY WINES LIMITED | B51: Company | C51: Food/Agriculture | D51: Food/Agricuture | E51: 1 | F51: =COUNTIFS('1.master_list_7May'!C:C,A51) -> 1 | G51: =VLOOKUP($A51,'1.master_list_7May'!C:G,5,0) -> No records | I51: =IF(H51=0,"No month", MONTH(H51)) -> No month
A52: FONTERRA CO-OPERATIVE GROUP LIMITED | B52: Company | C52: Food/Agriculture | D52: Food/Agricuture | E52: 1 | F52: =COUNTIFS('1.master_list_7May'!C:C,A52) -> 1 | G52: =VLOOKUP($A52,'1.master_list_7May'!C:G,5,0) -> No records | I52: =IF(H52=0,"No month", MONTH(H52)) -> No month
A53: FREIGHTWAYS GROUP LIMITED | B53: Company | C53: Transportation | D53: Other | E53: 1 | F53: =COUNTIFS('1.master_list_7May'!C:C,A53) -> 1 | G53: =VLOOKUP($A53,'1.master_list_7May'!C:G,5,0) -> No records | I53: =IF(H53=0,"No month", MONTH(H53)) -> No month
A54: FUNDROCK NZ LIMITED | B54: Investment Scheme | C54: Finance/Investment | D54: Financial Sector | E54: 1 | F54: =COUNTIFS('1.master_list_7May'!C:C,A54) -> 22 | G54: =VLOOKUP($A54,'1.master_list_7May'!C:G,5,0) -> Have records but not submitted | H54: =VLOOKUP(A54,'1.master_list_7May'!C:J,8,0) -> 45504 | I54: =IF(H54=0,"No month", MONTH(H54)) -> 7
A55: GENERATE INVESTMENT MANAGEMENT LIMITED | B55: Investment Scheme | C55: Finance/Investment | D55: Financial Sector | E55: 1 | F55: =COUNTIFS('1.master_list_7May'!C:C,A55) -> 2 | G55: =VLOOKUP($A55,'1.master_list_7May'!C:G,5,0) -> Have records but not submitted | H55: =VLOOKUP(A55,'1.master_list_7May'!C:J,8,0) -> 45504 | I55: =IF(H55=0,"No month", MONTH(H55)) -> 7
A56: GENESIS ENERGY LIMITED | B56: Company | C56: Energy | D56: Energy | E56: 1 | F56: =COUNTIFS('1.master_list_7May'!C:C,A56) -> 1 | G56: =VLOOKUP($A56,'1.master_list_7May'!C:G,5,0) -> No records | I56: =IF(H56=0,"No month", MONTH(H56)) -> No month
A57: GENTRACK GROUP LIMITED | B57: Company | C57: Energy | D57: Energy | E57: 1 | F57: =COUNTIFS('1.master_list_7May'!C:C,A57) -> 1 | G57: =VLOOKUP($A57,'1.master_list_7May'!C:G,5,0) -> No records | I57: =IF(H57=0,"No month", MONTH(H57)) -> No month
A58: GMT BOND ISSUER LIMITED | B58: Company | C58: Finance/Investment | D58: Financial Sector | E58: 1 | F58: =COUNTIFS('1.master_list_7May'!C:C,A58) -> 1 | G58: =VLOOKUP($A58,'1.master_list_7May'!C:G,5,0) -> Have records but not submitted | H58: =VLOOKUP(A58,'1.master_list_7May'!C:J,8,0) -> 45504 | I58: =IF(H58=0,"No month", MONTH(H58)) -> 7
A59: GOODMAN (NZ) LIMITED | B59: Investment Scheme | C59: Finance/Investment | D59: Financial Sector | E59: 1 | F59: =COUNTIFS('1.master_list_7May'!C:C,A59) -> 1 | G59: =VLOOKUP($A59,'1.master_list_7May'!C:G,5,0) -> Have records but not submitted | H59: =VLOOKUP(A59,'1.master_list_7May'!C:J,8,0) -> 45504 | I59: =IF(H59=0,"No month", MONTH(H59)) -> 7
A60: GREEN CROSS HEALTH LIMITED | B60: Company | C60: Healthcare | D60: Other | E60: 1 | F60: =COUNTIFS('1.master_list_7May'!C:C,A60) -> 1 | G60: =VLOOKUP($A60,'1.master_list_7May'!C:G,5,0) -> Have records but not submitted | H60: =VLOOKUP(A60,'1.master_list_7May'!C:J,8,0) -> 45504 | I60: =IF(H60=0,"No month", MONTH(H60)) -> 7
A61: HARBOUR ASSET MANAGEMENT LIMITED | B61: Investment Scheme | C61: Finance/Investment | D61: Financial Sector | E61: 1 | F61: =COUNTIFS('1.master_list_7May'!C:C,A61) -> 2 | G61: =VLOOKUP($A61,'1.master_list_7May'!C:G,5,0) -> No records | I61: =IF(H61=0,"No month", MONTH(H61)) -> No month
A62: HEARTLAND BANK LIMITED | B62: Company | C62: Australian/Nz Bank | D62: Financial Sector | E62: 1 | F62: =COUNTIFS('1.master_list_7May'!C:C,A62) -> 1 | G62: =VLOOKUP($A62,'1.master_list_7May'!C:G,5,0) -> No records | I62: =IF(H62=0,"No month", MONTH(H62)) -> No month
A63: HEARTLAND GROUP HOLDINGS LIMITED | B63: Company | C63: Australian/Nz Bank | D63: Financial Sector | E63: 1 | F63: =COUNTIFS('1.master_list_7May'!C:C,A63) -> 1 | G63: =VLOOKUP($A63,'1.master_list_7May'!C:G,5,0) -> No records | I63: =IF(H63=0,"No month", MONTH(H63)) -> No month
A64: HOUSING NEW ZEALAND LIMITED | B64: Company | C64: Property | D64: Real Estate | E64: 1 | F64: =COUNTIFS('1.master_list_7May'!C:C,A64) -> 1 | G64: =VLOOKUP($A64,'1.master_list_7May'!C:G,5,0) -> No records | I64: =IF(H64=0,"No month", MONTH(H64)) -> No month
A65: IAG NEW ZEALAND LIMITED | B65: Company | C65: Insurance | D65: Financial Sector | E65: 1 | F65: =COUNTIFS('1.master_list_7May'!C:C,A65) -> 1 | G65: =VLOOKUP($A65,'1.master_list_7May'!C:G,5,0) -> No records | I65: =IF(H65=0,"No month", MONTH(H65)) -> No month
A66: IKEGPS GROUP LIMITED | B66: Company | C66: Telecommunications | D66: It | E66: 1 | F66: =COUNTIFS('1.master_list_7May'!C:C,A66) -> 1 | G66: =VLOOKUP($A66,'1.master_list_7May'!C:G,5,0) -> Have records but not submitted | H66: =VLOOKUP(A66,'1.master_list_7May'!C:J,8,0) -> 45504 | I66: =IF(H66=0,"No month", MONTH(H66)) -> 7
A67: INDUSTRIAL AND COMMERCIAL BANK OF CHINA (NEW ZEALAND) LIMITED | B67: Company | C67: Foreign Bank | D67: Financial Sector | E67: 1 | F67: =COUNTIFS('1.master_list_7May'!C:C,A67) -> 1 | G67: =VLOOKUP($A67,'1.master_list_7May'!C:G,5,0) -> Have records and have submitted | I67: =IF(H67=0,"No month", MONTH(H67)) -> No month
A68: INDUSTRIAL AND COMMERCIAL BANK OF CHINA LIMITED | B68: Company | C68: Foreign Bank | D68: Financial Sector | E68: 1 | F68: =COUNTIFS('1.master_list_7May'!C:C,A68) -> 1 | G68: =VLOOKUP($A68,'1.master_list_7May'!C:G,5,0) -> Have records and have submitted | I68: =IF(H68=0,"No month", MONTH(H68)) -> No month
A69: INFRATIL LIMITED | B69: Company | C69: Airport/Infrastructure | D69: Other | E69: 1 | F69: =COUNTIFS('1.master_list_7May'!C:C,A69) -> 1 | G69: =VLOOKUP($A69,'1.master_list_7May'!C:G,5,0) -> Have records but not submitted | H69: =VLOOKUP(A69,'1.master_list_7May'!C:J,8,0) -> 45504 | I69: =IF(H69=0,"No month", MONTH(H69)) -> 7
A70: INSURANCE AUSTRALIA GROUP LIMITED | B70: Company | C70: Insurance | D70: Financial Sector | E70: 1 | F70: =COUNTIFS('1.master_list_7May'!C:C,A70) -> 1 | G70: =VLOOKUP($A70,'1.master_list_7May'!C:G,5,0) -> No records | I70: =IF(H70=0,"No month", MONTH(H70)) -> No month
A71: INVESTORE PROPERTY LIMITED | B71: Company | C71: Property | D71: Real Estate | E71: 1 | F71: =COUNTIFS('1.master_list_7May'!C:C,A71) -> 1 | G71: =VLOOKUP($A71,'1.master_list_7May'!C:G,5,0) -> Have records but not submitted | H71: =VLOOKUP(A71,'1.master_list_7May'!C:J,8,0) -> 45504 | I71: =IF(H71=0,"No month", MONTH(H71)) -> 7
A72: JPMORGAN CHASE BANK, N.A. | B72: Company | C72: Foreign Bank | D72: Financial Sector | E72: 1 | F72: =COUNTIFS('1.master_list_7May'!C:C,A72) -> 1 | G72: =VLOOKUP($A72,'1.master_list_7May'!C:G,5,0) -> Have records but not submitted | H72: =VLOOKUP(A72,'1.master_list_7May'!C:J,8,0) -> 45412 | I72: =IF(H72=0,"No month", MONTH(H72)) -> 4
A73: KINGFISH LIMITED | B73: Company | C73: Finance/Investment | D73: Financial Sector | E73: 1 | F73: =COUNTIFS('1.master_list_7May'!C:C,A73) -> 1 | G73: =VLOOKUP($A73,'1.master_list_7May'!C:G,5,0) -> Have records but not submitted | H73: =VLOOKUP(A73,'1.master_list_7May'!C:J,8,0) -> 45504 | I73: =IF(H73=0,"No month", MONTH(H73)) -> 7
A74: KIWI PROPERTY GROUP LIMITED | B74: Company | C74: Property | D74: Real Estate | E74: 1 | F74: =COUNTIFS('1.master_list_7May'!C:C,A74) -> 1 | G74: =VLOOKUP($A74,'1.master_list_7May'!C:G,5,0) -> Have records but not submitted | H74: =VLOOKUP(A74,'1.master_list_7May'!C:J,8,0) -> 45504 | I74: =IF(H74=0,"No month", MONTH(H74)) -> 7
A75: KIWI WEALTH INVESTMENTS LIMITED PARTNERSHIP | B75: Investment Scheme | C75: Finance/Investment | D75: Financial Sector | E75: 1 | F75: =COUNTIFS('1.master_list_7May'!C:C,A75) -> 1 | G75: =VLOOKUP($A75,'1.master_list_7May'!C:G,5,0) -> Have records but not submitted | H75: =VLOOKUP(A75,'1.master_list_7May'!C:J,8,0) -> 45504 | I75: =IF(H75=0,"No month", MONTH(H75)) -> 7
A76: KIWI WEALTH LIMITED | B76: Investment Scheme | C76: Finance/Investment | D76: Financial Sector | E76: 1 | F76: =COUNTIFS('1.master_list_7May'!C:C,A76) -> 2 | G76: =VLOOKUP($A76,'1.master_list_7May'!C:G,5,0) -> Have records but not submitted | H76: =VLOOKUP(A76,'1.master_list_7May'!C:J,8,0) -> 45504 | I76: =IF(H76=0,"No month", MONTH(H76)) -> 7
A77: KIWIBANK LIMITED | B77: Company | C77: Australian/Nz Bank | D77: Financial Sector | E77: 1 | F77: =COUNTIFS('1.master_list_7May'!C:C,A77) -> 1 | G77: =VLOOKUP($A77,'1.master_list_7May'!C:G,5,0) -> No records | I77: =IF(H77=0,"No month", MONTH(H77)) -> No month
A78: KMD BRANDS LIMITED | B78: Company | C78: Consumer | D78: Other | E78: 1 | F78: =COUNTIFS('1.master_list_7May'!C:C,A78) -> 1 | G78: =VLOOKUP($A78,'1.master_list_7May'!C:G,5,0) -> No records | I78: =IF(H78=0,"No month", MONTH(H78)) -> No month
A79: LIVESTOCK IMPROVEMENT CORPORATION LIMITED | B79: Company | C79: Food/Agriculture | D79: Food/Agricuture | E79: 1 | F79: =COUNTIFS('1.master_list_7May'!C:C,A79) -> 1 | G79: =VLOOKUP($A79,'1.master_list_7May'!C:G,5,0) -> No records | I79: =IF(H79=0,"No month", MONTH(H79)) -> No month
A80: MAINFREIGHT LIMITED | B80: Company | C80: Transportation | D80: Other | E80: 1 | F80: =COUNTIFS('1.master_list_7May'!C:C,A80) -> 1 | G80: =VLOOKUP($A80,'1.master_list_7May'!C:G,5,0) -> Have records but not submitted | H80: =VLOOKUP(A80,'1.master_list_7May'!C:J,8,0) -> 45504 | I80: =IF(H80=0,"No month", MONTH(H80)) -> 7
A81: MANAWA ENERGY LIMITED | B81: Company | C81: Energy | D81: Energy | E81: 1 | F81: =COUNTIFS('1.master_list_7May'!C:C,A81) -> 1 | G81: =VLOOKUP($A81,'1.master_list_7May'!C:G,5,0) -> Have records but not submitted | H81: =VLOOKUP(A81,'1.master_list_7May'!C:J,8,0) -> 45504 | I81: =IF(H81=0,"No month", MONTH(H81)) -> 7
A82: MARLIN GLOBAL LIMITED | B82: Company | C82: Finance/Investment | D82: Financial Sector | E82: 1 | F82: =COUNTIFS('1.master_list_7May'!C:C,A82) -> 1 | G82: =VLOOKUP($A82,'1.master_list_7May'!C:G,5,0) -> No records | I82: =IF(H82=0,"No month", MONTH(H82)) -> No month
A83: MARSDEN MARITIME HOLDINGS LIMITED | B83: Company | C83: Airport/Infrastructure | D83: Other | E83: 1 | F83: =COUNTIFS('1.master_list_7May'!C:C,A83) -> 1 | G83: =VLOOKUP($A83,'1.master_list_7May'!C:G,5,0) -> No records | I83: =IF(H83=0,"No month", MONTH(H83)) -> No month
A84: MEDICAL FUNDS MANAGEMENT LIMITED | B84: Investment Scheme | C84: Finance/Investment | D84: Financial Sector | E84: 1 | F84: =COUNTIFS('1.master_list_7May'!C:C,A84) -> 3 | G84: =VLOOKUP($A84,'1.master_list_7May'!C:G,5,0) -> Have records but not submitted | H84: =VLOOKUP(A84,'1.master_list_7May'!C:J,8,0) -> 45504 | I84: =IF(H84=0,"No month", MONTH(H84)) -> 7
A85: MERCER (N.Z.) LIMITED | B85: Investment Scheme | C85: Finance/Investment | D85: Financial Sector | E85: 1 | F85: =COUNTIFS('1.master_list_7May'!C:C,A85) -> 6 | G85: =VLOOKUP($A85,'1.master_list_7May'!C:G,5,0) -> Have records but not submitted | H85: =VLOOKUP(A85,'1.master_list_7May'!C:J,8,0) -> 45504 | I85: =IF(H85=0,"No month", MONTH(H85)) -> 7
A86: MERCURY NZ LIMITED | B86: Company | C86: Energy | D86: Energy | E86: 1 | F86: =COUNTIFS('1.master_list_7May'!C:C,A86) -> 1 | G86: =VLOOKUP($A86,'1.master_list_7May'!C:G,5,0) -> No records | I86: =IF(H86=0,"No month", MONTH(H86)) -> No month
A87: MERIDIAN ENERGY LIMITED | B87: Company | C87: Energy | D87: Energy | E87: 1 | F87: =COUNTIFS('1.master_list_7May'!C:C,A87) -> 1 | G87: =VLOOKUP($A87,'1.master_list_7May'!C:G,5,0) -> No records | I87: =IF(H87=0,"No month", MONTH(H87)) -> No month
A88: METLIFECARE LIMITED | B88: Company | C88: Insurance | D88: Financial Sector | E88: 1 | F88: =COUNTIFS('1.master_list_7May'!C:C,A88) -> 1 | G88: =VLOOKUP($A88,'1.master_list_7May'!C:G,5,0) -> No records | I88: =IF(H88=0,"No month", MONTH(H88)) -> No month
A89: MICHAEL HILL INTERNATIONAL LIMITED | B89: Company | C89: Manufacturing | D89: Other | E89: 1 | F89: =COUNTIFS('1.master_list_7May'!C:C,A89) -> 1 | G89: =VLOOKUP($A89,'1.master_list_7May'!C:G,5,0) -> No records | I89: =IF(H89=0,"No month", MONTH(H89)) -> No month
A90: MILFORD FUNDS LIMITED | B90: Investment Scheme | C90: Finance/Investment | D90: Financial Sector | E90: 1 | F90: =COUNTIFS('1.master_list_7May'!C:C,A90) -> 2 | G90: =VLOOKUP($A90,'1.master_list_7May'!C:G,5,0) -> Have records but not submitted | H90: =VLOOKUP(A90,'1.master_list_7May'!C:J,8,0) -> 45504 | I90: =IF(H90=0,"No month", MONTH(H90)) -> 7
A91: MILLENNIUM & COPTHORNE HOTELS NEW ZEALAND LIMITED | B91: Company | C91: Hotel/Restaurant/Tourism | D91: Industry | E91: 1 | F91: =COUNTIFS('1.master_list_7May'!C:C,A91) -> 1 | G91: =VLOOKUP($A91,'1.master_list_7May'!C:G,5,0) -> Have records and have submitted | I91: =IF(H91=0,"No month", MONTH(H91)) -> No month
A92: MOVE LOGISTICS GROUP LIMITED | B92: Company | C92: Transportation | D92: Other | E92: 1 | F92: =COUNTIFS('1.master_list_7May'!C:C,A92) -> 1 | G92: =VLOOKUP($A92,'1.master_list_7May'!C:G,5,0) -> No records | I92: =IF(H92=0,"No month", MONTH(H92)) -> No month
A93: MUFG BANK, LTD. | B93: Company | C93: Foreign Bank | D93: Financial Sector | E93: 1 | F93: =COUNTIFS('1.master_list_7May'!C:C,A93) -> 1 | G93: =VLOOKUP($A93,'1.master_list_7May'!C:G,5,0) -> Have records but not submitted | H93: =VLOOKUP(A93,'1.master_list_7May'!C:J,8,0) -> 45504 | I93: =IF(H93=0,"No month", MONTH(H93)) -> 7
A94: NELSON BUILDING SOCIETY | B94: Company | C94: Building | D94: Real Estate | E94: 1 | F94: =COUNTIFS('1.master_list_7May'!C:C,A94) -> 1 | G94: =VLOOKUP($A94,'1.master_list_7May'!C:G,5,0) -> Have records but not submitted | H94: =VLOOKUP(A94,'1.master_list_7May'!C:J,8,0) -> 45504 | I94: =IF(H94=0,"No month", MONTH(H94)) -> 7
A95: NEW ZEALAND FUNDS MANAGEMENT LIMITED | B95: Investment Scheme | C95: Finance/Investment | D95: Financial Sector | E95: 1 | F95: =COUNTIFS('1.master_list_7May'!C:C,A95) -> 4 | G95: =VLOOKUP($A95,'1.master_list_7May'!C:G,5,0) -> Have records but not submitted | H95: =VLOOKUP(A95,'1.master_list_7May'!C:J,8,0) -> 45504 | I95: =IF(H95=0,"No month", MONTH(H95)) -> 7
A96: NEW ZEALAND KING SALMON INVESTMENTS LIMITED | B96: Company | C96: Food/Agriculture | D96: Food/Agricuture | E96: 1 | F96: =COUNTIFS('1.master_list_7May'!C:C,A96) -> 1 | G96: =VLOOKUP($A96,'1.master_list_7May'!C:G,5,0) -> Have records but not submitted | H96: =VLOOKUP(A96,'1.master_list_7May'!C:J,8,0) -> 45443 | I96: =IF(H96=0,"No month", MONTH(H96)) -> 5
A97: NEW ZEALAND LOCAL GOVERNMENT FUNDING AGENCY LIMITED | B97: Company | C97: Government | D97: Other | E97: 1 | F97: =COUNTIFS('1.master_list_7May'!C:C,A97) -> 1 | G97: =VLOOKUP($A97,'1.master_list_7May'!C:G,5,0) -> No records | I97: =IF(H97=0,"No month", MONTH(H97)) -> No month
A98: NEW ZEALAND OIL & GAS LIMITED | B98: Company | C98: Energy | D98: Energy | E98: 1 | F98: =COUNTIFS('1.master_list_7May'!C:C,A98) -> 1 | G98: =VLOOKUP($A98,'1.master_list_7May'!C:G,5,0) -> No records | I98: =IF(H98=0,"No month", MONTH(H98)) -> No month
A99: NEW ZEALAND RURAL LAND COMPANY LIMITED | B99: Company | C99: Property | D99: Industry | E99: 1 | F99: =COUNTIFS('1.master_list_7May'!C:C,A99) -> 1 | G99: =VLOOKUP($A99,'1.master_list_7May'!C:G,5,0) -> Have records and have submitted | I99: =IF(H99=0,"No month", MONTH(H99)) -> No month
A100: NIB NZ LIMITED | B100: Company | C100: Insurance | D100: Financial Sector | E100: 1 | F100: =COUNTIFS('1.master_list_7May'!C:C,A100) -> 1 | G100: =VLOOKUP($A100,'1.master_list_7May'!C:G,5,0) -> No records | I100: =IF(H100=0,"No month", MONTH(H100)) -> No month
A101: NIKKO ASSET MANAGEMENT NEW ZEALAND LIMITED | B101: Investment Scheme | C101: Finance/Investment | D101: Financial Sector | E101: 1 | F101: =COUNTIFS('1.master_list_7May'!C:C,A101) -> 2 | G101: =VLOOKUP($A101,'1.master_list_7May'!C:G,5,0) -> Have records but not submitted | H101: =VLOOKUP(A101,'1.master_list_7May'!C:J,8,0) -> 45504 | I101: =IF(H101=0,"No month", MONTH(H101)) -> 7
...

Sheet 3.simple_text_analysis
B1: file_name | C1: pages_num | D1: number_characters | E1: number_words | F1: negative | G1: neutral | H1: positive | I1: compound | J1: readable | K1: company | L1: statement | M1: industry | N1: industry_large group | O1: status | P1: category
A2: 0 | B2: 2023 12 31 - PFI - Climate-related Disclosures - Signed.pdf | C2: 35 | D2: 101572 | E2: 13659 | F2: 0.08 | G2: 0.825 | H2: 0.094 | I2: 0.9997 | J2: Readable | K2: PROPERTY FOR INDUSTRY LIMITED | L2: statement | M2: =VLOOKUP(K2,'2.masterfirm'!A:D,3,0) -> Property | N2: =VLOOKUP(K2,'2.masterfirm'!A:D,4,0) -> Real Estate | O2: =IFERROR(VLOOKUP(K2,'1.master_list_7May'!C:K,9,0),"") -> Have records and have submitted | P2: climate statement
A3: 1 | B3: 2023 Climate Statements for Citibank N.A. (New Zealand Branch).pdf | C3: 51 | D3: 95807 | E3: 13761 | F3: 0.078 | G3: 0.845 | H3: 0.077 | I3: -0.9404 | J3: Readable | K3: CITIBANK, N.A. | L3: statement | M3: =VLOOKUP(K3,'2.masterfirm'!A:D,3,0) -> Foreign Bank | N3: =VLOOKUP(K3,'2.masterfirm'!A:D,4,0) -> Financial Sector | O3: =IFERROR(VLOOKUP(K3,'1.master_list_7May'!C:K,9,0),"") -> Have records but not submitted | P3: climate statement
A4: 2 | B4: AIA NZ Climate Related Disclosers Report FINAL_signed.pdf | C4: 23 | D4: 60167 | E4: 8354 | F4: 0.06 | G4: 0.847 | H4: 0.093 | I4: 0.9998 | J4: Readable | K4: AIA NEW ZEALAND LIMITED | L4: statement | M4: =VLOOKUP(K4,'2.masterfirm'!A:D,3,0) -> Insurance | N4: =VLOOKUP(K4,'2.masterfirm'!A:D,4,0) -> Financial Sector | O4: =IFERROR(VLOOKUP(K4,'1.master_list_7May'!C:K,9,0),"") -> Have records but not submitted | P4: climate statement
A5: 3 | B5: ANZ_climate-report-2023.pdf | J5: Nonreadable | K5: ANZ NEW ZEALAND INVESTMENTS LIMITED | L5: statement | M5: =VLOOKUP(K5,'2.masterfirm'!A:D,3,0) -> Australian/Nz Bank | N5: =VLOOKUP(K5,'2.masterfirm'!A:D,4,0) -> Financial Sector | O5: =IFERROR(VLOOKUP(K5,'1.master_list_7May'!C:K,9,0),"") -> Have records but not submitted | P5: climate statement
A6: 4 | B6: asb-climate-report-2022.pdf | J6: Nonreadable | K6: ASB BANK LIMITED | L6: statement | M6: =VLOOKUP(K6,'2.masterfirm'!A:D,3,0) -> Australian/Nz Bank | N6: =VLOOKUP(K6,'2.masterfirm'!A:D,4,0) -> Financial Sector | O6: =IFERROR(VLOOKUP(K6,'1.master_list_7May'!C:K,9,0),"") -> No records | P6: climate statement
A7: 5 | B7: Bank of China (New Zealand) Limited Climate Related Disclosure for the year ended 31 December 2023.pdf | C7: 22 | D7: 53361 | E7: 6502 | F7: 0.08 | G7: 0.857 | H7: 0.063 | I7: -0.9983 | J7: Readable | K7: BANK OF CHINA (NEW ZEALAND) LIMITED | L7: statement | M7: =VLOOKUP(K7,'2.masterfirm'!A:D,3,0) -> Foreign Bank | N7: =VLOOKUP(K7,'2.masterfirm'!A:D,4,0) -> Financial Sector | O7: =IFERROR(VLOOKUP(K7,'1.master_list_7May'!C:K,9,0),"") -> Have records but not submitted | P7: climate statement
A8: 6 | B8: Bank of China New Zealand Banking Group Climate Related Disclosure for the year ended 31 December 2023.pdf.pdf | C8: 22 | D8: 51228 | E8: 6245 | F8: 0.077 | G8: 0.86 | H8: 0.063 | I8: -0.9968 | J8: Readable | K8: BANK OF CHINA (NEW ZEALAND) LIMITED | L8: statement | M8: =VLOOKUP(K8,'2.masterfirm'!A:D,3,0) -> Foreign Bank | N8: =VLOOKUP(K8,'2.masterfirm'!A:D,4,0) -> Financial Sector | O8: =IFERROR(VLOOKUP(K8,'1.master_list_7May'!C:K,9,0),"") -> Have records but not submitted | P8: climate statement
A9: 7 | B9: BNZ_2023-Climate-Report.pdf | C9: 59 | D9: 208049 | E9: 27829 | F9: 0.082 | G9: 0.853 | H9: 0.065 | I9: -0.9999 | J9: Readable | K9: BNZ INVESTMENT SERVICES LIMITED | L9: statement | M9: =VLOOKUP(K9,'2.masterfirm'!A:D,3,0) -> Finance/Investment | N9: =VLOOKUP(K9,'2.masterfirm'!A:D,4,0) -> Financial Sector | O9: =IFERROR(VLOOKUP(K9,'1.master_list_7May'!C:K,9,0),"") -> Have records but not submitted | P9: climate statement
A10: 8 | B10: Briscoe Group 2024 Annual Report.pdf | C10: 94 | D10: 247464 | E10: 40464 | F10: 0.053 | G10: 0.815 | H10: 0.132 | I10: 1 | J10: Readable | K10: BRISCOE GROUP LIMITED | L10: statement | M10: =VLOOKUP(K10,'2.masterfirm'!A:D,3,0) -> Consumer | N10: =VLOOKUP(K10,'2.masterfirm'!A:D,4,0) -> Industry | O10: =IFERROR(VLOOKUP(K10,'1.master_list_7May'!C:K,9,0),"") -> Have records and have submitted | P10: Annual report
A11: 9 | B11: CCBNZBG Climate Report for the year ended 31 December 2023.pdf | J11: Nonreadable | K11: CHINA CONSTRUCTION BANK (NEW ZEALAND) LIMITED | L11: statement | M11: =VLOOKUP(K11,'2.masterfirm'!A:D,3,0) -> Foreign Bank | N11: =VLOOKUP(K11,'2.masterfirm'!A:D,4,0) -> Financial Sector | O11: =IFERROR(VLOOKUP(K11,'1.master_list_7May'!C:K,9,0),"") -> Have records but not submitted | P11: climate statement
A12: 10 | B12: CCBNZL Climate Report for the year ended 31 December 2023.pdf | J12: Nonreadable | K12: CHINA CONSTRUCTION BANK (NEW ZEALAND) LIMITED | L12: statement | M12: =VLOOKUP(K12,'2.masterfirm'!A:D,3,0) -> Foreign Bank | N12: =VLOOKUP(K12,'2.masterfirm'!A:D,4,0) -> Financial Sector | O12: =IFERROR(VLOOKUP(K12,'1.master_list_7May'!C:K,9,0),"") -> Have records but not submitted | P12: climate statement
A13: 11 | B13: CDL0017_Climate_Related_Disclosures_2023.pdf | C13: 12 | D13: 57241 | E13: 8643 | F13: 0.064 | G13: 0.853 | H13: 0.083 | I13: 0.9994 | J13: Readable | K13: CDL INVESTMENTS NEW ZEALAND LIMITED | L13: statement | M13: =VLOOKUP(K13,'2.masterfirm'!A:D,3,0) -> Finance/Investment | N13: =VLOOKUP(K13,'2.masterfirm'!A:D,4,0) -> Financial Sector | O13: =IFERROR(VLOOKUP(K13,'1.master_list_7May'!C:K,9,0),"") -> Have records and have submitted | P13: climate statement
A14: 12 | B14: Chubb Life Insurance New Zealand Limited Climate Disclosure 2023.pdf | C14: 23 | D14: 69324 | E14: 10179 | F14: 0.068 | G14: 0.841 | H14: 0.092 | I14: 0.9998 | J14: Readable | K14: CHUBB LIFE INSURANCE NEW ZEALAND LIMITED | L14: statement | M14: =VLOOKUP(K14,'2.masterfirm'!A:D,3,0) -> Insurance | N14: =VLOOKUP(K14,'2.masterfirm'!A:D,4,0) -> Financial Sector | O14: =IFERROR(VLOOKUP(K14,'1.master_list_7May'!C:K,9,0),"") -> Have records but not submitted | P14: climate statement
A15: 13 | B15: Citibank N.A. (New Zealand Branch) - Statement - 29 APRIL 2024 .pdf | C15: 1 | D15: 122 | E15: 31 | F15: 0.213 | G15: 0.787 | H15: 0 | I15: -0.6523 | J15: Readable | K15: CITIBANK, N.A. | L15: not a statement | M15: =VLOOKUP(K15,'2.masterfirm'!A:D,3,0) -> Foreign Bank | N15: =VLOOKUP(K15,'2.masterfirm'!A:D,4,0) -> Financial Sector | O15: =IFERROR(VLOOKUP(K15,'1.master_list_7May'!C:K,9,0),"") -> Have records but not submitted
A16: 14 | B16: Climate-Report-2023-Westpac-NZ.pdf | C16: 45 | D16: 171883 | E16: 25203 | F16: 0.05 | G16: 0.844 | H16: 0.106 | I16: 1 | J16: Readable | K16: WESTPAC | L16: statement | M16: =VLOOKUP(K16,'2.masterfirm'!A:D,3,0) -> Australian/Nz Bank | N16: =VLOOKUP(K16,'2.masterfirm'!A:D,4,0) -> Financial Sector | O16: =IFERROR(VLOOKUP(K16,'1.master_list_7May'!C:K,9,0),"") | P16: climate statement
A17: 15 | B17: CRD 2023 CEO Declaration.pdf | C17: 1 | D17: 0 | E17: 1 | F17: 0 | G17: 0 | H17: 0 | I17: 0 | J17: Readable | K17: RESOLUTION LIFE AUSTRALASIA LIMITED | L17: not a statement | M17: =VLOOKUP(K17,'2.masterfirm'!A:D,3,0) -> Finance/Investment | N17: =VLOOKUP(K17,'2.masterfirm'!A:D,4,0) -> Financial Sector | O17: =IFERROR(VLOOKUP(K17,'1.master_list_7May'!C:K,9,0),"") -> Have records but not submitted
A18: 16 | B18: HSBC NZ 2023 Climate Statement lodgement letter - signed.pdf | C18: 1 | D18: 1056 | E18: 175 | F18: 0.05 | G18: 0.9 | H18: 0.051 | I18: 0.2732 | J18: Readable | K18: THE HONGKONG AND SHANGHAI BANKING CORPORATION LIMITED | L18: not a statement | M18: =VLOOKUP(K18,'2.masterfirm'!A:D,3,0) -> Foreign Bank | N18: =VLOOKUP(K18,'2.masterfirm'!A:D,4,0) -> Financial Sector | O18: =IFERROR(VLOOKUP(K18,'1.master_list_7May'!C:K,9,0),"") -> Have records but not submitted | P18: climate statement
A19: 17 | B19: ICBC Ltd CRD 31 Dec 23 Final - For submission.pdf | C19: 29 | D19: 61409 | E19: 7632 | F19: 0.1 | G19: 0.812 | H19: 0.088 | I19: -0.9975 | J19: Readable | K19: INDUSTRIAL AND COMMERCIAL BANK OF CHINA LIMITED | L19: statement | M19: =VLOOKUP(K19,'2.masterfirm'!A:D,3,0) -> Foreign Bank | N19: =VLOOKUP(K19,'2.masterfirm'!A:D,4,0) -> Financial Sector | O19: =IFERROR(VLOOKUP(K19,'1.master_list_7May'!C:K,9,0),"") -> Have records but not submitted | P19: climate statement
A20: 18 | B20: ICBC NZ Ltd CRD 31 Dec 2023.pdf | C20: 30 | D20: 59284 | E20: 6765 | F20: 0.07 | G20: 0.873 | H20: 0.057 | I20: -0.9965 | J20: Readable | K20: INDUSTRIAL AND COMMERCIAL BANK OF CHINA (NEW ZEALAND) LIMITED | L20: statement | M20: =VLOOKUP(K20,'2.masterfirm'!A:D,3,0) -> Foreign Bank | N20: =VLOOKUP(K20,'2.masterfirm'!A:D,4,0) -> Financial Sector | O20: =IFERROR(VLOOKUP(K20,'1.master_list_7May'!C:K,9,0),"") -> Have records but not submitted | P20: climate statement
A21: 19 | B21: kiwibank_sustainability_report2023.pdf | C21: 31 | D21: 66207 | E21: 9860 | F21: 0.019 | G21: 0.833 | H21: 0.147 | I21: 1 | J21: Readable | K21: KIWIBANK LIMITED | L21: statement | M21: =VLOOKUP(K21,'2.masterfirm'!A:D,3,0) -> Australian/Nz Bank | N21: =VLOOKUP(K21,'2.masterfirm'!A:D,4,0) -> Financial Sector | O21: =IFERROR(VLOOKUP(K21,'1.master_list_7May'!C:K,9,0),"") -> No records | P21: sustainability report
A22: 20 | B22: MIL0019_Climate_Related_Disclosures_2023.pdf | C22: 10 | D22: 54770 | E22: 8398 | F22: 0.067 | G22: 0.844 | H22: 0.089 | I22: 0.9995 | J22: Readable | K22: MILLENNIUM & COPTHORNE HOTELS NEW ZEALAND LIMITED | L22: statement | M22: =VLOOKUP(K22,'2.masterfirm'!A:D,3,0) -> Hotel/Restaurant/Tourism | N22: =VLOOKUP(K22,'2.masterfirm'!A:D,4,0) -> Industry | O22: =IFERROR(VLOOKUP(K22,'1.master_list_7May'!C:K,9,0),"") -> Have records and have submitted | P22: climate statement
A23: 21 | B23: NZL Climate Related Disclosure.pdf | C23: 25 | D23: 52765 | E23: 7687 | F23: 0.051 | G23: 0.851 | H23: 0.098 | I23: 0.9998 | J23: Readable | K23: NEW ZEALAND RURAL LAND COMPANY LIMITED | L23: statement | M23: =VLOOKUP(K23,'2.masterfirm'!A:D,3,0) -> Property | N23: =VLOOKUP(K23,'2.masterfirm'!A:D,4,0) -> Industry | O23: =IFERROR(VLOOKUP(K23,'1.master_list_7May'!C:K,9,0),"") -> Have records but not submitted | P23: climate statement
A24: 22 | B24: nzm-cs-dec-2023.pdf | C24: 17 | D24: 70467 | E24: 11581 | F24: 0.081 | G24: 0.842 | H24: 0.077 | I24: 0.4716 | J24: Readable | K24: THE HONGKONG AND SHANGHAI BANKING CORPORATION LIMITED | L24: statement | M24: =VLOOKUP(K24,'2.masterfirm'!A:D,3,0) -> Foreign Bank | N24: =VLOOKUP(K24,'2.masterfirm'!A:D,4,0) -> Financial Sector | O24: =IFERROR(VLOOKUP(K24,'1.master_list_7May'!C:K,9,0),"") -> Have records but not submitted | P24: climate statement
A25: 23 | B25: NZME Annual Report 2023 (including climate statement).pdf | C25: 128 | D25: 271200 | E25: 38671 | F25: 0.042 | G25: 0.821 | H25: 0.138 | I25: 1 | J25: Readable | K25: NZME LIMITED | L25: statement | M25: =VLOOKUP(K25,'2.masterfirm'!A:D,3,0) -> Technology | N25: =VLOOKUP(K25,'2.masterfirm'!A:D,4,0) -> Industry | O25: =IFERROR(VLOOKUP(K25,'1.master_list_7May'!C:K,9,0),"") -> Have records and have submitted | P25: Annual report
A26: 24 | B26: NZX Annual Report 2023 (including climate statement).pdf | C26: 172 | D26: 458948 | E26: 64966 | F26: 0.044 | G26: 0.83 | H26: 0.126 | I26: 1 | J26: Readable | K26: NZX LIMITED | L26: statement | M26: =VLOOKUP(K26,'2.masterfirm'!A:D,3,0) -> Finance/Investment | N26: =VLOOKUP(K26,'2.masterfirm'!A:D,4,0) -> Financial Sector | O26: =IFERROR(VLOOKUP(K26,'1.master_list_7May'!C:K,9,0),"") -> Have records and have submitted | P26: Annual report
A27: 25 | B27: QBE_NZ Climate Statement.pdf | C27: 20 | D27: 51781 | E27: 7404 | F27: 0.066 | G27: 0.842 | H27: 0.091 | I27: 0.9992 | J27: Readable | K27: QBE INSURANCE (AUSTRALIA) LIMITED | L27: statement | M27: =VLOOKUP(K27,'2.masterfirm'!A:D,3,0) -> Insurance | N27: =VLOOKUP(K27,'2.masterfirm'!A:D,4,0) -> Financial Sector | O27: =IFERROR(VLOOKUP(K27,'1.master_list_7May'!C:K,9,0),"") -> Have records but not submitted | P27: climate statement
A28: 26 | B28: Rabobank New Zealand Banking Group 2023 Climate Statements.pdf | J28: Nonreadable | K28: RABOBANK NEW ZEALAND LIMITED | L28: statement | M28: =VLOOKUP(K28,'2.masterfirm'!A:D,3,0) -> Australian/Nz Bank | N28: =VLOOKUP(K28,'2.masterfirm'!A:D,4,0) -> Financial Sector | O28: =IFERROR(VLOOKUP(K28,'1.master_list_7May'!C:K,9,0),"") -> Have records but not submitted | P28: climate statement
A29: 27 | B29: Rabobank New Zealand Limited 2023 Climate Statements.pdf | J29: Nonreadable | K29: RABOBANK NEW ZEALAND LIMITED | L29: statement | M29: =VLOOKUP(K29,'2.masterfirm'!A:D,3,0) -> Australian/Nz Bank | N29: =VLOOKUP(K29,'2.masterfirm'!A:D,4,0) -> Financial Sector | O29: =IFERROR(VLOOKUP(K29,'1.master_list_7May'!C:K,9,0),"") -> Have records but not submitted | P29: climate statement
A30: 28 | B30: RBD 2023 CRD.pdf | C30: 36 | D30: 48482 | E30: 7591 | F30: 0.075 | G30: 0.849 | H30: 0.076 | I30: 0.9923 | J30: Readable | K30: RESTAURANT BRANDS NEW ZEALAND LIMITED | L30: statement | M30: =VLOOKUP(K30,'2.masterfirm'!A:D,3,0) -> Hotel/Restaurant/Tourism | N30: =VLOOKUP(K30,'2.masterfirm'!A:D,4,0) -> Industry | O30: =IFERROR(VLOOKUP(K30,'1.master_list_7May'!C:K,9,0),"") -> Have records but not submitted | P30: climate statement
A31: 29 | B31: Resilient infrastructure for a decarbonising world (7) - FINAL 28.02.24 9.30pm.pdf | C31: 125 | D31: 223771 | E31: 31511 | F31: 0.055 | G31: 0.833 | H31: 0.113 | I31: 1 | J31: Readable | K31: CHANNEL INFRASTRUCTURE NZ LIMITED | L31: statement | M31: =VLOOKUP(K31,'2.masterfirm'!A:D,3,0) -> Airport/Infrastructure | N31: =VLOOKUP(K31,'2.masterfirm'!A:D,4,0) -> Industry | O31: =IFERROR(VLOOKUP(K31,'1.master_list_7May'!C:K,9,0),"") -> Have records and have submitted | P31: sustainability report
A32: 30 | B32: RLAL-NZ Climate-Related Disclosures 2023.pdf | C32: 28 | D32: 71724 | E32: 10131 | F32: 0.091 | G32: 0.805 | H32: 0.104 | I32: 0.9995 | J32: Readable | K32: RESOLUTION LIFE AUSTRALASIA LIMITED | L32: statement | M32: =VLOOKUP(K32,'2.masterfirm'!A:D,3,0) -> Finance/Investment | N32: =VLOOKUP(K32,'2.masterfirm'!A:D,4,0) -> Financial Sector | O32: =IFERROR(VLOOKUP(K32,'1.master_list_7May'!C:K,9,0),"") -> Have records but not submitted | P32: climate statement
A33: 31 | B33: SC9600 Climate Related Disclosure Final Copy.pdf | C33: 31 | D33: 77210 | E33: 10621 | F33: 0.089 | G33: 0.837 | H33: 0.074 | I33: -0.998 | J33: Readable | K33: SCALES CORPORATION LIMITED | L33: statement | M33: =VLOOKUP(K33,'2.masterfirm'!A:D,3,0) -> Food/Agriculture | N33: =VLOOKUP(K33,'2.masterfirm'!A:D,4,0) -> Industry | O33: =IFERROR(VLOOKUP(K33,'1.master_list_7May'!C:K,9,0),"") -> Have records but not submitted | P33: climate statement
A34: 32 | B34: Seeka Limited Climate Disclosure 2023.pdf | C34: 15 | D34: 60497 | E34: 7155 | F34: 0.064 | G34: 0.854 | H34: 0.083 | I34: 0.9993 | J34: Readable | K34: SEEKA LIMITED | L34: statement | M34: =VLOOKUP(K34,'2.masterfirm'!A:D,3,0) -> Food/Agriculture | N34: =VLOOKUP(K34,'2.masterfirm'!A:D,4,0) -> Industry | O34: =IFERROR(VLOOKUP(K34,'1.master_list_7May'!C:K,9,0),"") -> Have records and have submitted | P34: climate statement
A35: 33 | B35: SRLHA NZ CRD Statement_signed.pdf | C35: 20 | D35: 76 | E35: 1 | F35: 0 | G35: 1 | H35: 0 | I35: 0 | J35: Readable | K35: SWISS RE LIFE & HEALTH AUSTRALIA LIMITED | L35: statement | M35: =VLOOKUP(K35,'2.masterfirm'!A:D,3,0) -> Insurance | N35: =VLOOKUP(K35,'2.masterfirm'!A:D,4,0) -> Financial Sector | O35: =IFERROR(VLOOKUP(K35,'1.master_list_7May'!C:K,9,0),"") -> Have records but not submitted | P35: climate statement
A36: 34 | B36: Sustainability Review & Climate Related Disclosures - FY23.pdf | C36: 40 | D36: 117337 | E36: 16966 | F36: 0.063 | G36: 0.794 | H36: 0.144 | I36: 1 | J36: Readable | K36: SUMMERSET GROUP HOLDINGS LIMITED | L36: statement | M36: =VLOOKUP(K36,'2.masterfirm'!A:D,3,0) -> Age Care | N36: =VLOOKUP(K36,'2.masterfirm'!A:D,4,0) -> Real Estate | O36: =IFERROR(VLOOKUP(K36,'1.master_list_7May'!C:K,9,0),"") -> Have records and have submitted | P36: climate statement
A37: 35 | B37: TGG_ClimateRelatedDisclosure.pdf | C37: 23 | D37: 70344 | E37: 9642 | F37: 0.064 | G37: 0.798 | H37: 0.138 | I37: 1 | J37: Readable | K37: TURNERS AUTOMOTIVE GROUP LIMITED | L37: statement | M37: =VLOOKUP(K37,'2.masterfirm'!A:D,3,0) -> Manufacturing | N37: =VLOOKUP(K37,'2.masterfirm'!A:D,4,0) -> Industry | O37: =IFERROR(VLOOKUP(K37,'1.master_list_7May'!C:K,9,0),"") -> Have records but not submitted | P37: climate statement
A38: 36 | B38: Ventia - 2023 Sustainability Report.pdf | C38: 80 | D38: 198465 | E38: 28258 | F38: 0.035 | G38: 0.774 | H38: 0.19 | I38: 1 | J38: Readable | K38: VENTIA SERVICES GROUP LIMITED | L38: statement | M38: =VLOOKUP(K38,'2.masterfirm'!A:D,3,0) -> Airport/Infrastructure | N38: =VLOOKUP(K38,'2.masterfirm'!A:D,4,0) -> Industry | O38: =IFERROR(VLOOKUP(K38,'1.master_list_7May'!C:K,9,0),"") -> Have records but not submitted | P38: sustainability report
A39: 37 | B39: Vista Group 2023 Group Climate Statement.pdf | C39: 31 | D39: 59162 | E39: 8181 | F39: 0.065 | G39: 0.845 | H39: 0.09 | I39: 0.9997 | J39: Readable | K39: VISTA GROUP INTERNATIONAL LIMITED | L39: statement | M39: =VLOOKUP(K39,'2.masterfirm'!A:D,3,0) -> Technology | N39: =VLOOKUP(K39,'2.masterfirm'!A:D,4,0) -> Industry | O39: =IFERROR(VLOOKUP(K39,'1.master_list_7May'!C:K,9,0),"") -> Have records but not submitted | P39: climate statement
A40: 38 | B40: Z Climate Statements 2023 - FINAL.pdf | C40: 25 | D40: 126445 | E40: 17906 | F40: 0.071 | G40: 0.81 | H40: 0.119 | I40: 1 | J40: Readable | K40: Z ENERGY LIMITED | L40: statement | M40: =VLOOKUP(K40,'2.masterfirm'!A:D,3,0) -> Energy | N40: =VLOOKUP(K40,'2.masterfirm'!A:D,4,0) -> Energy | O40: =IFERROR(VLOOKUP(K40,'1.master_list_7May'!C:K,9,0),"") -> Have records and have submitted | P40: climate statement

Sheet Sheet2
A1: PROPERTY FOR INDUSTRY LIMITED
A2: CITIBANK, N.A.
A3: AIA NEW ZEALAND LIMITED
A4: ANZ NEW ZEALAND INVESTMENTS LIMITED
A5: ASB BANK LIMITED
A6: BANK OF CHINA (NEW ZEALAND) LIMITED
A7: BNZ INVESTMENT SERVICES LIMITED
A8: BRISCOE GROUP LIMITED
A9: CHINA CONSTRUCTION BANK (NEW ZEALAND) LIMITED
A10: CDL INVESTMENTS NEW ZEALAND LIMITED
A11: CHUBB LIFE INSURANCE NEW ZEALAND LIMITED
A12: WESTPAC
... A33: Z ENERGY LIMITED

Sheet Sheet1
A1: PROPERTY FOR INDUSTRY LIMITED
A2: CITIBANK, N.A.
A3: AIA NEW ZEALAND LIMITED
A4: ANZ NEW ZEALAND INVESTMENTS LIMITED
A5: ASB BANK LIMITED
A6: BANK OF CHINA (NEW ZEALAND) LIMITED
A7: BNZ INVESTMENT SERVICES LIMITED
A8: BRISCOE GROUP LIMITED
A9: CHINA CONSTRUCTION BANK (NEW ZEALAND) LIMITED
A10: CDL INVESTMENTS NEW ZEALAND LIMITED
A11: CHUBB LIFE INSURANCE NEW ZEALAND LIMITED
A12: WESTPAC
... A33: Z ENERGY LIMITED

Sheet 4.pdf_list
A1: file_name | B1: Company Name | C1: RealStatement | D1: Addiitonal | E1: Category
A2: AIA NZ Climate Related Disclosers Report FINAL_signed.pdf | B2: AIA NEW ZEALAND LIMITED | E2: Climate Statement
A3: ANZ_climate-report-2023.pdf | B3: ANZ NEW ZEALAND INVESTMENTS LIMITED | D3: Yes | E3: Climate Statement
A4: asb-climate-report-2022.pdf | B4: ASB BANK LIMITED | D4: Yes | E4: Climate Statement
A5: Bank of China (New Zealand) Limited Climate Related Disclosure for the year ended 31 December 2023.pdf | B5: BANK OF CHINA (NEW ZEALAND) LIMITED | E5: Climate Statement
A6: Bank of China New Zealand Banking Group Climate Related Disclosure for the year ended 31 December 2023.pdf.pdf | B6: BANK OF CHINA (NEW ZEALAND) LIMITED | E6: Climate Statement
A7: BNZ_2023-Climate-Report.pdf | B7: BNZ INVESTMENT SERVICES LIMITED | D7: Yes | E7: Climate Statement
A8: Briscoe Group 2024 Annual Report.pdf | B8: BRISCOE GROUP LIMITED | E8: Annual Report
A9: CDL0017_Climate_Related_Disclosures_2023.pdf | B9: CDL INVESTMENTS NEW ZEALAND LIMITED | E9: Climate Statement
A10: Resilient infrastructure for a decarbonising world (7) - FINAL 28.02.24 9.30pm.pdf | B10: CHANNEL INFRASTRUCTURE NZ LIMITED | E10: Sustainability Report
A11: CCBNZL Climate Report for the year ended 31 December 2023.pdf | B11: CHINA CONSTRUCTION BANK (NEW ZEALAND) LIMITED | E11: Climate Statement
A12: CCBNZBG Climate Report for the year ended 31 December 2023.pdf | B12: CHINA CONSTRUCTION BANK CORPORATION | E12: Climate Statement
A13: Chubb Life Insurance New Zealand Limited Climate Disclosure 2023.pdf | B13: CHUBB LIFE INSURANCE NEW ZEALAND LIMITED | E13: Climate Statement
A14: 2023 Climate Statements for Citibank N.A. (New Zealand Branch).pdf | B14: CITIBANK, N.A. | E14: Climate Statement
A15: Citibank N.A. (New Zealand Branch) - Statement - 29 APRIL 2024 .pdf | B15: CITIBANK, N.A. | C15: letter
A16: Rabobank New Zealand Banking Group 2023 Climate Statements.pdf | B16: COOPERATIEVE RABOBANK U.A. | E16: Climate Statement
A17: ICBC NZ Ltd CRD 31 Dec 2023.pdf | B17: INDUSTRIAL AND COMMERCIAL BANK OF CHINA (NEW ZEALAND) LIMITED | E17: Climate Statement
A18: ICBC Ltd CRD 31 Dec 23 Final - For submission.pdf | B18: INDUSTRIAL AND COMMERCIAL BANK OF CHINA LIMITED | E18: Climate Statement
A19: kiwibank_sustainability_report2023.pdf | B19: KIWIBANK LIMITED | D19: Yes | E19: Sustainability Report
A20: MIL0019_Climate_Related_Disclosures_2023.pdf | B20: MILLENNIUM & COPTHORNE HOTELS NEW ZEALAND LIMITED | E20: Climate Statement
A21: NZL Climate Related Disclosure.pdf | B21: NEW ZEALAND RURAL LAND COMPANY LIMITED | E21: Climate Statement
A22: NZME Annual Report 2023 (including climate statement).pdf | B22: NZME LIMITED | E22: Annual Report
A23: NZX Annual Report 2023 (including climate statement).pdf | B23: NZX LIMITED | E23: Annual Report
A24: 2023 12 31 - PFI - Climate-related Disclosures - Signed.pdf | B24: PROPERTY FOR INDUSTRY LIMITED | E24: Climate Statement
A25: QBE_NZ Climate Statement.pdf | B25: QBE INSURANCE (AUSTRALIA) LIMITED | E25: Climate Statement
A26: Rabobank New Zealand Limited 2023 Climate Statements.pdf | B26: RABOBANK NEW ZEALAND LIMITED | E26: Climate Statement
A27: CRD 2023 CEO Declaration.pdf | B27: RESOLUTION LIFE AUSTRALASIA LIMITED | C27: letter
A28: RLAL-NZ Climate-Related Disclosures 2023.pdf | B28: RESOLUTION LIFE AUSTRALASIA LIMITED | E28: Climate Statement
A29: RBD 2023 CRD.pdf | B29: RESTAURANT BRANDS NEW ZEALAND LIMITED | E29: Climate Statement
A30: SC9600 Climate Related Disclosure Final Copy.pdf | B30: SCALES CORPORATION LIMITED | E30: Climate Statement
A31: Seeka Limited Climate Disclosure 2023.pdf | B31: SEEKA LIMITED | E31: Climate Statement
A32: Sustainability Review & Climate Related Disclosures - FY23.pdf | B32: SUMMERSET GROUP HOLDINGS LIMITED | E32: Climate Statement
A33: SRLHA NZ CRD Statement_signed.pdf | B33: SWISS RE LIFE & HEALTH AUSTRALIA LIMITED | C33: letter/inreadable | E33: Climate Statement
A34: TGG_ClimateRelatedDisclosure.pdf | B34: T&G GLOBAL LIMITED | E34: Climate Statement
A35: nzm-cs-dec-2023.pdf | B35: THE HONGKONG AND SHANGHAI BANKING CORPORATION LIMITED | E35: Climate Statement
A36: HSBC NZ 2023 Climate Statement lodgement letter - signed.pdf | B36: THE HONGKONG AND SHANGHAI BANKING CORPORATION LIMITED | C36: letter | E36: Climate Statement
A37: Ventia - 2023 Sustainability Report.pdf | B37: VENTIA SERVICES GROUP LIMITED | E37: Sustainability Report
A38: Vista Group 2023 Group Climate Statement.pdf | B38: VISTA GROUP INTERNATIONAL LIMITED | E38: Climate Statement
A39: Climate-Report-2023-Westpac-NZ.pdf | B39: Westpac | D39: Yes | E39: Climate Statement
A40: Z Climate Statements 2023 - FINAL.pdf | B40: Z ENERGY LIMITED | E40: Climate Statement
